Workbook

Sheet 仕訳帳 
A1: 2026 | B1: 年
E2: 簡 単 仕 訳 帳 | L2: 元帳兼仕訳帳 | P2: 元帳兼精算表
L3: 501 | M3: 502 | N3: 503 | O3: 504 | P3: 505 | Q3: 506 | R3: 507 | S3: 508 | T3: 509 | U3: 510 | V3: 511 | W3: 512 | X3: 513 | Y3: 514 | Z3: 515 | AA3: 516 | AB3: 517 | AC3: 518 | AD3: 519 | AE3: 520 | AF3: 521 | AG3: 522 | AH3: 523 | AI3: 524 | AJ3: 525 | AK3: 526 | AL3: 530 | AM3: 401 | AN3: 402 | AO3: 403 | AP3: 101 | AQ3: 102 | AR3: 103 | AS3: 104 | AT3: 105 | AU3: 106 | AV3: 107 | AW3: 108 | AX3: 109 | AY3: 110 | AZ3: 111 | BA3: 112 | BB3: 113 | BC3: 114 | BD3: 121 | BE3: 122 | BF3: 123 | BG3: 124 | BH3: 125 | BI3: 126 | BJ3: 127 | BK3: 128 | BL3: 201 | BM3: 202 | BN3: 203 | BO3: 204 | BP3: 205 | BQ3: 206 | BR3: 207 | BS3: 208 | BT3: 209 | BU3: 301 | BV3: 302
A4: 伝票№ | B4: 月 | C4: 日 | D4: 摘要 | E4: ｺｰﾄﾞ | F4: 借方科目 | G4: 金額 | H4: ｺｰﾄﾞ2 | I4: 貸方科目 | J4: 金額3 | L4: =IF(L$3="","",IF(ISNA(VLOOKUP(L$3,科目コード表!$C$4:$D$67,2,FALSE)),"該当科目なし",VLOOKUP(L$3,科目コード表!$C$4:$D$67,2,FALSE))) | M4: =IF(M$3="","",IF(ISNA(VLOOKUP(M$3,科目コード表!$C$4:$D$67,2,FALSE)),"該当科目なし",VLOOKUP(M$3,科目コード表!$C$4:$D$67,2,FALSE))) | N4: =IF(N$3="","",IF(ISNA(VLOOKUP(N$3,科目コード表!$C$4:$D$67,2,FALSE)),"該当科目なし",VLOOKUP(N$3,科目コード表!$C$4:$D$67,2,FALSE))) | O4: =IF(O$3="","",IF(ISNA(VLOOKUP(O$3,科目コード表!$C$4:$D$67,2,FALSE)),"該当科目なし",VLOOKUP(O$3,科目コード表!$C$4:$D$67,2,FALSE))) | P4: =IF(P$3="","",IF(ISNA(VLOOKUP(P$3,科目コード表!$C$4:$D$67,2,FALSE)),"該当科目なし",VLOOKUP(P$3,科目コード表!$C$4:$D$67,2,FALSE))) | Q4: =IF(Q$3="","",IF(ISNA(VLOOKUP(Q$3,科目コード表!$C$4:$D$67,2,FALSE)),"該当科目なし",VLOOKUP(Q$3,科目コード表!$C$4:$D$67,2,FALSE))) | R4: =IF(R$3="","",IF(ISNA(VLOOKUP(R$3,科目コード表!$C$4:$D$67,2,FALSE)),"該当科目なし",VLOOKUP(R$3,科目コード表!$C$4:$D$67,2,FALSE))) | S4: =IF(S$3="","",IF(ISNA(VLOOKUP(S$3,科目コード表!$C$4:$D$67,2,FALSE)),"該当科目なし",VLOOKUP(S$3,科目コード表!$C$4:$D$67,2,FALSE))) | ... BV4: =IF(BV$3="","",IF(ISNA(VLOOKUP(BV$3,科目コード表!$C$4:$D$67,2,FALSE)),"該当科目なし",VLOOKUP(BV$3,科目コード表!$C$4:$D$67,2,FALSE)))
B5: 1 | C5: 1 | D5: 前年繰越 現金 | E5: 101 | F5: =IF(E5="","",IF(ISNA(VLOOKUP(E5,科目コード表!$C$4:$D$67,2,FALSE)),"該当科目なし",VLOOKUP(E5,科目コード表!$C$4:$D$67,2,FALSE))) | G5: 1046520 | I5: =IF(H5="","",IF(ISNA(VLOOKUP(H5,科目コード表!$C$4:$D$67,2,FALSE)),"該当科目なし",VLOOKUP(H5,科目コード表!$C$4:$D$67,2,FALSE))) | L5: =IF($E5=L$3,$G5,0)-IF($H5=L$3,$J5,0) | M5: =IF($E5=M$3,$G5,0)-IF($H5=M$3,$J5,0) | N5: =IF($E5=N$3,$G5,0)-IF($H5=N$3,$J5,0) | O5: =IF($E5=O$3,$G5,0)-IF($H5=O$3,$J5,0) | P5: =IF($E5=P$3,$G5,0)-IF($H5=P$3,$J5,0) | Q5: =IF($E5=Q$3,$G5,0)-IF($H5=Q$3,$J5,0) | R5: =IF($E5=R$3,$G5,0)-IF($H5=R$3,$J5,0) | S5: =IF($E5=S$3,$G5,0)-IF($H5=S$3,$J5,0) | ... AL5: =IF($E5=AL$3,$G5,0)-IF($H5=AL$3,$J5,0) | AM5: =-IF($E5=AM$3,$G5,0)+IF($H5=AM$3,$J5,0) | AN5: =-IF($E5=AN$3,$G5,0)+IF($H5=AN$3,$J5,0) | AO5: =-IF($E5=AO$3,$G5,0)+IF($H5=AO$3,$J5,0) | AP5: =IF($E5=AP$3,$G5,0)-IF($H5=AP$3,$J5,0) | AQ5: =IF($E5=AQ$3,$G5,0)-IF($H5=AQ$3,$J5,0) | AR5: =IF($E5=AR$3,$G5,0)-IF($H5=AR$3,$J5,0) | AS5: =IF($E5=AS$3,$G5,0)-IF($H5=AS$3,$J5,0) | AT5: =IF($E5=AT$3,$G5,0)-IF($H5=AT$3,$J5,0) | AU5: =IF($E5=AU$3,$G5,0)-IF($H5=AU$3,$J5,0) | AV5: =IF($E5=AV$3,$G5,0)-IF($H5=AV$3,$J5,0) | AW5: =IF($E5=AW$3,$G5,0)-IF($H5=AW$3,$J5,0) | ... BK5: =IF($E5=BK$3,$G5,0)-IF($H5=BK$3,$J5,0) | BL5: =-IF($E5=BL$3,$G5,0)+IF($H5=BL$3,$J5,0) | BM5: =-IF($E5=BM$3,$G5,0)+IF($H5=BM$3,$J5,0) | BN5: =-IF($E5=BN$3,$G5,0)+IF($H5=BN$3,$J5,0) | BO5: =-IF($E5=BO$3,$G5,0)+IF($H5=BO$3,$J5,0) | BP5: =-IF($E5=BP$3,$G5,0)+IF($H5=BP$3,$J5,0) | BQ5: =-IF($E5=BQ$3,$G5,0)+IF($H5=BQ$3,$J5,0) | BR5: =-IF($E5=BR$3,$G5,0)+IF($H5=BR$3,$J5,0) | BS5: =-IF($E5=BS$3,$G5,0)+IF($H5=BS$3,$J5,0) | BT5: =-IF($E5=BT$3,$G5,0)+IF($H5=BT$3,$J5,0) | BU5: =+G5-J5 | BV5: =-IF($E5=BV$3,$G5,0)+IF($H5=BV$3,$J5,0)
B6: 1 | C6: 1 | D6: 前年繰越 売掛金 | E6: 107 | F6: =IF(E6="","",IF(ISNA(VLOOKUP(E6,科目コード表!$C$4:$D$67,2,FALSE)),"該当科目なし",VLOOKUP(E6,科目コード表!$C$4:$D$67,2,FALSE))) | G6: 1370500 | I6: =IF(H6="","",IF(ISNA(VLOOKUP(H6,科目コード表!$C$4:$D$67,2,FALSE)),"該当科目なし",VLOOKUP(H6,科目コード表!$C$4:$D$67,2,FALSE))) | L6: =IF($E6=L$3,$G6,0)-IF($H6=L$3,$J6,0) | M6: =IF($E6=M$3,$G6,0)-IF($H6=M$3,$J6,0) | N6: =IF($E6=N$3,$G6,0)-IF($H6=N$3,$J6,0) | O6: =IF($E6=O$3,$G6,0)-IF($H6=O$3,$J6,0) | P6: =IF($E6=P$3,$G6,0)-IF($H6=P$3,$J6,0) | Q6: =IF($E6=Q$3,$G6,0)-IF($H6=Q$3,$J6,0) | R6: =IF($E6=R$3,$G6,0)-IF($H6=R$3,$J6,0) | S6: =IF($E6=S$3,$G6,0)-IF($H6=S$3,$J6,0) | ... AL6: =IF($E6=AL$3,$G6,0)-IF($H6=AL$3,$J6,0) | AM6: =-IF($E6=AM$3,$G6,0)+IF($H6=AM$3,$J6,0) | AN6: =-IF($E6=AN$3,$G6,0)+IF($H6=AN$3,$J6,0) | AO6: =-IF($E6=AO$3,$G6,0)+IF($H6=AO$3,$J6,0) | AP6: =IF($E6=AP$3,$G6,0)-IF($H6=AP$3,$J6,0) | AQ6: =IF($E6=AQ$3,$G6,0)-IF($H6=AQ$3,$J6,0) | AR6: =IF($E6=AR$3,$G6,0)-IF($H6=AR$3,$J6,0) | AS6: =IF($E6=AS$3,$G6,0)-IF($H6=AS$3,$J6,0) | AT6: =IF($E6=AT$3,$G6,0)-IF($H6=AT$3,$J6,0) | AU6: =IF($E6=AU$3,$G6,0)-IF($H6=AU$3,$J6,0) | AV6: =IF($E6=AV$3,$G6,0)-IF($H6=AV$3,$J6,0) | AW6: =IF($E6=AW$3,$G6,0)-IF($H6=AW$3,$J6,0) | ... BK6: =IF($E6=BK$3,$G6,0)-IF($H6=BK$3,$J6,0) | BL6: =-IF($E6=BL$3,$G6,0)+IF($H6=BL$3,$J6,0) | BM6: =-IF($E6=BM$3,$G6,0)+IF($H6=BM$3,$J6,0) | BN6: =-IF($E6=BN$3,$G6,0)+IF($H6=BN$3,$J6,0) | BO6: =-IF($E6=BO$3,$G6,0)+IF($H6=BO$3,$J6,0) | BP6: =-IF($E6=BP$3,$G6,0)+IF($H6=BP$3,$J6,0) | BQ6: =-IF($E6=BQ$3,$G6,0)+IF($H6=BQ$3,$J6,0) | BR6: =-IF($E6=BR$3,$G6,0)+IF($H6=BR$3,$J6,0) | BS6: =-IF($E6=BS$3,$G6,0)+IF($H6=BS$3,$J6,0) | BT6: =-IF($E6=BT$3,$G6,0)+IF($H6=BT$3,$J6,0) | BU6: =+G6-J6 | BV6: =-IF($E6=BV$3,$G6,0)+IF($H6=BV$3,$J6,0)
B7: 1 | C7: 1 | D7: 前年繰越 普通預金 | E7: 103 | F7: =IF(E7="","",IF(ISNA(VLOOKUP(E7,科目コード表!$C$4:$D$67,2,FALSE)),"該当科目なし",VLOOKUP(E7,科目コード表!$C$4:$D$67,2,FALSE))) | G7: 10475394 | I7: =IF(H7="","",IF(ISNA(VLOOKUP(H7,科目コード表!$C$4:$D$67,2,FALSE)),"該当科目なし",VLOOKUP(H7,科目コード表!$C$4:$D$67,2,FALSE))) | L7: =IF($E7=L$3,$G7,0)-IF($H7=L$3,$J7,0) | M7: =IF($E7=M$3,$G7,0)-IF($H7=M$3,$J7,0) | N7: =IF($E7=N$3,$G7,0)-IF($H7=N$3,$J7,0) | O7: =IF($E7=O$3,$G7,0)-IF($H7=O$3,$J7,0) | P7: =IF($E7=P$3,$G7,0)-IF($H7=P$3,$J7,0) | Q7: =IF($E7=Q$3,$G7,0)-IF($H7=Q$3,$J7,0) | R7: =IF($E7=R$3,$G7,0)-IF($H7=R$3,$J7,0) | S7: =IF($E7=S$3,$G7,0)-IF($H7=S$3,$J7,0) | ... AL7: =IF($E7=AL$3,$G7,0)-IF($H7=AL$3,$J7,0) | AM7: =-IF($E7=AM$3,$G7,0)+IF($H7=AM$3,$J7,0) | AN7: =-IF($E7=AN$3,$G7,0)+IF($H7=AN$3,$J7,0) | AO7: =-IF($E7=AO$3,$G7,0)+IF($H7=AO$3,$J7,0) | AP7: =IF($E7=AP$3,$G7,0)-IF($H7=AP$3,$J7,0) | AQ7: =IF($E7=AQ$3,$G7,0)-IF($H7=AQ$3,$J7,0) | AR7: =IF($E7=AR$3,$G7,0)-IF($H7=AR$3,$J7,0) | AS7: =IF($E7=AS$3,$G7,0)-IF($H7=AS$3,$J7,0) | AT7: =IF($E7=AT$3,$G7,0)-IF($H7=AT$3,$J7,0) | AU7: =IF($E7=AU$3,$G7,0)-IF($H7=AU$3,$J7,0) | AV7: =IF($E7=AV$3,$G7,0)-IF($H7=AV$3,$J7,0) | AW7: =IF($E7=AW$3,$G7,0)-IF($H7=AW$3,$J7,0) | ... BK7: =IF($E7=BK$3,$G7,0)-IF($H7=BK$3,$J7,0) | BL7: =-IF($E7=BL$3,$G7,0)+IF($H7=BL$3,$J7,0) | BM7: =-IF($E7=BM$3,$G7,0)+IF($H7=BM$3,$J7,0) | BN7: =-IF($E7=BN$3,$G7,0)+IF($H7=BN$3,$J7,0) | BO7: =-IF($E7=BO$3,$G7,0)+IF($H7=BO$3,$J7,0) | BP7: =-IF($E7=BP$3,$G7,0)+IF($H7=BP$3,$J7,0) | BQ7: =-IF($E7=BQ$3,$G7,0)+IF($H7=BQ$3,$J7,0) | BR7: =-IF($E7=BR$3,$G7,0)+IF($H7=BR$3,$J7,0) | BS7: =-IF($E7=BS$3,$G7,0)+IF($H7=BS$3,$J7,0) | BT7: =-IF($E7=BT$3,$G7,0)+IF($H7=BT$3,$J7,0) | BU7: =+G7-J7 | BV7: =-IF($E7=BV$3,$G7,0)+IF($H7=BV$3,$J7,0)
B8: 1 | C8: 1 | D8: 前年繰越 建物 | E8: 121 | F8: =IF(E8="","",IF(ISNA(VLOOKUP(E8,科目コード表!$C$4:$D$67,2,FALSE)),"該当科目なし",VLOOKUP(E8,科目コード表!$C$4:$D$67,2,FALSE))) | G8: 14597430 | I8: =IF(H8="","",IF(ISNA(VLOOKUP(H8,科目コード表!$C$4:$D$67,2,FALSE)),"該当科目なし",VLOOKUP(H8,科目コード表!$C$4:$D$67,2,FALSE))) | L8: =IF($E8=L$3,$G8,0)-IF($H8=L$3,$J8,0) | M8: =IF($E8=M$3,$G8,0)-IF($H8=M$3,$J8,0) | N8: =IF($E8=N$3,$G8,0)-IF($H8=N$3,$J8,0) | O8: =IF($E8=O$3,$G8,0)-IF($H8=O$3,$J8,0) | P8: =IF($E8=P$3,$G8,0)-IF($H8=P$3,$J8,0) | Q8: =IF($E8=Q$3,$G8,0)-IF($H8=Q$3,$J8,0) | R8: =IF($E8=R$3,$G8,0)-IF($H8=R$3,$J8,0) | S8: =IF($E8=S$3,$G8,0)-IF($H8=S$3,$J8,0) | ... AL8: =IF($E8=AL$3,$G8,0)-IF($H8=AL$3,$J8,0) | AM8: =-IF($E8=AM$3,$G8,0)+IF($H8=AM$3,$J8,0) | AN8: =-IF($E8=AN$3,$G8,0)+IF($H8=AN$3,$J8,0) | AO8: =-IF($E8=AO$3,$G8,0)+IF($H8=AO$3,$J8,0) | AP8: =IF($E8=AP$3,$G8,0)-IF($H8=AP$3,$J8,0) | AQ8: =IF($E8=AQ$3,$G8,0)-IF($H8=AQ$3,$J8,0) | AR8: =IF($E8=AR$3,$G8,0)-IF($H8=AR$3,$J8,0) | AS8: =IF($E8=AS$3,$G8,0)-IF($H8=AS$3,$J8,0) | AT8: =IF($E8=AT$3,$G8,0)-IF($H8=AT$3,$J8,0) | AU8: =IF($E8=AU$3,$G8,0)-IF($H8=AU$3,$J8,0) | AV8: =IF($E8=AV$3,$G8,0)-IF($H8=AV$3,$J8,0) | AW8: =IF($E8=AW$3,$G8,0)-IF($H8=AW$3,$J8,0) | ... BK8: =IF($E8=BK$3,$G8,0)-IF($H8=BK$3,$J8,0) | BL8: =-IF($E8=BL$3,$G8,0)+IF($H8=BL$3,$J8,0) | BM8: =-IF($E8=BM$3,$G8,0)+IF($H8=BM$3,$J8,0) | BN8: =-IF($E8=BN$3,$G8,0)+IF($H8=BN$3,$J8,0) | BO8: =-IF($E8=BO$3,$G8,0)+IF($H8=BO$3,$J8,0) | BP8: =-IF($E8=BP$3,$G8,0)+IF($H8=BP$3,$J8,0) | BQ8: =-IF($E8=BQ$3,$G8,0)+IF($H8=BQ$3,$J8,0) | BR8: =-IF($E8=BR$3,$G8,0)+IF($H8=BR$3,$J8,0) | BS8: =-IF($E8=BS$3,$G8,0)+IF($H8=BS$3,$J8,0) | BT8: =-IF($E8=BT$3,$G8,0)+IF($H8=BT$3,$J8,0) | BU8: =+G8-J8 | BV8: =-IF($E8=BV$3,$G8,0)+IF($H8=BV$3,$J8,0)
B9: 1 | C9: 1 | D9: 前年繰越 構築物 | E9: 127 | F9: =IF(E9="","",IF(ISNA(VLOOKUP(E9,科目コード表!$C$4:$D$67,2,FALSE)),"該当科目なし",VLOOKUP(E9,科目コード表!$C$4:$D$67,2,FALSE))) | G9: 1303020 | I9: =IF(H9="","",IF(ISNA(VLOOKUP(H9,科目コード表!$C$4:$D$67,2,FALSE)),"該当科目なし",VLOOKUP(H9,科目コード表!$C$4:$D$67,2,FALSE))) | L9: =IF($E9=L$3,$G9,0)-IF($H9=L$3,$J9,0) | M9: =IF($E9=M$3,$G9,0)-IF($H9=M$3,$J9,0) | N9: =IF($E9=N$3,$G9,0)-IF($H9=N$3,$J9,0) | O9: =IF($E9=O$3,$G9,0)-IF($H9=O$3,$J9,0) | P9: =IF($E9=P$3,$G9,0)-IF($H9=P$3,$J9,0) | Q9: =IF($E9=Q$3,$G9,0)-IF($H9=Q$3,$J9,0) | R9: =IF($E9=R$3,$G9,0)-IF($H9=R$3,$J9,0) | S9: =IF($E9=S$3,$G9,0)-IF($H9=S$3,$J9,0) | ... AL9: =IF($E9=AL$3,$G9,0)-IF($H9=AL$3,$J9,0) | AM9: =-IF($E9=AM$3,$G9,0)+IF($H9=AM$3,$J9,0) | AN9: =-IF($E9=AN$3,$G9,0)+IF($H9=AN$3,$J9,0) | AO9: =-IF($E9=AO$3,$G9,0)+IF($H9=AO$3,$J9,0) | AP9: =IF($E9=AP$3,$G9,0)-IF($H9=AP$3,$J9,0) | AQ9: =IF($E9=AQ$3,$G9,0)-IF($H9=AQ$3,$J9,0) | AR9: =IF($E9=AR$3,$G9,0)-IF($H9=AR$3,$J9,0) | AS9: =IF($E9=AS$3,$G9,0)-IF($H9=AS$3,$J9,0) | AT9: =IF($E9=AT$3,$G9,0)-IF($H9=AT$3,$J9,0) | AU9: =IF($E9=AU$3,$G9,0)-IF($H9=AU$3,$J9,0) | AV9: =IF($E9=AV$3,$G9,0)-IF($H9=AV$3,$J9,0) | AW9: =IF($E9=AW$3,$G9,0)-IF($H9=AW$3,$J9,0) | ... BK9: =IF($E9=BK$3,$G9,0)-IF($H9=BK$3,$J9,0) | BL9: =-IF($E9=BL$3,$G9,0)+IF($H9=BL$3,$J9,0) | BM9: =-IF($E9=BM$3,$G9,0)+IF($H9=BM$3,$J9,0) | BN9: =-IF($E9=BN$3,$G9,0)+IF($H9=BN$3,$J9,0) | BO9: =-IF($E9=BO$3,$G9,0)+IF($H9=BO$3,$J9,0) | BP9: =-IF($E9=BP$3,$G9,0)+IF($H9=BP$3,$J9,0) | BQ9: =-IF($E9=BQ$3,$G9,0)+IF($H9=BQ$3,$J9,0) | BR9: =-IF($E9=BR$3,$G9,0)+IF($H9=BR$3,$J9,0) | BS9: =-IF($E9=BS$3,$G9,0)+IF($H9=BS$3,$J9,0) | BT9: =-IF($E9=BT$3,$G9,0)+IF($H9=BT$3,$J9,0) | BU9: =+G9-J9 | BV9: =-IF($E9=BV$3,$G9,0)+IF($H9=BV$3,$J9,0)
B10: 1 | C10: 1 | D10: 前年繰越 車両運搬具 | E10: 124 | F10: =IF(E10="","",IF(ISNA(VLOOKUP(E10,科目コード表!$C$4:$D$67,2,FALSE)),"該当科目なし",VLOOKUP(E10,科目コード表!$C$4:$D$67,2,FALSE))) | G10: 1 | I10: =IF(H10="","",IF(ISNA(VLOOKUP(H10,科目コード表!$C$4:$D$67,2,FALSE)),"該当科目なし",VLOOKUP(H10,科目コード表!$C$4:$D$67,2,FALSE))) | L10: =IF($E10=L$3,$G10,0)-IF($H10=L$3,$J10,0) | M10: =IF($E10=M$3,$G10,0)-IF($H10=M$3,$J10,0) | N10: =IF($E10=N$3,$G10,0)-IF($H10=N$3,$J10,0) | O10: =IF($E10=O$3,$G10,0)-IF($H10=O$3,$J10,0) | P10: =IF($E10=P$3,$G10,0)-IF($H10=P$3,$J10,0) | Q10: =IF($E10=Q$3,$G10,0)-IF($H10=Q$3,$J10,0) | R10: =IF($E10=R$3,$G10,0)-IF($H10=R$3,$J10,0) | S10: =IF($E10=S$3,$G10,0)-IF($H10=S$3,$J10,0) | ... AL10: =IF($E10=AL$3,$G10,0)-IF($H10=AL$3,$J10,0) | AM10: =-IF($E10=AM$3,$G10,0)+IF($H10=AM$3,$J10,0) | AN10: =-IF($E10=AN$3,$G10,0)+IF($H10=AN$3,$J10,0) | AO10: =-IF($E10=AO$3,$G10,0)+IF($H10=AO$3,$J10,0) | AP10: =IF($E10=AP$3,$G10,0)-IF($H10=AP$3,$J10,0) | AQ10: =IF($E10=AQ$3,$G10,0)-IF($H10=AQ$3,$J10,0) | AR10: =IF($E10=AR$3,$G10,0)-IF($H10=AR$3,$J10,0) | AS10: =IF($E10=AS$3,$G10,0)-IF($H10=AS$3,$J10,0) | AT10: =IF($E10=AT$3,$G10,0)-IF($H10=AT$3,$J10,0) | AU10: =IF($E10=AU$3,$G10,0)-IF($H10=AU$3,$J10,0) | AV10: =IF($E10=AV$3,$G10,0)-IF($H10=AV$3,$J10,0) | AW10: =IF($E10=AW$3,$G10,0)-IF($H10=AW$3,$J10,0) | ... BK10: =IF($E10=BK$3,$G10,0)-IF($H10=BK$3,$J10,0) | BL10: =-IF($E10=BL$3,$G10,0)+IF($H10=BL$3,$J10,0) | BM10: =-IF($E10=BM$3,$G10,0)+IF($H10=BM$3,$J10,0) | BN10: =-IF($E10=BN$3,$G10,0)+IF($H10=BN$3,$J10,0) | BO10: =-IF($E10=BO$3,$G10,0)+IF($H10=BO$3,$J10,0) | BP10: =-IF($E10=BP$3,$G10,0)+IF($H10=BP$3,$J10,0) | BQ10: =-IF($E10=BQ$3,$G10,0)+IF($H10=BQ$3,$J10,0) | BR10: =-IF($E10=BR$3,$G10,0)+IF($H10=BR$3,$J10,0) | BS10: =-IF($E10=BS$3,$G10,0)+IF($H10=BS$3,$J10,0) | BT10: =-IF($E10=BT$3,$G10,0)+IF($H10=BT$3,$J10,0) | BU10: =+G10-J10 | BV10: =-IF($E10=BV$3,$G10,0)+IF($H10=BV$3,$J10,0)
B11: 1 | C11: 1 | D11: 前年繰越 リサイクル預託金 | E11: 114 | F11: =IF(E11="","",IF(ISNA(VLOOKUP(E11,科目コード表!$C$4:$D$67,2,FALSE)),"該当科目なし",VLOOKUP(E11,科目コード表!$C$4:$D$67,2,FALSE))) | G11: 9130 | I11: =IF(H11="","",IF(ISNA(VLOOKUP(H11,科目コード表!$C$4:$D$67,2,FALSE)),"該当科目なし",VLOOKUP(H11,科目コード表!$C$4:$D$67,2,FALSE))) | L11: =IF($E11=L$3,$G11,0)-IF($H11=L$3,$J11,0) | M11: =IF($E11=M$3,$G11,0)-IF($H11=M$3,$J11,0) | N11: =IF($E11=N$3,$G11,0)-IF($H11=N$3,$J11,0) | O11: =IF($E11=O$3,$G11,0)-IF($H11=O$3,$J11,0) | P11: =IF($E11=P$3,$G11,0)-IF($H11=P$3,$J11,0) | Q11: =IF($E11=Q$3,$G11,0)-IF($H11=Q$3,$J11,0) | R11: =IF($E11=R$3,$G11,0)-IF($H11=R$3,$J11,0) | S11: =IF($E11=S$3,$G11,0)-IF($H11=S$3,$J11,0) | ... AL11: =IF($E11=AL$3,$G11,0)-IF($H11=AL$3,$J11,0) | AM11: =-IF($E11=AM$3,$G11,0)+IF($H11=AM$3,$J11,0) | AN11: =-IF($E11=AN$3,$G11,0)+IF($H11=AN$3,$J11,0) | AO11: =-IF($E11=AO$3,$G11,0)+IF($H11=AO$3,$J11,0) | AP11: =IF($E11=AP$3,$G11,0)-IF($H11=AP$3,$J11,0) | AQ11: =IF($E11=AQ$3,$G11,0)-IF($H11=AQ$3,$J11,0) | AR11: =IF($E11=AR$3,$G11,0)-IF($H11=AR$3,$J11,0) | AS11: =IF($E11=AS$3,$G11,0)-IF($H11=AS$3,$J11,0) | AT11: =IF($E11=AT$3,$G11,0)-IF($H11=AT$3,$J11,0) | AU11: =IF($E11=AU$3,$G11,0)-IF($H11=AU$3,$J11,0) | AV11: =IF($E11=AV$3,$G11,0)-IF($H11=AV$3,$J11,0) | AW11: =IF($E11=AW$3,$G11,0)-IF($H11=AW$3,$J11,0) | ... BK11: =IF($E11=BK$3,$G11,0)-IF($H11=BK$3,$J11,0) | BL11: =-IF($E11=BL$3,$G11,0)+IF($H11=BL$3,$J11,0) | BM11: =-IF($E11=BM$3,$G11,0)+IF($H11=BM$3,$J11,0) | BN11: =-IF($E11=BN$3,$G11,0)+IF($H11=BN$3,$J11,0) | BO11: =-IF($E11=BO$3,$G11,0)+IF($H11=BO$3,$J11,0) | BP11: =-IF($E11=BP$3,$G11,0)+IF($H11=BP$3,$J11,0) | BQ11: =-IF($E11=BQ$3,$G11,0)+IF($H11=BQ$3,$J11,0) | BR11: =-IF($E11=BR$3,$G11,0)+IF($H11=BR$3,$J11,0) | BS11: =-IF($E11=BS$3,$G11,0)+IF($H11=BS$3,$J11,0) | BT11: =-IF($E11=BT$3,$G11,0)+IF($H11=BT$3,$J11,0) | BU11: =+G11-J11 | BV11: =-IF($E11=BV$3,$G11,0)+IF($H11=BV$3,$J11,0)
B12: 1 | C12: 1 | D12: 前年繰越 未払金 | F12: =IF(E12="","",IF(ISNA(VLOOKUP(E12,科目コード表!$C$4:$D$67,2,FALSE)),"該当科目なし",VLOOKUP(E12,科目コード表!$C$4:$D$67,2,FALSE))) | H12: 204 | I12: =IF(H12="","",IF(ISNA(VLOOKUP(H12,科目コード表!$C$4:$D$67,2,FALSE)),"該当科目なし",VLOOKUP(H12,科目コード表!$C$4:$D$67,2,FALSE))) | J12: 61327 | L12: =IF($E12=L$3,$G12,0)-IF($H12=L$3,$J12,0) | M12: =IF($E12=M$3,$G12,0)-IF($H12=M$3,$J12,0) | N12: =IF($E12=N$3,$G12,0)-IF($H12=N$3,$J12,0) | O12: =IF($E12=O$3,$G12,0)-IF($H12=O$3,$J12,0) | P12: =IF($E12=P$3,$G12,0)-IF($H12=P$3,$J12,0) | Q12: =IF($E12=Q$3,$G12,0)-IF($H12=Q$3,$J12,0) | R12: =IF($E12=R$3,$G12,0)-IF($H12=R$3,$J12,0) | S12: =IF($E12=S$3,$G12,0)-IF($H12=S$3,$J12,0) | ... AL12: =IF($E12=AL$3,$G12,0)-IF($H12=AL$3,$J12,0) | AM12: =-IF($E12=AM$3,$G12,0)+IF($H12=AM$3,$J12,0) | AN12: =-IF($E12=AN$3,$G12,0)+IF($H12=AN$3,$J12,0) | AO12: =-IF($E12=AO$3,$G12,0)+IF($H12=AO$3,$J12,0) | AP12: =IF($E12=AP$3,$G12,0)-IF($H12=AP$3,$J12,0) | AQ12: =IF($E12=AQ$3,$G12,0)-IF($H12=AQ$3,$J12,0) | AR12: =IF($E12=AR$3,$G12,0)-IF($H12=AR$3,$J12,0) | AS12: =IF($E12=AS$3,$G12,0)-IF($H12=AS$3,$J12,0) | AT12: =IF($E12=AT$3,$G12,0)-IF($H12=AT$3,$J12,0) | AU12: =IF($E12=AU$3,$G12,0)-IF($H12=AU$3,$J12,0) | AV12: =IF($E12=AV$3,$G12,0)-IF($H12=AV$3,$J12,0) | AW12: =IF($E12=AW$3,$G12,0)-IF($H12=AW$3,$J12,0) | ... BK12: =IF($E12=BK$3,$G12,0)-IF($H12=BK$3,$J12,0) | BL12: =-IF($E12=BL$3,$G12,0)+IF($H12=BL$3,$J12,0) | BM12: =-IF($E12=BM$3,$G12,0)+IF($H12=BM$3,$J12,0) | BN12: =-IF($E12=BN$3,$G12,0)+IF($H12=BN$3,$J12,0) | BO12: =-IF($E12=BO$3,$G12,0)+IF($H12=BO$3,$J12,0) | BP12: =-IF($E12=BP$3,$G12,0)+IF($H12=BP$3,$J12,0) | BQ12: =-IF($E12=BQ$3,$G12,0)+IF($H12=BQ$3,$J12,0) | BR12: =-IF($E12=BR$3,$G12,0)+IF($H12=BR$3,$J12,0) | BS12: =-IF($E12=BS$3,$G12,0)+IF($H12=BS$3,$J12,0) | BT12: =-IF($E12=BT$3,$G12,0)+IF($H12=BT$3,$J12,0) | BU12: =+G12-J12 | BV12: =-IF($E12=BV$3,$G12,0)+IF($H12=BV$3,$J12,0)
B13: 1 | C13: 1 | D13: 前年繰越 元入金 | F13: =IF(E13="","",IF(ISNA(VLOOKUP(E13,科目コード表!$C$4:$D$67,2,FALSE)),"該当科目なし",VLOOKUP(E13,科目コード表!$C$4:$D$67,2,FALSE))) | H13: 302 | I13: =IF(H13="","",IF(ISNA(VLOOKUP(H13,科目コード表!$C$4:$D$67,2,FALSE)),"該当科目なし",VLOOKUP(H13,科目コード表!$C$4:$D$67,2,FALSE))) | J13: 25846530 | L13: =IF($E13=L$3,$G13,0)-IF($H13=L$3,$J13,0) | M13: =IF($E13=M$3,$G13,0)-IF($H13=M$3,$J13,0) | N13: =IF($E13=N$3,$G13,0)-IF($H13=N$3,$J13,0) | O13: =IF($E13=O$3,$G13,0)-IF($H13=O$3,$J13,0) | P13: =IF($E13=P$3,$G13,0)-IF($H13=P$3,$J13,0) | Q13: =IF($E13=Q$3,$G13,0)-IF($H13=Q$3,$J13,0) | R13: =IF($E13=R$3,$G13,0)-IF($H13=R$3,$J13,0) | S13: =IF($E13=S$3,$G13,0)-IF($H13=S$3,$J13,0) | ... AL13: =IF($E13=AL$3,$G13,0)-IF($H13=AL$3,$J13,0) | AM13: =-IF($E13=AM$3,$G13,0)+IF($H13=AM$3,$J13,0) | AN13: =-IF($E13=AN$3,$G13,0)+IF($H13=AN$3,$J13,0) | AO13: =-IF($E13=AO$3,$G13,0)+IF($H13=AO$3,$J13,0) | AP13: =IF($E13=AP$3,$G13,0)-IF($H13=AP$3,$J13,0) | AQ13: =IF($E13=AQ$3,$G13,0)-IF($H13=AQ$3,$J13,0) | AR13: =IF($E13=AR$3,$G13,0)-IF($H13=AR$3,$J13,0) | AS13: =IF($E13=AS$3,$G13,0)-IF($H13=AS$3,$J13,0) | AT13: =IF($E13=AT$3,$G13,0)-IF($H13=AT$3,$J13,0) | AU13: =IF($E13=AU$3,$G13,0)-IF($H13=AU$3,$J13,0) | AV13: =IF($E13=AV$3,$G13,0)-IF($H13=AV$3,$J13,0) | AW13: =IF($E13=AW$3,$G13,0)-IF($H13=AW$3,$J13,0) | ... BK13: =IF($E13=BK$3,$G13,0)-IF($H13=BK$3,$J13,0) | BL13: =-IF($E13=BL$3,$G13,0)+IF($H13=BL$3,$J13,0) | BM13: =-IF($E13=BM$3,$G13,0)+IF($H13=BM$3,$J13,0) | BN13: =-IF($E13=BN$3,$G13,0)+IF($H13=BN$3,$J13,0) | BO13: =-IF($E13=BO$3,$G13,0)+IF($H13=BO$3,$J13,0) | BP13: =-IF($E13=BP$3,$G13,0)+IF($H13=BP$3,$J13,0) | BQ13: =-IF($E13=BQ$3,$G13,0)+IF($H13=BQ$3,$J13,0) | BR13: =-IF($E13=BR$3,$G13,0)+IF($H13=BR$3,$J13,0) | BS13: =-IF($E13=BS$3,$G13,0)+IF($H13=BS$3,$J13,0) | BT13: =-IF($E13=BT$3,$G13,0)+IF($H13=BT$3,$J13,0) | BU13: =+G13-J13 | BV13: =-IF($E13=BV$3,$G13,0)+IF($H13=BV$3,$J13,0)
B14: 1 | C14: 1 | D14: 前年繰越 控除前利益 | F14: =IF(E14="","",IF(ISNA(VLOOKUP(E14,科目コード表!$C$4:$D$67,2,FALSE)),"該当科目なし",VLOOKUP(E14,科目コード表!$C$4:$D$67,2,FALSE))) | H14: 302 | I14: =IF(H14="","",IF(ISNA(VLOOKUP(H14,科目コード表!$C$4:$D$67,2,FALSE)),"該当科目なし",VLOOKUP(H14,科目コード表!$C$4:$D$67,2,FALSE))) | J14: 2894138 | L14: =IF($E14=L$3,$G14,0)-IF($H14=L$3,$J14,0) | M14: =IF($E14=M$3,$G14,0)-IF($H14=M$3,$J14,0) | N14: =IF($E14=N$3,$G14,0)-IF($H14=N$3,$J14,0) | O14: =IF($E14=O$3,$G14,0)-IF($H14=O$3,$J14,0) | P14: =IF($E14=P$3,$G14,0)-IF($H14=P$3,$J14,0) | Q14: =IF($E14=Q$3,$G14,0)-IF($H14=Q$3,$J14,0) | R14: =IF($E14=R$3,$G14,0)-IF($H14=R$3,$J14,0) | S14: =IF($E14=S$3,$G14,0)-IF($H14=S$3,$J14,0) | ... AL14: =IF($E14=AL$3,$G14,0)-IF($H14=AL$3,$J14,0) | AM14: =-IF($E14=AM$3,$G14,0)+IF($H14=AM$3,$J14,0) | AN14: =-IF($E14=AN$3,$G14,0)+IF($H14=AN$3,$J14,0) | AO14: =-IF($E14=AO$3,$G14,0)+IF($H14=AO$3,$J14,0) | AP14: =IF($E14=AP$3,$G14,0)-IF($H14=AP$3,$J14,0) | AQ14: =IF($E14=AQ$3,$G14,0)-IF($H14=AQ$3,$J14,0) | AR14: =IF($E14=AR$3,$G14,0)-IF($H14=AR$3,$J14,0) | AS14: =IF($E14=AS$3,$G14,0)-IF($H14=AS$3,$J14,0) | AT14: =IF($E14=AT$3,$G14,0)-IF($H14=AT$3,$J14,0) | AU14: =IF($E14=AU$3,$G14,0)-IF($H14=AU$3,$J14,0) | AV14: =IF($E14=AV$3,$G14,0)-IF($H14=AV$3,$J14,0) | AW14: =IF($E14=AW$3,$G14,0)-IF($H14=AW$3,$J14,0) | ... BK14: =IF($E14=BK$3,$G14,0)-IF($H14=BK$3,$J14,0) | BL14: =-IF($E14=BL$3,$G14,0)+IF($H14=BL$3,$J14,0) | BM14: =-IF($E14=BM$3,$G14,0)+IF($H14=BM$3,$J14,0) | BN14: =-IF($E14=BN$3,$G14,0)+IF($H14=BN$3,$J14,0) | BO14: =-IF($E14=BO$3,$G14,0)+IF($H14=BO$3,$J14,0) | BP14: =-IF($E14=BP$3,$G14,0)+IF($H14=BP$3,$J14,0) | BQ14: =-IF($E14=BQ$3,$G14,0)+IF($H14=BQ$3,$J14,0) | BR14: =-IF($E14=BR$3,$G14,0)+IF($H14=BR$3,$J14,0) | BS14: =-IF($E14=BS$3,$G14,0)+IF($H14=BS$3,$J14,0) | BT14: =-IF($E14=BT$3,$G14,0)+IF($H14=BT$3,$J14,0) | BU14: =+G14-J14 | BV14: =-IF($E14=BV$3,$G14,0)+IF($H14=BV$3,$J14,0)
B15: 1 | C15: 1 | D15: 振り戻し 未払金 | E15: 204 | F15: =IF(E15="","",IF(ISNA(VLOOKUP(E15,科目コード表!$C$4:$D$67,2,FALSE)),"該当科目なし",VLOOKUP(E15,科目コード表!$C$4:$D$67,2,FALSE))) | G15: 61327 | I15: =IF(H15="","",IF(ISNA(VLOOKUP(H15,科目コード表!$C$4:$D$67,2,FALSE)),"該当科目なし",VLOOKUP(H15,科目コード表!$C$4:$D$67,2,FALSE))) | L15: =IF($E15=L$3,$G15,0)-IF($H15=L$3,$J15,0) | M15: =IF($E15=M$3,$G15,0)-IF($H15=M$3,$J15,0) | N15: =IF($E15=N$3,$G15,0)-IF($H15=N$3,$J15,0) | O15: =IF($E15=O$3,$G15,0)-IF($H15=O$3,$J15,0) | P15: =IF($E15=P$3,$G15,0)-IF($H15=P$3,$J15,0) | Q15: =IF($E15=Q$3,$G15,0)-IF($H15=Q$3,$J15,0) | R15: =IF($E15=R$3,$G15,0)-IF($H15=R$3,$J15,0) | S15: =IF($E15=S$3,$G15,0)-IF($H15=S$3,$J15,0) | ... AL15: =IF($E15=AL$3,$G15,0)-IF($H15=AL$3,$J15,0) | AM15: =-IF($E15=AM$3,$G15,0)+IF($H15=AM$3,$J15,0) | AN15: =-IF($E15=AN$3,$G15,0)+IF($H15=AN$3,$J15,0) | AO15: =-IF($E15=AO$3,$G15,0)+IF($H15=AO$3,$J15,0) | AP15: =IF($E15=AP$3,$G15,0)-IF($H15=AP$3,$J15,0) | AQ15: =IF($E15=AQ$3,$G15,0)-IF($H15=AQ$3,$J15,0) | AR15: =IF($E15=AR$3,$G15,0)-IF($H15=AR$3,$J15,0) | AS15: =IF($E15=AS$3,$G15,0)-IF($H15=AS$3,$J15,0) | AT15: =IF($E15=AT$3,$G15,0)-IF($H15=AT$3,$J15,0) | AU15: =IF($E15=AU$3,$G15,0)-IF($H15=AU$3,$J15,0) | AV15: =IF($E15=AV$3,$G15,0)-IF($H15=AV$3,$J15,0) | AW15: =IF($E15=AW$3,$G15,0)-IF($H15=AW$3,$J15,0) | ... BK15: =IF($E15=BK$3,$G15,0)-IF($H15=BK$3,$J15,0) | BL15: =-IF($E15=BL$3,$G15,0)+IF($H15=BL$3,$J15,0) | BM15: =-IF($E15=BM$3,$G15,0)+IF($H15=BM$3,$J15,0) | BN15: =-IF($E15=BN$3,$G15,0)+IF($H15=BN$3,$J15,0) | BO15: =-IF($E15=BO$3,$G15,0)+IF($H15=BO$3,$J15,0) | BP15: =-IF($E15=BP$3,$G15,0)+IF($H15=BP$3,$J15,0) | BQ15: =-IF($E15=BQ$3,$G15,0)+IF($H15=BQ$3,$J15,0) | BR15: =-IF($E15=BR$3,$G15,0)+IF($H15=BR$3,$J15,0) | BS15: =-IF($E15=BS$3,$G15,0)+IF($H15=BS$3,$J15,0) | BT15: =-IF($E15=BT$3,$G15,0)+IF($H15=BT$3,$J15,0) | BU15: =+G15-J15 | BV15: =-IF($E15=BV$3,$G15,0)+IF($H15=BV$3,$J15,0)
B16: 1 | C16: 1 | D16: 現金を事業主へ戻し | F16: =IF(E16="","",IF(ISNA(VLOOKUP(E16,科目コード表!$C$4:$D$67,2,FALSE)),"該当科目なし",VLOOKUP(E16,科目コード表!$C$4:$D$67,2,FALSE))) | H16: 101 | I16: =IF(H16="","",IF(ISNA(VLOOKUP(H16,科目コード表!$C$4:$D$67,2,FALSE)),"該当科目なし",VLOOKUP(H16,科目コード表!$C$4:$D$67,2,FALSE))) | J16: 1046520 | L16: =IF($E16=L$3,$G16,0)-IF($H16=L$3,$J16,0) | M16: =IF($E16=M$3,$G16,0)-IF($H16=M$3,$J16,0) | N16: =IF($E16=N$3,$G16,0)-IF($H16=N$3,$J16,0) | O16: =IF($E16=O$3,$G16,0)-IF($H16=O$3,$J16,0) | P16: =IF($E16=P$3,$G16,0)-IF($H16=P$3,$J16,0) | Q16: =IF($E16=Q$3,$G16,0)-IF($H16=Q$3,$J16,0) | R16: =IF($E16=R$3,$G16,0)-IF($H16=R$3,$J16,0) | S16: =IF($E16=S$3,$G16,0)-IF($H16=S$3,$J16,0) | ... AL16: =IF($E16=AL$3,$G16,0)-IF($H16=AL$3,$J16,0) | AM16: =-IF($E16=AM$3,$G16,0)+IF($H16=AM$3,$J16,0) | AN16: =-IF($E16=AN$3,$G16,0)+IF($H16=AN$3,$J16,0) | AO16: =-IF($E16=AO$3,$G16,0)+IF($H16=AO$3,$J16,0) | AP16: =IF($E16=AP$3,$G16,0)-IF($H16=AP$3,$J16,0) | AQ16: =IF($E16=AQ$3,$G16,0)-IF($H16=AQ$3,$J16,0) | AR16: =IF($E16=AR$3,$G16,0)-IF($H16=AR$3,$J16,0) | AS16: =IF($E16=AS$3,$G16,0)-IF($H16=AS$3,$J16,0) | AT16: =IF($E16=AT$3,$G16,0)-IF($H16=AT$3,$J16,0) | AU16: =IF($E16=AU$3,$G16,0)-IF($H16=AU$3,$J16,0) | AV16: =IF($E16=AV$3,$G16,0)-IF($H16=AV$3,$J16,0) | AW16: =IF($E16=AW$3,$G16,0)-IF($H16=AW$3,$J16,0) | ... BK16: =IF($E16=BK$3,$G16,0)-IF($H16=BK$3,$J16,0) | BL16: =-IF($E16=BL$3,$G16,0)+IF($H16=BL$3,$J16,0) | BM16: =-IF($E16=BM$3,$G16,0)+IF($H16=BM$3,$J16,0) | BN16: =-IF($E16=BN$3,$G16,0)+IF($H16=BN$3,$J16,0) | BO16: =-IF($E16=BO$3,$G16,0)+IF($H16=BO$3,$J16,0) | BP16: =-IF($E16=BP$3,$G16,0)+IF($H16=BP$3,$J16,0) | BQ16: =-IF($E16=BQ$3,$G16,0)+IF($H16=BQ$3,$J16,0) | BR16: =-IF($E16=BR$3,$G16,0)+IF($H16=BR$3,$J16,0) | BS16: =-IF($E16=BS$3,$G16,0)+IF($H16=BS$3,$J16,0) | BT16: =-IF($E16=BT$3,$G16,0)+IF($H16=BT$3,$J16,0) | BU16: =+G16-J16 | BV16: =-IF($E16=BV$3,$G16,0)+IF($H16=BV$3,$J16,0)
B17: 1 | C17: 1 | D17: 普通預金を事業主へ戻し | F17: =IF(E17="","",IF(ISNA(VLOOKUP(E17,科目コード表!$C$4:$D$67,2,FALSE)),"該当科目なし",VLOOKUP(E17,科目コード表!$C$4:$D$67,2,FALSE))) | H17: 103 | I17: =IF(H17="","",IF(ISNA(VLOOKUP(H17,科目コード表!$C$4:$D$67,2,FALSE)),"該当科目なし",VLOOKUP(H17,科目コード表!$C$4:$D$67,2,FALSE))) | J17: 10475394 | L17: =IF($E17=L$3,$G17,0)-IF($H17=L$3,$J17,0) | M17: =IF($E17=M$3,$G17,0)-IF($H17=M$3,$J17,0) | N17: =IF($E17=N$3,$G17,0)-IF($H17=N$3,$J17,0) | O17: =IF($E17=O$3,$G17,0)-IF($H17=O$3,$J17,0) | P17: =IF($E17=P$3,$G17,0)-IF($H17=P$3,$J17,0) | Q17: =IF($E17=Q$3,$G17,0)-IF($H17=Q$3,$J17,0) | R17: =IF($E17=R$3,$G17,0)-IF($H17=R$3,$J17,0) | S17: =IF($E17=S$3,$G17,0)-IF($H17=S$3,$J17,0) | ... AL17: =IF($E17=AL$3,$G17,0)-IF($H17=AL$3,$J17,0) | AM17: =-IF($E17=AM$3,$G17,0)+IF($H17=AM$3,$J17,0) | AN17: =-IF($E17=AN$3,$G17,0)+IF($H17=AN$3,$J17,0) | AO17: =-IF($E17=AO$3,$G17,0)+IF($H17=AO$3,$J17,0) | AP17: =IF($E17=AP$3,$G17,0)-IF($H17=AP$3,$J17,0) | AQ17: =IF($E17=AQ$3,$G17,0)-IF($H17=AQ$3,$J17,0) | AR17: =IF($E17=AR$3,$G17,0)-IF($H17=AR$3,$J17,0) | AS17: =IF($E17=AS$3,$G17,0)-IF($H17=AS$3,$J17,0) | AT17: =IF($E17=AT$3,$G17,0)-IF($H17=AT$3,$J17,0) | AU17: =IF($E17=AU$3,$G17,0)-IF($H17=AU$3,$J17,0) | AV17: =IF($E17=AV$3,$G17,0)-IF($H17=AV$3,$J17,0) | AW17: =IF($E17=AW$3,$G17,0)-IF($H17=AW$3,$J17,0) | ... BK17: =IF($E17=BK$3,$G17,0)-IF($H17=BK$3,$J17,0) | BL17: =-IF($E17=BL$3,$G17,0)+IF($H17=BL$3,$J17,0) | BM17: =-IF($E17=BM$3,$G17,0)+IF($H17=BM$3,$J17,0) | BN17: =-IF($E17=BN$3,$G17,0)+IF($H17=BN$3,$J17,0) | BO17: =-IF($E17=BO$3,$G17,0)+IF($H17=BO$3,$J17,0) | BP17: =-IF($E17=BP$3,$G17,0)+IF($H17=BP$3,$J17,0) | BQ17: =-IF($E17=BQ$3,$G17,0)+IF($H17=BQ$3,$J17,0) | BR17: =-IF($E17=BR$3,$G17,0)+IF($H17=BR$3,$J17,0) | BS17: =-IF($E17=BS$3,$G17,0)+IF($H17=BS$3,$J17,0) | BT17: =-IF($E17=BT$3,$G17,0)+IF($H17=BT$3,$J17,0) | BU17: =+G17-J17 | BV17: =-IF($E17=BV$3,$G17,0)+IF($H17=BV$3,$J17,0)
B18: 1 | C18: 4 | D18: ドア保護フィルム | E18: 523 | F18: =IF(E18="","",IF(ISNA(VLOOKUP(E18,科目コード表!$C$4:$D$67,2,FALSE)),"該当科目なし",VLOOKUP(E18,科目コード表!$C$4:$D$67,2,FALSE))) | G18: 1905 | I18: =IF(H18="","",IF(ISNA(VLOOKUP(H18,科目コード表!$C$4:$D$67,2,FALSE)),"該当科目なし",VLOOKUP(H18,科目コード表!$C$4:$D$67,2,FALSE))) | L18: =IF($E18=L$3,$G18,0)-IF($H18=L$3,$J18,0) | M18: =IF($E18=M$3,$G18,0)-IF($H18=M$3,$J18,0) | N18: =IF($E18=N$3,$G18,0)-IF($H18=N$3,$J18,0) | O18: =IF($E18=O$3,$G18,0)-IF($H18=O$3,$J18,0) | P18: =IF($E18=P$3,$G18,0)-IF($H18=P$3,$J18,0) | Q18: =IF($E18=Q$3,$G18,0)-IF($H18=Q$3,$J18,0) | R18: =IF($E18=R$3,$G18,0)-IF($H18=R$3,$J18,0) | S18: =IF($E18=S$3,$G18,0)-IF($H18=S$3,$J18,0) | ... AL18: =IF($E18=AL$3,$G18,0)-IF($H18=AL$3,$J18,0) | AM18: =-IF($E18=AM$3,$G18,0)+IF($H18=AM$3,$J18,0) | AN18: =-IF($E18=AN$3,$G18,0)+IF($H18=AN$3,$J18,0) | AO18: =-IF($E18=AO$3,$G18,0)+IF($H18=AO$3,$J18,0) | AP18: =IF($E18=AP$3,$G18,0)-IF($H18=AP$3,$J18,0) | AQ18: =IF($E18=AQ$3,$G18,0)-IF($H18=AQ$3,$J18,0) | AR18: =IF($E18=AR$3,$G18,0)-IF($H18=AR$3,$J18,0) | AS18: =IF($E18=AS$3,$G18,0)-IF($H18=AS$3,$J18,0) | AT18: =IF($E18=AT$3,$G18,0)-IF($H18=AT$3,$J18,0) | AU18: =IF($E18=AU$3,$G18,0)-IF($H18=AU$3,$J18,0) | AV18: =IF($E18=AV$3,$G18,0)-IF($H18=AV$3,$J18,0) | AW18: =IF($E18=AW$3,$G18,0)-IF($H18=AW$3,$J18,0) | ... BK18: =IF($E18=BK$3,$G18,0)-IF($H18=BK$3,$J18,0) | BL18: =-IF($E18=BL$3,$G18,0)+IF($H18=BL$3,$J18,0) | BM18: =-IF($E18=BM$3,$G18,0)+IF($H18=BM$3,$J18,0) | BN18: =-IF($E18=BN$3,$G18,0)+IF($H18=BN$3,$J18,0) | BO18: =-IF($E18=BO$3,$G18,0)+IF($H18=BO$3,$J18,0) | BP18: =-IF($E18=BP$3,$G18,0)+IF($H18=BP$3,$J18,0) | BQ18: =-IF($E18=BQ$3,$G18,0)+IF($H18=BQ$3,$J18,0) | BR18: =-IF($E18=BR$3,$G18,0)+IF($H18=BR$3,$J18,0) | BS18: =-IF($E18=BS$3,$G18,0)+IF($H18=BS$3,$J18,0) | BT18: =-IF($E18=BT$3,$G18,0)+IF($H18=BT$3,$J18,0) | BU18: =+G18-J18 | BV18: =-IF($E18=BV$3,$G18,0)+IF($H18=BV$3,$J18,0)
B19: 1 | C19: 4 | D19: ナビ保護フィルム | E19: 523 | F19: =IF(E19="","",IF(ISNA(VLOOKUP(E19,科目コード表!$C$4:$D$67,2,FALSE)),"該当科目なし",VLOOKUP(E19,科目コード表!$C$4:$D$67,2,FALSE))) | G19: 3196 | I19: =IF(H19="","",IF(ISNA(VLOOKUP(H19,科目コード表!$C$4:$D$67,2,FALSE)),"該当科目なし",VLOOKUP(H19,科目コード表!$C$4:$D$67,2,FALSE))) | L19: =IF($E19=L$3,$G19,0)-IF($H19=L$3,$J19,0) | M19: =IF($E19=M$3,$G19,0)-IF($H19=M$3,$J19,0) | N19: =IF($E19=N$3,$G19,0)-IF($H19=N$3,$J19,0) | O19: =IF($E19=O$3,$G19,0)-IF($H19=O$3,$J19,0) | P19: =IF($E19=P$3,$G19,0)-IF($H19=P$3,$J19,0) | Q19: =IF($E19=Q$3,$G19,0)-IF($H19=Q$3,$J19,0) | R19: =IF($E19=R$3,$G19,0)-IF($H19=R$3,$J19,0) | S19: =IF($E19=S$3,$G19,0)-IF($H19=S$3,$J19,0) | ... AL19: =IF($E19=AL$3,$G19,0)-IF($H19=AL$3,$J19,0) | AM19: =-IF($E19=AM$3,$G19,0)+IF($H19=AM$3,$J19,0) | AN19: =-IF($E19=AN$3,$G19,0)+IF($H19=AN$3,$J19,0) | AO19: =-IF($E19=AO$3,$G19,0)+IF($H19=AO$3,$J19,0) | AP19: =IF($E19=AP$3,$G19,0)-IF($H19=AP$3,$J19,0) | AQ19: =IF($E19=AQ$3,$G19,0)-IF($H19=AQ$3,$J19,0) | AR19: =IF($E19=AR$3,$G19,0)-IF($H19=AR$3,$J19,0) | AS19: =IF($E19=AS$3,$G19,0)-IF($H19=AS$3,$J19,0) | AT19: =IF($E19=AT$3,$G19,0)-IF($H19=AT$3,$J19,0) | AU19: =IF($E19=AU$3,$G19,0)-IF($H19=AU$3,$J19,0) | AV19: =IF($E19=AV$3,$G19,0)-IF($H19=AV$3,$J19,0) | AW19: =IF($E19=AW$3,$G19,0)-IF($H19=AW$3,$J19,0) | ... BK19: =IF($E19=BK$3,$G19,0)-IF($H19=BK$3,$J19,0) | BL19: =-IF($E19=BL$3,$G19,0)+IF($H19=BL$3,$J19,0) | BM19: =-IF($E19=BM$3,$G19,0)+IF($H19=BM$3,$J19,0) | BN19: =-IF($E19=BN$3,$G19,0)+IF($H19=BN$3,$J19,0) | BO19: =-IF($E19=BO$3,$G19,0)+IF($H19=BO$3,$J19,0) | BP19: =-IF($E19=BP$3,$G19,0)+IF($H19=BP$3,$J19,0) | BQ19: =-IF($E19=BQ$3,$G19,0)+IF($H19=BQ$3,$J19,0) | BR19: =-IF($E19=BR$3,$G19,0)+IF($H19=BR$3,$J19,0) | BS19: =-IF($E19=BS$3,$G19,0)+IF($H19=BS$3,$J19,0) | BT19: =-IF($E19=BT$3,$G19,0)+IF($H19=BT$3,$J19,0) | BU19: =+G19-J19 | BV19: =-IF($E19=BV$3,$G19,0)+IF($H19=BV$3,$J19,0)
B20: 1 | C20: 4 | D20: ラゲッジマット | E20: 523 | F20: =IF(E20="","",IF(ISNA(VLOOKUP(E20,科目コード表!$C$4:$D$67,2,FALSE)),"該当科目なし",VLOOKUP(E20,科目コード表!$C$4:$D$67,2,FALSE))) | G20: 4122 | I20: =IF(H20="","",IF(ISNA(VLOOKUP(H20,科目コード表!$C$4:$D$67,2,FALSE)),"該当科目なし",VLOOKUP(H20,科目コード表!$C$4:$D$67,2,FALSE))) | L20: =IF($E20=L$3,$G20,0)-IF($H20=L$3,$J20,0) | M20: =IF($E20=M$3,$G20,0)-IF($H20=M$3,$J20,0) | N20: =IF($E20=N$3,$G20,0)-IF($H20=N$3,$J20,0) | O20: =IF($E20=O$3,$G20,0)-IF($H20=O$3,$J20,0) | P20: =IF($E20=P$3,$G20,0)-IF($H20=P$3,$J20,0) | Q20: =IF($E20=Q$3,$G20,0)-IF($H20=Q$3,$J20,0) | R20: =IF($E20=R$3,$G20,0)-IF($H20=R$3,$J20,0) | S20: =IF($E20=S$3,$G20,0)-IF($H20=S$3,$J20,0) | ... AL20: =IF($E20=AL$3,$G20,0)-IF($H20=AL$3,$J20,0) | AM20: =-IF($E20=AM$3,$G20,0)+IF($H20=AM$3,$J20,0) | AN20: =-IF($E20=AN$3,$G20,0)+IF($H20=AN$3,$J20,0) | AO20: =-IF($E20=AO$3,$G20,0)+IF($H20=AO$3,$J20,0) | AP20: =IF($E20=AP$3,$G20,0)-IF($H20=AP$3,$J20,0) | AQ20: =IF($E20=AQ$3,$G20,0)-IF($H20=AQ$3,$J20,0) | AR20: =IF($E20=AR$3,$G20,0)-IF($H20=AR$3,$J20,0) | AS20: =IF($E20=AS$3,$G20,0)-IF($H20=AS$3,$J20,0) | AT20: =IF($E20=AT$3,$G20,0)-IF($H20=AT$3,$J20,0) | AU20: =IF($E20=AU$3,$G20,0)-IF($H20=AU$3,$J20,0) | AV20: =IF($E20=AV$3,$G20,0)-IF($H20=AV$3,$J20,0) | AW20: =IF($E20=AW$3,$G20,0)-IF($H20=AW$3,$J20,0) | ... BK20: =IF($E20=BK$3,$G20,0)-IF($H20=BK$3,$J20,0) | BL20: =-IF($E20=BL$3,$G20,0)+IF($H20=BL$3,$J20,0) | BM20: =-IF($E20=BM$3,$G20,0)+IF($H20=BM$3,$J20,0) | BN20: =-IF($E20=BN$3,$G20,0)+IF($H20=BN$3,$J20,0) | BO20: =-IF($E20=BO$3,$G20,0)+IF($H20=BO$3,$J20,0) | BP20: =-IF($E20=BP$3,$G20,0)+IF($H20=BP$3,$J20,0) | BQ20: =-IF($E20=BQ$3,$G20,0)+IF($H20=BQ$3,$J20,0) | BR20: =-IF($E20=BR$3,$G20,0)+IF($H20=BR$3,$J20,0) | BS20: =-IF($E20=BS$3,$G20,0)+IF($H20=BS$3,$J20,0) | BT20: =-IF($E20=BT$3,$G20,0)+IF($H20=BT$3,$J20,0) | BU20: =+G20-J20 | BV20: =-IF($E20=BV$3,$G20,0)+IF($H20=BV$3,$J20,0)
B21: 1 | C21: 5 | D21: 中尾洋一へ地代振込 | E21: 520 | F21: =IF(E21="","",IF(ISNA(VLOOKUP(E21,科目コード表!$C$4:$D$67,2,FALSE)),"該当科目なし",VLOOKUP(E21,科目コード表!$C$4:$D$67,2,FALSE))) | G21: 20000 | I21: =IF(H21="","",IF(ISNA(VLOOKUP(H21,科目コード表!$C$4:$D$67,2,FALSE)),"該当科目なし",VLOOKUP(H21,科目コード表!$C$4:$D$67,2,FALSE))) | L21: =IF($E21=L$3,$G21,0)-IF($H21=L$3,$J21,0) | M21: =IF($E21=M$3,$G21,0)-IF($H21=M$3,$J21,0) | N21: =IF($E21=N$3,$G21,0)-IF($H21=N$3,$J21,0) | O21: =IF($E21=O$3,$G21,0)-IF($H21=O$3,$J21,0) | P21: =IF($E21=P$3,$G21,0)-IF($H21=P$3,$J21,0) | Q21: =IF($E21=Q$3,$G21,0)-IF($H21=Q$3,$J21,0) | R21: =IF($E21=R$3,$G21,0)-IF($H21=R$3,$J21,0) | S21: =IF($E21=S$3,$G21,0)-IF($H21=S$3,$J21,0) | ... AL21: =IF($E21=AL$3,$G21,0)-IF($H21=AL$3,$J21,0) | AM21: =-IF($E21=AM$3,$G21,0)+IF($H21=AM$3,$J21,0) | AN21: =-IF($E21=AN$3,$G21,0)+IF($H21=AN$3,$J21,0) | AO21: =-IF($E21=AO$3,$G21,0)+IF($H21=AO$3,$J21,0) | AP21: =IF($E21=AP$3,$G21,0)-IF($H21=AP$3,$J21,0) | AQ21: =IF($E21=AQ$3,$G21,0)-IF($H21=AQ$3,$J21,0) | AR21: =IF($E21=AR$3,$G21,0)-IF($H21=AR$3,$J21,0) | AS21: =IF($E21=AS$3,$G21,0)-IF($H21=AS$3,$J21,0) | AT21: =IF($E21=AT$3,$G21,0)-IF($H21=AT$3,$J21,0) | AU21: =IF($E21=AU$3,$G21,0)-IF($H21=AU$3,$J21,0) | AV21: =IF($E21=AV$3,$G21,0)-IF($H21=AV$3,$J21,0) | AW21: =IF($E21=AW$3,$G21,0)-IF($H21=AW$3,$J21,0) | ... BK21: =IF($E21=BK$3,$G21,0)-IF($H21=BK$3,$J21,0) | BL21: =-IF($E21=BL$3,$G21,0)+IF($H21=BL$3,$J21,0) | BM21: =-IF($E21=BM$3,$G21,0)+IF($H21=BM$3,$J21,0) | BN21: =-IF($E21=BN$3,$G21,0)+IF($H21=BN$3,$J21,0) | BO21: =-IF($E21=BO$3,$G21,0)+IF($H21=BO$3,$J21,0) | BP21: =-IF($E21=BP$3,$G21,0)+IF($H21=BP$3,$J21,0) | BQ21: =-IF($E21=BQ$3,$G21,0)+IF($H21=BQ$3,$J21,0) | BR21: =-IF($E21=BR$3,$G21,0)+IF($H21=BR$3,$J21,0) | BS21: =-IF($E21=BS$3,$G21,0)+IF($H21=BS$3,$J21,0) | BT21: =-IF($E21=BT$3,$G21,0)+IF($H21=BT$3,$J21,0) | BU21: =+G21-J21 | BV21: =-IF($E21=BV$3,$G21,0)+IF($H21=BV$3,$J21,0)
B22: 1 | C22: 15 | D22: セレサ川崎 ユーユー入金 | F22: =IF(E22="","",IF(ISNA(VLOOKUP(E22,科目コード表!$C$4:$D$67,2,FALSE)),"該当科目なし",VLOOKUP(E22,科目コード表!$C$4:$D$67,2,FALSE))) | H22: 107 | I22: =IF(H22="","",IF(ISNA(VLOOKUP(H22,科目コード表!$C$4:$D$67,2,FALSE)),"該当科目なし",VLOOKUP(H22,科目コード表!$C$4:$D$67,2,FALSE))) | J22: 100000 | L22: =IF($E22=L$3,$G22,0)-IF($H22=L$3,$J22,0) | M22: =IF($E22=M$3,$G22,0)-IF($H22=M$3,$J22,0) | N22: =IF($E22=N$3,$G22,0)-IF($H22=N$3,$J22,0) | O22: =IF($E22=O$3,$G22,0)-IF($H22=O$3,$J22,0) | P22: =IF($E22=P$3,$G22,0)-IF($H22=P$3,$J22,0) | Q22: =IF($E22=Q$3,$G22,0)-IF($H22=Q$3,$J22,0) | R22: =IF($E22=R$3,$G22,0)-IF($H22=R$3,$J22,0) | S22: =IF($E22=S$3,$G22,0)-IF($H22=S$3,$J22,0) | ... AL22: =IF($E22=AL$3,$G22,0)-IF($H22=AL$3,$J22,0) | AM22: =-IF($E22=AM$3,$G22,0)+IF($H22=AM$3,$J22,0) | AN22: =-IF($E22=AN$3,$G22,0)+IF($H22=AN$3,$J22,0) | AO22: =-IF($E22=AO$3,$G22,0)+IF($H22=AO$3,$J22,0) | AP22: =IF($E22=AP$3,$G22,0)-IF($H22=AP$3,$J22,0) | AQ22: =IF($E22=AQ$3,$G22,0)-IF($H22=AQ$3,$J22,0) | AR22: =IF($E22=AR$3,$G22,0)-IF($H22=AR$3,$J22,0) | AS22: =IF($E22=AS$3,$G22,0)-IF($H22=AS$3,$J22,0) | AT22: =IF($E22=AT$3,$G22,0)-IF($H22=AT$3,$J22,0) | AU22: =IF($E22=AU$3,$G22,0)-IF($H22=AU$3,$J22,0) | AV22: =IF($E22=AV$3,$G22,0)-IF($H22=AV$3,$J22,0) | AW22: =IF($E22=AW$3,$G22,0)-IF($H22=AW$3,$J22,0) | ... BK22: =IF($E22=BK$3,$G22,0)-IF($H22=BK$3,$J22,0) | BL22: =-IF($E22=BL$3,$G22,0)+IF($H22=BL$3,$J22,0) | BM22: =-IF($E22=BM$3,$G22,0)+IF($H22=BM$3,$J22,0) | BN22: =-IF($E22=BN$3,$G22,0)+IF($H22=BN$3,$J22,0) | BO22: =-IF($E22=BO$3,$G22,0)+IF($H22=BO$3,$J22,0) | BP22: =-IF($E22=BP$3,$G22,0)+IF($H22=BP$3,$J22,0) | BQ22: =-IF($E22=BQ$3,$G22,0)+IF($H22=BQ$3,$J22,0) | BR22: =-IF($E22=BR$3,$G22,0)+IF($H22=BR$3,$J22,0) | BS22: =-IF($E22=BS$3,$G22,0)+IF($H22=BS$3,$J22,0) | BT22: =-IF($E22=BT$3,$G22,0)+IF($H22=BT$3,$J22,0) | BU22: =+G22-J22 | BV22: =-IF($E22=BV$3,$G22,0)+IF($H22=BV$3,$J22,0)
B23: 1 | C23: 16 | D23: Kindle Unlimited会費 | E23: 524 | F23: =IF(E23="","",IF(ISNA(VLOOKUP(E23,科目コード表!$C$4:$D$67,2,FALSE)),"該当科目なし",VLOOKUP(E23,科目コード表!$C$4:$D$67,2,FALSE))) | G23: 980 | I23: =IF(H23="","",IF(ISNA(VLOOKUP(H23,科目コード表!$C$4:$D$67,2,FALSE)),"該当科目なし",VLOOKUP(H23,科目コード表!$C$4:$D$67,2,FALSE))) | L23: =IF($E23=L$3,$G23,0)-IF($H23=L$3,$J23,0) | M23: =IF($E23=M$3,$G23,0)-IF($H23=M$3,$J23,0) | N23: =IF($E23=N$3,$G23,0)-IF($H23=N$3,$J23,0) | O23: =IF($E23=O$3,$G23,0)-IF($H23=O$3,$J23,0) | P23: =IF($E23=P$3,$G23,0)-IF($H23=P$3,$J23,0) | Q23: =IF($E23=Q$3,$G23,0)-IF($H23=Q$3,$J23,0) | R23: =IF($E23=R$3,$G23,0)-IF($H23=R$3,$J23,0) | S23: =IF($E23=S$3,$G23,0)-IF($H23=S$3,$J23,0) | ... AL23: =IF($E23=AL$3,$G23,0)-IF($H23=AL$3,$J23,0) | AM23: =-IF($E23=AM$3,$G23,0)+IF($H23=AM$3,$J23,0) | AN23: =-IF($E23=AN$3,$G23,0)+IF($H23=AN$3,$J23,0) | AO23: =-IF($E23=AO$3,$G23,0)+IF($H23=AO$3,$J23,0) | AP23: =IF($E23=AP$3,$G23,0)-IF($H23=AP$3,$J23,0) | AQ23: =IF($E23=AQ$3,$G23,0)-IF($H23=AQ$3,$J23,0) | AR23: =IF($E23=AR$3,$G23,0)-IF($H23=AR$3,$J23,0) | AS23: =IF($E23=AS$3,$G23,0)-IF($H23=AS$3,$J23,0) | AT23: =IF($E23=AT$3,$G23,0)-IF($H23=AT$3,$J23,0) | AU23: =IF($E23=AU$3,$G23,0)-IF($H23=AU$3,$J23,0) | AV23: =IF($E23=AV$3,$G23,0)-IF($H23=AV$3,$J23,0) | AW23: =IF($E23=AW$3,$G23,0)-IF($H23=AW$3,$J23,0) | ... BK23: =IF($E23=BK$3,$G23,0)-IF($H23=BK$3,$J23,0) | BL23: =-IF($E23=BL$3,$G23,0)+IF($H23=BL$3,$J23,0) | BM23: =-IF($E23=BM$3,$G23,0)+IF($H23=BM$3,$J23,0) | BN23: =-IF($E23=BN$3,$G23,0)+IF($H23=BN$3,$J23,0) | BO23: =-IF($E23=BO$3,$G23,0)+IF($H23=BO$3,$J23,0) | BP23: =-IF($E23=BP$3,$G23,0)+IF($H23=BP$3,$J23,0) | BQ23: =-IF($E23=BQ$3,$G23,0)+IF($H23=BQ$3,$J23,0) | BR23: =-IF($E23=BR$3,$G23,0)+IF($H23=BR$3,$J23,0) | BS23: =-IF($E23=BS$3,$G23,0)+IF($H23=BS$3,$J23,0) | BT23: =-IF($E23=BT$3,$G23,0)+IF($H23=BT$3,$J23,0) | BU23: =+G23-J23 | BV23: =-IF($E23=BV$3,$G23,0)+IF($H23=BV$3,$J23,0)
B24: 1 | C24: 17 | D24: デミオを売却 | F24: =IF(E24="","",IF(ISNA(VLOOKUP(E24,科目コード表!$C$4:$D$67,2,FALSE)),"該当科目なし",VLOOKUP(E24,科目コード表!$C$4:$D$67,2,FALSE))) | H24: 124 | I24: =IF(H24="","",IF(ISNA(VLOOKUP(H24,科目コード表!$C$4:$D$67,2,FALSE)),"該当科目なし",VLOOKUP(H24,科目コード表!$C$4:$D$67,2,FALSE))) | J24: 1 | L24: =IF($E24=L$3,$G24,0)-IF($H24=L$3,$J24,0) | M24: =IF($E24=M$3,$G24,0)-IF($H24=M$3,$J24,0) | N24: =IF($E24=N$3,$G24,0)-IF($H24=N$3,$J24,0) | O24: =IF($E24=O$3,$G24,0)-IF($H24=O$3,$J24,0) | P24: =IF($E24=P$3,$G24,0)-IF($H24=P$3,$J24,0) | Q24: =IF($E24=Q$3,$G24,0)-IF($H24=Q$3,$J24,0) | R24: =IF($E24=R$3,$G24,0)-IF($H24=R$3,$J24,0) | S24: =IF($E24=S$3,$G24,0)-IF($H24=S$3,$J24,0) | ... AL24: =IF($E24=AL$3,$G24,0)-IF($H24=AL$3,$J24,0) | AM24: =-IF($E24=AM$3,$G24,0)+IF($H24=AM$3,$J24,0) | AN24: =-IF($E24=AN$3,$G24,0)+IF($H24=AN$3,$J24,0) | AO24: =-IF($E24=AO$3,$G24,0)+IF($H24=AO$3,$J24,0) | AP24: =IF($E24=AP$3,$G24,0)-IF($H24=AP$3,$J24,0) | AQ24: =IF($E24=AQ$3,$G24,0)-IF($H24=AQ$3,$J24,0) | AR24: =IF($E24=AR$3,$G24,0)-IF($H24=AR$3,$J24,0) | AS24: =IF($E24=AS$3,$G24,0)-IF($H24=AS$3,$J24,0) | AT24: =IF($E24=AT$3,$G24,0)-IF($H24=AT$3,$J24,0) | AU24: =IF($E24=AU$3,$G24,0)-IF($H24=AU$3,$J24,0) | AV24: =IF($E24=AV$3,$G24,0)-IF($H24=AV$3,$J24,0) | AW24: =IF($E24=AW$3,$G24,0)-IF($H24=AW$3,$J24,0) | ... BK24: =IF($E24=BK$3,$G24,0)-IF($H24=BK$3,$J24,0) | BL24: =-IF($E24=BL$3,$G24,0)+IF($H24=BL$3,$J24,0) | BM24: =-IF($E24=BM$3,$G24,0)+IF($H24=BM$3,$J24,0) | BN24: =-IF($E24=BN$3,$G24,0)+IF($H24=BN$3,$J24,0) | BO24: =-IF($E24=BO$3,$G24,0)+IF($H24=BO$3,$J24,0) | BP24: =-IF($E24=BP$3,$G24,0)+IF($H24=BP$3,$J24,0) | BQ24: =-IF($E24=BQ$3,$G24,0)+IF($H24=BQ$3,$J24,0) | BR24: =-IF($E24=BR$3,$G24,0)+IF($H24=BR$3,$J24,0) | BS24: =-IF($E24=BS$3,$G24,0)+IF($H24=BS$3,$J24,0) | BT24: =-IF($E24=BT$3,$G24,0)+IF($H24=BT$3,$J24,0) | BU24: =+G24-J24 | BV24: =-IF($E24=BV$3,$G24,0)+IF($H24=BV$3,$J24,0)
B25: 1 | C25: 17 | D25: 固定資産売却益 | F25: =IF(E25="","",IF(ISNA(VLOOKUP(E25,科目コード表!$C$4:$D$67,2,FALSE)),"該当科目なし",VLOOKUP(E25,科目コード表!$C$4:$D$67,2,FALSE))) | H25: 403 | I25: =IF(H25="","",IF(ISNA(VLOOKUP(H25,科目コード表!$C$4:$D$67,2,FALSE)),"該当科目なし",VLOOKUP(H25,科目コード表!$C$4:$D$67,2,FALSE))) | J25: 329999 | L25: =IF($E25=L$3,$G25,0)-IF($H25=L$3,$J25,0) | M25: =IF($E25=M$3,$G25,0)-IF($H25=M$3,$J25,0) | N25: =IF($E25=N$3,$G25,0)-IF($H25=N$3,$J25,0) | O25: =IF($E25=O$3,$G25,0)-IF($H25=O$3,$J25,0) | P25: =IF($E25=P$3,$G25,0)-IF($H25=P$3,$J25,0) | Q25: =IF($E25=Q$3,$G25,0)-IF($H25=Q$3,$J25,0) | R25: =IF($E25=R$3,$G25,0)-IF($H25=R$3,$J25,0) | S25: =IF($E25=S$3,$G25,0)-IF($H25=S$3,$J25,0) | ... AL25: =IF($E25=AL$3,$G25,0)-IF($H25=AL$3,$J25,0) | AM25: =-IF($E25=AM$3,$G25,0)+IF($H25=AM$3,$J25,0) | AN25: =-IF($E25=AN$3,$G25,0)+IF($H25=AN$3,$J25,0) | AO25: =-IF($E25=AO$3,$G25,0)+IF($H25=AO$3,$J25,0) | AP25: =IF($E25=AP$3,$G25,0)-IF($H25=AP$3,$J25,0) | AQ25: =IF($E25=AQ$3,$G25,0)-IF($H25=AQ$3,$J25,0) | AR25: =IF($E25=AR$3,$G25,0)-IF($H25=AR$3,$J25,0) | AS25: =IF($E25=AS$3,$G25,0)-IF($H25=AS$3,$J25,0) | AT25: =IF($E25=AT$3,$G25,0)-IF($H25=AT$3,$J25,0) | AU25: =IF($E25=AU$3,$G25,0)-IF($H25=AU$3,$J25,0) | AV25: =IF($E25=AV$3,$G25,0)-IF($H25=AV$3,$J25,0) | AW25: =IF($E25=AW$3,$G25,0)-IF($H25=AW$3,$J25,0) | ... BK25: =IF($E25=BK$3,$G25,0)-IF($H25=BK$3,$J25,0) | BL25: =-IF($E25=BL$3,$G25,0)+IF($H25=BL$3,$J25,0) | BM25: =-IF($E25=BM$3,$G25,0)+IF($H25=BM$3,$J25,0) | BN25: =-IF($E25=BN$3,$G25,0)+IF($H25=BN$3,$J25,0) | BO25: =-IF($E25=BO$3,$G25,0)+IF($H25=BO$3,$J25,0) | BP25: =-IF($E25=BP$3,$G25,0)+IF($H25=BP$3,$J25,0) | BQ25: =-IF($E25=BQ$3,$G25,0)+IF($H25=BQ$3,$J25,0) | BR25: =-IF($E25=BR$3,$G25,0)+IF($H25=BR$3,$J25,0) | BS25: =-IF($E25=BS$3,$G25,0)+IF($H25=BS$3,$J25,0) | BT25: =-IF($E25=BT$3,$G25,0)+IF($H25=BT$3,$J25,0) | BU25: =+G25-J25 | BV25: =-IF($E25=BV$3,$G25,0)+IF($H25=BV$3,$J25,0)
B26: 1 | C26: 17 | D26: リサイクル預託金 | F26: =IF(E26="","",IF(ISNA(VLOOKUP(E26,科目コード表!$C$4:$D$67,2,FALSE)),"該当科目なし",VLOOKUP(E26,科目コード表!$C$4:$D$67,2,FALSE))) | H26: 114 | I26: =IF(H26="","",IF(ISNA(VLOOKUP(H26,科目コード表!$C$4:$D$67,2,FALSE)),"該当科目なし",VLOOKUP(H26,科目コード表!$C$4:$D$67,2,FALSE))) | J26: 9130 | L26: =IF($E26=L$3,$G26,0)-IF($H26=L$3,$J26,0) | M26: =IF($E26=M$3,$G26,0)-IF($H26=M$3,$J26,0) | N26: =IF($E26=N$3,$G26,0)-IF($H26=N$3,$J26,0) | O26: =IF($E26=O$3,$G26,0)-IF($H26=O$3,$J26,0) | P26: =IF($E26=P$3,$G26,0)-IF($H26=P$3,$J26,0) | Q26: =IF($E26=Q$3,$G26,0)-IF($H26=Q$3,$J26,0) | R26: =IF($E26=R$3,$G26,0)-IF($H26=R$3,$J26,0) | S26: =IF($E26=S$3,$G26,0)-IF($H26=S$3,$J26,0) | ... AL26: =IF($E26=AL$3,$G26,0)-IF($H26=AL$3,$J26,0) | AM26: =-IF($E26=AM$3,$G26,0)+IF($H26=AM$3,$J26,0) | AN26: =-IF($E26=AN$3,$G26,0)+IF($H26=AN$3,$J26,0) | AO26: =-IF($E26=AO$3,$G26,0)+IF($H26=AO$3,$J26,0) | AP26: =IF($E26=AP$3,$G26,0)-IF($H26=AP$3,$J26,0) | AQ26: =IF($E26=AQ$3,$G26,0)-IF($H26=AQ$3,$J26,0) | AR26: =IF($E26=AR$3,$G26,0)-IF($H26=AR$3,$J26,0) | AS26: =IF($E26=AS$3,$G26,0)-IF($H26=AS$3,$J26,0) | AT26: =IF($E26=AT$3,$G26,0)-IF($H26=AT$3,$J26,0) | AU26: =IF($E26=AU$3,$G26,0)-IF($H26=AU$3,$J26,0) | AV26: =IF($E26=AV$3,$G26,0)-IF($H26=AV$3,$J26,0) | AW26: =IF($E26=AW$3,$G26,0)-IF($H26=AW$3,$J26,0) | ... BK26: =IF($E26=BK$3,$G26,0)-IF($H26=BK$3,$J26,0) | BL26: =-IF($E26=BL$3,$G26,0)+IF($H26=BL$3,$J26,0) | BM26: =-IF($E26=BM$3,$G26,0)+IF($H26=BM$3,$J26,0) | BN26: =-IF($E26=BN$3,$G26,0)+IF($H26=BN$3,$J26,0) | BO26: =-IF($E26=BO$3,$G26,0)+IF($H26=BO$3,$J26,0) | BP26: =-IF($E26=BP$3,$G26,0)+IF($H26=BP$3,$J26,0) | BQ26: =-IF($E26=BQ$3,$G26,0)+IF($H26=BQ$3,$J26,0) | BR26: =-IF($E26=BR$3,$G26,0)+IF($H26=BR$3,$J26,0) | BS26: =-IF($E26=BS$3,$G26,0)+IF($H26=BS$3,$J26,0) | BT26: =-IF($E26=BT$3,$G26,0)+IF($H26=BT$3,$J26,0) | BU26: =+G26-J26 | BV26: =-IF($E26=BV$3,$G26,0)+IF($H26=BV$3,$J26,0)
B27: 1 | C27: 17 | D27: シエンタ(車両)購入 | E27: 124 | F27: =IF(E27="","",IF(ISNA(VLOOKUP(E27,科目コード表!$C$4:$D$67,2,FALSE)),"該当科目なし",VLOOKUP(E27,科目コード表!$C$4:$D$67,2,FALSE))) | G27: 3057480 | I27: =IF(H27="","",IF(ISNA(VLOOKUP(H27,科目コード表!$C$4:$D$67,2,FALSE)),"該当科目なし",VLOOKUP(H27,科目コード表!$C$4:$D$67,2,FALSE))) | L27: =IF($E27=L$3,$G27,0)-IF($H27=L$3,$J27,0) | M27: =IF($E27=M$3,$G27,0)-IF($H27=M$3,$J27,0) | N27: =IF($E27=N$3,$G27,0)-IF($H27=N$3,$J27,0) | O27: =IF($E27=O$3,$G27,0)-IF($H27=O$3,$J27,0) | P27: =IF($E27=P$3,$G27,0)-IF($H27=P$3,$J27,0) | Q27: =IF($E27=Q$3,$G27,0)-IF($H27=Q$3,$J27,0) | R27: =IF($E27=R$3,$G27,0)-IF($H27=R$3,$J27,0) | S27: =IF($E27=S$3,$G27,0)-IF($H27=S$3,$J27,0) | ... AL27: =IF($E27=AL$3,$G27,0)-IF($H27=AL$3,$J27,0) | AM27: =-IF($E27=AM$3,$G27,0)+IF($H27=AM$3,$J27,0) | AN27: =-IF($E27=AN$3,$G27,0)+IF($H27=AN$3,$J27,0) | AO27: =-IF($E27=AO$3,$G27,0)+IF($H27=AO$3,$J27,0) | AP27: =IF($E27=AP$3,$G27,0)-IF($H27=AP$3,$J27,0) | AQ27: =IF($E27=AQ$3,$G27,0)-IF($H27=AQ$3,$J27,0) | AR27: =IF($E27=AR$3,$G27,0)-IF($H27=AR$3,$J27,0) | AS27: =IF($E27=AS$3,$G27,0)-IF($H27=AS$3,$J27,0) | AT27: =IF($E27=AT$3,$G27,0)-IF($H27=AT$3,$J27,0) | AU27: =IF($E27=AU$3,$G27,0)-IF($H27=AU$3,$J27,0) | AV27: =IF($E27=AV$3,$G27,0)-IF($H27=AV$3,$J27,0) | AW27: =IF($E27=AW$3,$G27,0)-IF($H27=AW$3,$J27,0) | ... BK27: =IF($E27=BK$3,$G27,0)-IF($H27=BK$3,$J27,0) | BL27: =-IF($E27=BL$3,$G27,0)+IF($H27=BL$3,$J27,0) | BM27: =-IF($E27=BM$3,$G27,0)+IF($H27=BM$3,$J27,0) | BN27: =-IF($E27=BN$3,$G27,0)+IF($H27=BN$3,$J27,0) | BO27: =-IF($E27=BO$3,$G27,0)+IF($H27=BO$3,$J27,0) | BP27: =-IF($E27=BP$3,$G27,0)+IF($H27=BP$3,$J27,0) | BQ27: =-IF($E27=BQ$3,$G27,0)+IF($H27=BQ$3,$J27,0) | BR27: =-IF($E27=BR$3,$G27,0)+IF($H27=BR$3,$J27,0) | BS27: =-IF($E27=BS$3,$G27,0)+IF($H27=BS$3,$J27,0) | BT27: =-IF($E27=BT$3,$G27,0)+IF($H27=BT$3,$J27,0) | BU27: =+G27-J27 | BV27: =-IF($E27=BV$3,$G27,0)+IF($H27=BV$3,$J27,0)
B28: 1 | C28: 17 | D28: シエンタのリサイクル預託金 | E28: 114 | F28: =IF(E28="","",IF(ISNA(VLOOKUP(E28,科目コード表!$C$4:$D$67,2,FALSE)),"該当科目なし",VLOOKUP(E28,科目コード表!$C$4:$D$67,2,FALSE))) | G28: 11650 | I28: =IF(H28="","",IF(ISNA(VLOOKUP(H28,科目コード表!$C$4:$D$67,2,FALSE)),"該当科目なし",VLOOKUP(H28,科目コード表!$C$4:$D$67,2,FALSE))) | L28: =IF($E28=L$3,$G28,0)-IF($H28=L$3,$J28,0) | M28: =IF($E28=M$3,$G28,0)-IF($H28=M$3,$J28,0) | N28: =IF($E28=N$3,$G28,0)-IF($H28=N$3,$J28,0) | O28: =IF($E28=O$3,$G28,0)-IF($H28=O$3,$J28,0) | P28: =IF($E28=P$3,$G28,0)-IF($H28=P$3,$J28,0) | Q28: =IF($E28=Q$3,$G28,0)-IF($H28=Q$3,$J28,0) | R28: =IF($E28=R$3,$G28,0)-IF($H28=R$3,$J28,0) | S28: =IF($E28=S$3,$G28,0)-IF($H28=S$3,$J28,0) | ... AL28: =IF($E28=AL$3,$G28,0)-IF($H28=AL$3,$J28,0) | AM28: =-IF($E28=AM$3,$G28,0)+IF($H28=AM$3,$J28,0) | AN28: =-IF($E28=AN$3,$G28,0)+IF($H28=AN$3,$J28,0) | AO28: =-IF($E28=AO$3,$G28,0)+IF($H28=AO$3,$J28,0) | AP28: =IF($E28=AP$3,$G28,0)-IF($H28=AP$3,$J28,0) | AQ28: =IF($E28=AQ$3,$G28,0)-IF($H28=AQ$3,$J28,0) | AR28: =IF($E28=AR$3,$G28,0)-IF($H28=AR$3,$J28,0) | AS28: =IF($E28=AS$3,$G28,0)-IF($H28=AS$3,$J28,0) | AT28: =IF($E28=AT$3,$G28,0)-IF($H28=AT$3,$J28,0) | AU28: =IF($E28=AU$3,$G28,0)-IF($H28=AU$3,$J28,0) | AV28: =IF($E28=AV$3,$G28,0)-IF($H28=AV$3,$J28,0) | AW28: =IF($E28=AW$3,$G28,0)-IF($H28=AW$3,$J28,0) | ... BK28: =IF($E28=BK$3,$G28,0)-IF($H28=BK$3,$J28,0) | BL28: =-IF($E28=BL$3,$G28,0)+IF($H28=BL$3,$J28,0) | BM28: =-IF($E28=BM$3,$G28,0)+IF($H28=BM$3,$J28,0) | BN28: =-IF($E28=BN$3,$G28,0)+IF($H28=BN$3,$J28,0) | BO28: =-IF($E28=BO$3,$G28,0)+IF($H28=BO$3,$J28,0) | BP28: =-IF($E28=BP$3,$G28,0)+IF($H28=BP$3,$J28,0) | BQ28: =-IF($E28=BQ$3,$G28,0)+IF($H28=BQ$3,$J28,0) | BR28: =-IF($E28=BR$3,$G28,0)+IF($H28=BR$3,$J28,0) | BS28: =-IF($E28=BS$3,$G28,0)+IF($H28=BS$3,$J28,0) | BT28: =-IF($E28=BT$3,$G28,0)+IF($H28=BT$3,$J28,0) | BU28: =+G28-J28 | BV28: =-IF($E28=BV$3,$G28,0)+IF($H28=BV$3,$J28,0)
B29: 1 | C29: 18 | D29: エポス Github | E29: 525 | F29: =IF(E29="","",IF(ISNA(VLOOKUP(E29,科目コード表!$C$4:$D$67,2,FALSE)),"該当科目なし",VLOOKUP(E29,科目コード表!$C$4:$D$67,2,FALSE))) | G29: 1813 | I29: =IF(H29="","",IF(ISNA(VLOOKUP(H29,科目コード表!$C$4:$D$67,2,FALSE)),"該当科目なし",VLOOKUP(H29,科目コード表!$C$4:$D$67,2,FALSE))) | L29: =IF($E29=L$3,$G29,0)-IF($H29=L$3,$J29,0) | M29: =IF($E29=M$3,$G29,0)-IF($H29=M$3,$J29,0) | N29: =IF($E29=N$3,$G29,0)-IF($H29=N$3,$J29,0) | O29: =IF($E29=O$3,$G29,0)-IF($H29=O$3,$J29,0) | P29: =IF($E29=P$3,$G29,0)-IF($H29=P$3,$J29,0) | Q29: =IF($E29=Q$3,$G29,0)-IF($H29=Q$3,$J29,0) | R29: =IF($E29=R$3,$G29,0)-IF($H29=R$3,$J29,0) | S29: =IF($E29=S$3,$G29,0)-IF($H29=S$3,$J29,0) | ... AL29: =IF($E29=AL$3,$G29,0)-IF($H29=AL$3,$J29,0) | AM29: =-IF($E29=AM$3,$G29,0)+IF($H29=AM$3,$J29,0) | AN29: =-IF($E29=AN$3,$G29,0)+IF($H29=AN$3,$J29,0) | AO29: =-IF($E29=AO$3,$G29,0)+IF($H29=AO$3,$J29,0) | AP29: =IF($E29=AP$3,$G29,0)-IF($H29=AP$3,$J29,0) | AQ29: =IF($E29=AQ$3,$G29,0)-IF($H29=AQ$3,$J29,0) | AR29: =IF($E29=AR$3,$G29,0)-IF($H29=AR$3,$J29,0) | AS29: =IF($E29=AS$3,$G29,0)-IF($H29=AS$3,$J29,0) | AT29: =IF($E29=AT$3,$G29,0)-IF($H29=AT$3,$J29,0) | AU29: =IF($E29=AU$3,$G29,0)-IF($H29=AU$3,$J29,0) | AV29: =IF($E29=AV$3,$G29,0)-IF($H29=AV$3,$J29,0) | AW29: =IF($E29=AW$3,$G29,0)-IF($H29=AW$3,$J29,0) | ... BK29: =IF($E29=BK$3,$G29,0)-IF($H29=BK$3,$J29,0) | BL29: =-IF($E29=BL$3,$G29,0)+IF($H29=BL$3,$J29,0) | BM29: =-IF($E29=BM$3,$G29,0)+IF($H29=BM$3,$J29,0) | BN29: =-IF($E29=BN$3,$G29,0)+IF($H29=BN$3,$J29,0) | BO29: =-IF($E29=BO$3,$G29,0)+IF($H29=BO$3,$J29,0) | BP29: =-IF($E29=BP$3,$G29,0)+IF($H29=BP$3,$J29,0) | BQ29: =-IF($E29=BQ$3,$G29,0)+IF($H29=BQ$3,$J29,0) | BR29: =-IF($E29=BR$3,$G29,0)+IF($H29=BR$3,$J29,0) | BS29: =-IF($E29=BS$3,$G29,0)+IF($H29=BS$3,$J29,0) | BT29: =-IF($E29=BT$3,$G29,0)+IF($H29=BT$3,$J29,0) | BU29: =+G29-J29 | BV29: =-IF($E29=BV$3,$G29,0)+IF($H29=BV$3,$J29,0)
B30: 1 | C30: 19 | D30: エポス ガソリン代 | E30: 523 | F30: =IF(E30="","",IF(ISNA(VLOOKUP(E30,科目コード表!$C$4:$D$67,2,FALSE)),"該当科目なし",VLOOKUP(E30,科目コード表!$C$4:$D$67,2,FALSE))) | G30: 3097 | I30: =IF(H30="","",IF(ISNA(VLOOKUP(H30,科目コード表!$C$4:$D$67,2,FALSE)),"該当科目なし",VLOOKUP(H30,科目コード表!$C$4:$D$67,2,FALSE))) | L30: =IF($E30=L$3,$G30,0)-IF($H30=L$3,$J30,0) | M30: =IF($E30=M$3,$G30,0)-IF($H30=M$3,$J30,0) | N30: =IF($E30=N$3,$G30,0)-IF($H30=N$3,$J30,0) | O30: =IF($E30=O$3,$G30,0)-IF($H30=O$3,$J30,0) | P30: =IF($E30=P$3,$G30,0)-IF($H30=P$3,$J30,0) | Q30: =IF($E30=Q$3,$G30,0)-IF($H30=Q$3,$J30,0) | R30: =IF($E30=R$3,$G30,0)-IF($H30=R$3,$J30,0) | S30: =IF($E30=S$3,$G30,0)-IF($H30=S$3,$J30,0) | ... AL30: =IF($E30=AL$3,$G30,0)-IF($H30=AL$3,$J30,0) | AM30: =-IF($E30=AM$3,$G30,0)+IF($H30=AM$3,$J30,0) | AN30: =-IF($E30=AN$3,$G30,0)+IF($H30=AN$3,$J30,0) | AO30: =-IF($E30=AO$3,$G30,0)+IF($H30=AO$3,$J30,0) | AP30: =IF($E30=AP$3,$G30,0)-IF($H30=AP$3,$J30,0) | AQ30: =IF($E30=AQ$3,$G30,0)-IF($H30=AQ$3,$J30,0) | AR30: =IF($E30=AR$3,$G30,0)-IF($H30=AR$3,$J30,0) | AS30: =IF($E30=AS$3,$G30,0)-IF($H30=AS$3,$J30,0) | AT30: =IF($E30=AT$3,$G30,0)-IF($H30=AT$3,$J30,0) | AU30: =IF($E30=AU$3,$G30,0)-IF($H30=AU$3,$J30,0) | AV30: =IF($E30=AV$3,$G30,0)-IF($H30=AV$3,$J30,0) | AW30: =IF($E30=AW$3,$G30,0)-IF($H30=AW$3,$J30,0) | ... BK30: =IF($E30=BK$3,$G30,0)-IF($H30=BK$3,$J30,0) | BL30: =-IF($E30=BL$3,$G30,0)+IF($H30=BL$3,$J30,0) | BM30: =-IF($E30=BM$3,$G30,0)+IF($H30=BM$3,$J30,0) | BN30: =-IF($E30=BN$3,$G30,0)+IF($H30=BN$3,$J30,0) | BO30: =-IF($E30=BO$3,$G30,0)+IF($H30=BO$3,$J30,0) | BP30: =-IF($E30=BP$3,$G30,0)+IF($H30=BP$3,$J30,0) | BQ30: =-IF($E30=BQ$3,$G30,0)+IF($H30=BQ$3,$J30,0) | BR30: =-IF($E30=BR$3,$G30,0)+IF($H30=BR$3,$J30,0) | BS30: =-IF($E30=BS$3,$G30,0)+IF($H30=BS$3,$J30,0) | BT30: =-IF($E30=BT$3,$G30,0)+IF($H30=BT$3,$J30,0) | BU30: =+G30-J30 | BV30: =-IF($E30=BV$3,$G30,0)+IF($H30=BV$3,$J30,0)
B31: 1 | C31: 20 | D31: エポス Microsoft | E31: 525 | F31: =IF(E31="","",IF(ISNA(VLOOKUP(E31,科目コード表!$C$4:$D$67,2,FALSE)),"該当科目なし",VLOOKUP(E31,科目コード表!$C$4:$D$67,2,FALSE))) | G31: 2856 | I31: =IF(H31="","",IF(ISNA(VLOOKUP(H31,科目コード表!$C$4:$D$67,2,FALSE)),"該当科目なし",VLOOKUP(H31,科目コード表!$C$4:$D$67,2,FALSE))) | L31: =IF($E31=L$3,$G31,0)-IF($H31=L$3,$J31,0) | M31: =IF($E31=M$3,$G31,0)-IF($H31=M$3,$J31,0) | N31: =IF($E31=N$3,$G31,0)-IF($H31=N$3,$J31,0) | O31: =IF($E31=O$3,$G31,0)-IF($H31=O$3,$J31,0) | P31: =IF($E31=P$3,$G31,0)-IF($H31=P$3,$J31,0) | Q31: =IF($E31=Q$3,$G31,0)-IF($H31=Q$3,$J31,0) | R31: =IF($E31=R$3,$G31,0)-IF($H31=R$3,$J31,0) | S31: =IF($E31=S$3,$G31,0)-IF($H31=S$3,$J31,0) | ... AL31: =IF($E31=AL$3,$G31,0)-IF($H31=AL$3,$J31,0) | AM31: =-IF($E31=AM$3,$G31,0)+IF($H31=AM$3,$J31,0) | AN31: =-IF($E31=AN$3,$G31,0)+IF($H31=AN$3,$J31,0) | AO31: =-IF($E31=AO$3,$G31,0)+IF($H31=AO$3,$J31,0) | AP31: =IF($E31=AP$3,$G31,0)-IF($H31=AP$3,$J31,0) | AQ31: =IF($E31=AQ$3,$G31,0)-IF($H31=AQ$3,$J31,0) | AR31: =IF($E31=AR$3,$G31,0)-IF($H31=AR$3,$J31,0) | AS31: =IF($E31=AS$3,$G31,0)-IF($H31=AS$3,$J31,0) | AT31: =IF($E31=AT$3,$G31,0)-IF($H31=AT$3,$J31,0) | AU31: =IF($E31=AU$3,$G31,0)-IF($H31=AU$3,$J31,0) | AV31: =IF($E31=AV$3,$G31,0)-IF($H31=AV$3,$J31,0) | AW31: =IF($E31=AW$3,$G31,0)-IF($H31=AW$3,$J31,0) | ... BK31: =IF($E31=BK$3,$G31,0)-IF($H31=BK$3,$J31,0) | BL31: =-IF($E31=BL$3,$G31,0)+IF($H31=BL$3,$J31,0) | BM31: =-IF($E31=BM$3,$G31,0)+IF($H31=BM$3,$J31,0) | BN31: =-IF($E31=BN$3,$G31,0)+IF($H31=BN$3,$J31,0) | BO31: =-IF($E31=BO$3,$G31,0)+IF($H31=BO$3,$J31,0) | BP31: =-IF($E31=BP$3,$G31,0)+IF($H31=BP$3,$J31,0) | BQ31: =-IF($E31=BQ$3,$G31,0)+IF($H31=BQ$3,$J31,0) | BR31: =-IF($E31=BR$3,$G31,0)+IF($H31=BR$3,$J31,0) | BS31: =-IF($E31=BS$3,$G31,0)+IF($H31=BS$3,$J31,0) | BT31: =-IF($E31=BT$3,$G31,0)+IF($H31=BT$3,$J31,0) | BU31: =+G31-J31 | BV31: =-IF($E31=BV$3,$G31,0)+IF($H31=BV$3,$J31,0)
B32: 1 | C32: 21 | D32: ドアプロテクター | E32: 523 | F32: =IF(E32="","",IF(ISNA(VLOOKUP(E32,科目コード表!$C$4:$D$67,2,FALSE)),"該当科目なし",VLOOKUP(E32,科目コード表!$C$4:$D$67,2,FALSE))) | G32: 859 | I32: =IF(H32="","",IF(ISNA(VLOOKUP(H32,科目コード表!$C$4:$D$67,2,FALSE)),"該当科目なし",VLOOKUP(H32,科目コード表!$C$4:$D$67,2,FALSE))) | L32: =IF($E32=L$3,$G32,0)-IF($H32=L$3,$J32,0) | M32: =IF($E32=M$3,$G32,0)-IF($H32=M$3,$J32,0) | N32: =IF($E32=N$3,$G32,0)-IF($H32=N$3,$J32,0) | O32: =IF($E32=O$3,$G32,0)-IF($H32=O$3,$J32,0) | P32: =IF($E32=P$3,$G32,0)-IF($H32=P$3,$J32,0) | Q32: =IF($E32=Q$3,$G32,0)-IF($H32=Q$3,$J32,0) | R32: =IF($E32=R$3,$G32,0)-IF($H32=R$3,$J32,0) | S32: =IF($E32=S$3,$G32,0)-IF($H32=S$3,$J32,0) | ... AL32: =IF($E32=AL$3,$G32,0)-IF($H32=AL$3,$J32,0) | AM32: =-IF($E32=AM$3,$G32,0)+IF($H32=AM$3,$J32,0) | AN32: =-IF($E32=AN$3,$G32,0)+IF($H32=AN$3,$J32,0) | AO32: =-IF($E32=AO$3,$G32,0)+IF($H32=AO$3,$J32,0) | AP32: =IF($E32=AP$3,$G32,0)-IF($H32=AP$3,$J32,0) | AQ32: =IF($E32=AQ$3,$G32,0)-IF($H32=AQ$3,$J32,0) | AR32: =IF($E32=AR$3,$G32,0)-IF($H32=AR$3,$J32,0) | AS32: =IF($E32=AS$3,$G32,0)-IF($H32=AS$3,$J32,0) | AT32: =IF($E32=AT$3,$G32,0)-IF($H32=AT$3,$J32,0) | AU32: =IF($E32=AU$3,$G32,0)-IF($H32=AU$3,$J32,0) | AV32: =IF($E32=AV$3,$G32,0)-IF($H32=AV$3,$J32,0) | AW32: =IF($E32=AW$3,$G32,0)-IF($H32=AW$3,$J32,0) | ... BK32: =IF($E32=BK$3,$G32,0)-IF($H32=BK$3,$J32,0) | BL32: =-IF($E32=BL$3,$G32,0)+IF($H32=BL$3,$J32,0) | BM32: =-IF($E32=BM$3,$G32,0)+IF($H32=BM$3,$J32,0) | BN32: =-IF($E32=BN$3,$G32,0)+IF($H32=BN$3,$J32,0) | BO32: =-IF($E32=BO$3,$G32,0)+IF($H32=BO$3,$J32,0) | BP32: =-IF($E32=BP$3,$G32,0)+IF($H32=BP$3,$J32,0) | BQ32: =-IF($E32=BQ$3,$G32,0)+IF($H32=BQ$3,$J32,0) | BR32: =-IF($E32=BR$3,$G32,0)+IF($H32=BR$3,$J32,0) | BS32: =-IF($E32=BS$3,$G32,0)+IF($H32=BS$3,$J32,0) | BT32: =-IF($E32=BT$3,$G32,0)+IF($H32=BT$3,$J32,0) | BU32: =+G32-J32 | BV32: =-IF($E32=BV$3,$G32,0)+IF($H32=BV$3,$J32,0)
B33: 1 | C33: 21 | D33: Bluetooth 5.4 対応 USB | E33: 514 | F33: =IF(E33="","",IF(ISNA(VLOOKUP(E33,科目コード表!$C$4:$D$67,2,FALSE)),"該当科目なし",VLOOKUP(E33,科目コード表!$C$4:$D$67,2,FALSE))) | G33: 1190 | I33: =IF(H33="","",IF(ISNA(VLOOKUP(H33,科目コード表!$C$4:$D$67,2,FALSE)),"該当科目なし",VLOOKUP(H33,科目コード表!$C$4:$D$67,2,FALSE))) | L33: =IF($E33=L$3,$G33,0)-IF($H33=L$3,$J33,0) | M33: =IF($E33=M$3,$G33,0)-IF($H33=M$3,$J33,0) | N33: =IF($E33=N$3,$G33,0)-IF($H33=N$3,$J33,0) | O33: =IF($E33=O$3,$G33,0)-IF($H33=O$3,$J33,0) | P33: =IF($E33=P$3,$G33,0)-IF($H33=P$3,$J33,0) | Q33: =IF($E33=Q$3,$G33,0)-IF($H33=Q$3,$J33,0) | R33: =IF($E33=R$3,$G33,0)-IF($H33=R$3,$J33,0) | S33: =IF($E33=S$3,$G33,0)-IF($H33=S$3,$J33,0) | ... AL33: =IF($E33=AL$3,$G33,0)-IF($H33=AL$3,$J33,0) | AM33: =-IF($E33=AM$3,$G33,0)+IF($H33=AM$3,$J33,0) | AN33: =-IF($E33=AN$3,$G33,0)+IF($H33=AN$3,$J33,0) | AO33: =-IF($E33=AO$3,$G33,0)+IF($H33=AO$3,$J33,0) | AP33: =IF($E33=AP$3,$G33,0)-IF($H33=AP$3,$J33,0) | AQ33: =IF($E33=AQ$3,$G33,0)-IF($H33=AQ$3,$J33,0) | AR33: =IF($E33=AR$3,$G33,0)-IF($H33=AR$3,$J33,0) | AS33: =IF($E33=AS$3,$G33,0)-IF($H33=AS$3,$J33,0) | AT33: =IF($E33=AT$3,$G33,0)-IF($H33=AT$3,$J33,0) | AU33: =IF($E33=AU$3,$G33,0)-IF($H33=AU$3,$J33,0) | AV33: =IF($E33=AV$3,$G33,0)-IF($H33=AV$3,$J33,0) | AW33: =IF($E33=AW$3,$G33,0)-IF($H33=AW$3,$J33,0) | ... BK33: =IF($E33=BK$3,$G33,0)-IF($H33=BK$3,$J33,0) | BL33: =-IF($E33=BL$3,$G33,0)+IF($H33=BL$3,$J33,0) | BM33: =-IF($E33=BM$3,$G33,0)+IF($H33=BM$3,$J33,0) | BN33: =-IF($E33=BN$3,$G33,0)+IF($H33=BN$3,$J33,0) | BO33: =-IF($E33=BO$3,$G33,0)+IF($H33=BO$3,$J33,0) | BP33: =-IF($E33=BP$3,$G33,0)+IF($H33=BP$3,$J33,0) | BQ33: =-IF($E33=BQ$3,$G33,0)+IF($H33=BQ$3,$J33,0) | BR33: =-IF($E33=BR$3,$G33,0)+IF($H33=BR$3,$J33,0) | BS33: =-IF($E33=BS$3,$G33,0)+IF($H33=BS$3,$J33,0) | BT33: =-IF($E33=BT$3,$G33,0)+IF($H33=BT$3,$J33,0) | BU33: =+G33-J33 | BV33: =-IF($E33=BV$3,$G33,0)+IF($H33=BV$3,$J33,0)
B34: 1 | C34: 22 | D34: トランクネット | E34: 523 | F34: =IF(E34="","",IF(ISNA(VLOOKUP(E34,科目コード表!$C$4:$D$67,2,FALSE)),"該当科目なし",VLOOKUP(E34,科目コード表!$C$4:$D$67,2,FALSE))) | G34: 999 | I34: =IF(H34="","",IF(ISNA(VLOOKUP(H34,科目コード表!$C$4:$D$67,2,FALSE)),"該当科目なし",VLOOKUP(H34,科目コード表!$C$4:$D$67,2,FALSE))) | L34: =IF($E34=L$3,$G34,0)-IF($H34=L$3,$J34,0) | M34: =IF($E34=M$3,$G34,0)-IF($H34=M$3,$J34,0) | N34: =IF($E34=N$3,$G34,0)-IF($H34=N$3,$J34,0) | O34: =IF($E34=O$3,$G34,0)-IF($H34=O$3,$J34,0) | P34: =IF($E34=P$3,$G34,0)-IF($H34=P$3,$J34,0) | Q34: =IF($E34=Q$3,$G34,0)-IF($H34=Q$3,$J34,0) | R34: =IF($E34=R$3,$G34,0)-IF($H34=R$3,$J34,0) | S34: =IF($E34=S$3,$G34,0)-IF($H34=S$3,$J34,0) | ... AL34: =IF($E34=AL$3,$G34,0)-IF($H34=AL$3,$J34,0) | AM34: =-IF($E34=AM$3,$G34,0)+IF($H34=AM$3,$J34,0) | AN34: =-IF($E34=AN$3,$G34,0)+IF($H34=AN$3,$J34,0) | AO34: =-IF($E34=AO$3,$G34,0)+IF($H34=AO$3,$J34,0) | AP34: =IF($E34=AP$3,$G34,0)-IF($H34=AP$3,$J34,0) | AQ34: =IF($E34=AQ$3,$G34,0)-IF($H34=AQ$3,$J34,0) | AR34: =IF($E34=AR$3,$G34,0)-IF($H34=AR$3,$J34,0) | AS34: =IF($E34=AS$3,$G34,0)-IF($H34=AS$3,$J34,0) | AT34: =IF($E34=AT$3,$G34,0)-IF($H34=AT$3,$J34,0) | AU34: =IF($E34=AU$3,$G34,0)-IF($H34=AU$3,$J34,0) | AV34: =IF($E34=AV$3,$G34,0)-IF($H34=AV$3,$J34,0) | AW34: =IF($E34=AW$3,$G34,0)-IF($H34=AW$3,$J34,0) | ... BK34: =IF($E34=BK$3,$G34,0)-IF($H34=BK$3,$J34,0) | BL34: =-IF($E34=BL$3,$G34,0)+IF($H34=BL$3,$J34,0) | BM34: =-IF($E34=BM$3,$G34,0)+IF($H34=BM$3,$J34,0) | BN34: =-IF($E34=BN$3,$G34,0)+IF($H34=BN$3,$J34,0) | BO34: =-IF($E34=BO$3,$G34,0)+IF($H34=BO$3,$J34,0) | BP34: =-IF($E34=BP$3,$G34,0)+IF($H34=BP$3,$J34,0) | BQ34: =-IF($E34=BQ$3,$G34,0)+IF($H34=BQ$3,$J34,0) | BR34: =-IF($E34=BR$3,$G34,0)+IF($H34=BR$3,$J34,0) | BS34: =-IF($E34=BS$3,$G34,0)+IF($H34=BS$3,$J34,0) | BT34: =-IF($E34=BT$3,$G34,0)+IF($H34=BT$3,$J34,0) | BU34: =+G34-J34 | BV34: =-IF($E34=BV$3,$G34,0)+IF($H34=BV$3,$J34,0)
B35: 1 | C35: 22 | D35: 荷掛けフック | E35: 523 | F35: =IF(E35="","",IF(ISNA(VLOOKUP(E35,科目コード表!$C$4:$D$67,2,FALSE)),"該当科目なし",VLOOKUP(E35,科目コード表!$C$4:$D$67,2,FALSE))) | G35: 849 | I35: =IF(H35="","",IF(ISNA(VLOOKUP(H35,科目コード表!$C$4:$D$67,2,FALSE)),"該当科目なし",VLOOKUP(H35,科目コード表!$C$4:$D$67,2,FALSE))) | L35: =IF($E35=L$3,$G35,0)-IF($H35=L$3,$J35,0) | M35: =IF($E35=M$3,$G35,0)-IF($H35=M$3,$J35,0) | N35: =IF($E35=N$3,$G35,0)-IF($H35=N$3,$J35,0) | O35: =IF($E35=O$3,$G35,0)-IF($H35=O$3,$J35,0) | P35: =IF($E35=P$3,$G35,0)-IF($H35=P$3,$J35,0) | Q35: =IF($E35=Q$3,$G35,0)-IF($H35=Q$3,$J35,0) | R35: =IF($E35=R$3,$G35,0)-IF($H35=R$3,$J35,0) | S35: =IF($E35=S$3,$G35,0)-IF($H35=S$3,$J35,0) | ... AL35: =IF($E35=AL$3,$G35,0)-IF($H35=AL$3,$J35,0) | AM35: =-IF($E35=AM$3,$G35,0)+IF($H35=AM$3,$J35,0) | AN35: =-IF($E35=AN$3,$G35,0)+IF($H35=AN$3,$J35,0) | AO35: =-IF($E35=AO$3,$G35,0)+IF($H35=AO$3,$J35,0) | AP35: =IF($E35=AP$3,$G35,0)-IF($H35=AP$3,$J35,0) | AQ35: =IF($E35=AQ$3,$G35,0)-IF($H35=AQ$3,$J35,0) | AR35: =IF($E35=AR$3,$G35,0)-IF($H35=AR$3,$J35,0) | AS35: =IF($E35=AS$3,$G35,0)-IF($H35=AS$3,$J35,0) | AT35: =IF($E35=AT$3,$G35,0)-IF($H35=AT$3,$J35,0) | AU35: =IF($E35=AU$3,$G35,0)-IF($H35=AU$3,$J35,0) | AV35: =IF($E35=AV$3,$G35,0)-IF($H35=AV$3,$J35,0) | AW35: =IF($E35=AW$3,$G35,0)-IF($H35=AW$3,$J35,0) | ... BK35: =IF($E35=BK$3,$G35,0)-IF($H35=BK$3,$J35,0) | BL35: =-IF($E35=BL$3,$G35,0)+IF($H35=BL$3,$J35,0) | BM35: =-IF($E35=BM$3,$G35,0)+IF($H35=BM$3,$J35,0) | BN35: =-IF($E35=BN$3,$G35,0)+IF($H35=BN$3,$J35,0) | BO35: =-IF($E35=BO$3,$G35,0)+IF($H35=BO$3,$J35,0) | BP35: =-IF($E35=BP$3,$G35,0)+IF($H35=BP$3,$J35,0) | BQ35: =-IF($E35=BQ$3,$G35,0)+IF($H35=BQ$3,$J35,0) | BR35: =-IF($E35=BR$3,$G35,0)+IF($H35=BR$3,$J35,0) | BS35: =-IF($E35=BS$3,$G35,0)+IF($H35=BS$3,$J35,0) | BT35: =-IF($E35=BT$3,$G35,0)+IF($H35=BT$3,$J35,0) | BU35: =+G35-J35 | BV35: =-IF($E35=BV$3,$G35,0)+IF($H35=BV$3,$J35,0)
B36: 1 | C36: 24 | D36: クランプノブ M4 | E36: 523 | F36: =IF(E36="","",IF(ISNA(VLOOKUP(E36,科目コード表!$C$4:$D$67,2,FALSE)),"該当科目なし",VLOOKUP(E36,科目コード表!$C$4:$D$67,2,FALSE))) | G36: 999 | I36: =IF(H36="","",IF(ISNA(VLOOKUP(H36,科目コード表!$C$4:$D$67,2,FALSE)),"該当科目なし",VLOOKUP(H36,科目コード表!$C$4:$D$67,2,FALSE))) | L36: =IF($E36=L$3,$G36,0)-IF($H36=L$3,$J36,0) | M36: =IF($E36=M$3,$G36,0)-IF($H36=M$3,$J36,0) | N36: =IF($E36=N$3,$G36,0)-IF($H36=N$3,$J36,0) | O36: =IF($E36=O$3,$G36,0)-IF($H36=O$3,$J36,0) | P36: =IF($E36=P$3,$G36,0)-IF($H36=P$3,$J36,0) | Q36: =IF($E36=Q$3,$G36,0)-IF($H36=Q$3,$J36,0) | R36: =IF($E36=R$3,$G36,0)-IF($H36=R$3,$J36,0) | S36: =IF($E36=S$3,$G36,0)-IF($H36=S$3,$J36,0) | ... AL36: =IF($E36=AL$3,$G36,0)-IF($H36=AL$3,$J36,0) | AM36: =-IF($E36=AM$3,$G36,0)+IF($H36=AM$3,$J36,0) | AN36: =-IF($E36=AN$3,$G36,0)+IF($H36=AN$3,$J36,0) | AO36: =-IF($E36=AO$3,$G36,0)+IF($H36=AO$3,$J36,0) | AP36: =IF($E36=AP$3,$G36,0)-IF($H36=AP$3,$J36,0) | AQ36: =IF($E36=AQ$3,$G36,0)-IF($H36=AQ$3,$J36,0) | AR36: =IF($E36=AR$3,$G36,0)-IF($H36=AR$3,$J36,0) | AS36: =IF($E36=AS$3,$G36,0)-IF($H36=AS$3,$J36,0) | AT36: =IF($E36=AT$3,$G36,0)-IF($H36=AT$3,$J36,0) | AU36: =IF($E36=AU$3,$G36,0)-IF($H36=AU$3,$J36,0) | AV36: =IF($E36=AV$3,$G36,0)-IF($H36=AV$3,$J36,0) | AW36: =IF($E36=AW$3,$G36,0)-IF($H36=AW$3,$J36,0) | ... BK36: =IF($E36=BK$3,$G36,0)-IF($H36=BK$3,$J36,0) | BL36: =-IF($E36=BL$3,$G36,0)+IF($H36=BL$3,$J36,0) | BM36: =-IF($E36=BM$3,$G36,0)+IF($H36=BM$3,$J36,0) | BN36: =-IF($E36=BN$3,$G36,0)+IF($H36=BN$3,$J36,0) | BO36: =-IF($E36=BO$3,$G36,0)+IF($H36=BO$3,$J36,0) | BP36: =-IF($E36=BP$3,$G36,0)+IF($H36=BP$3,$J36,0) | BQ36: =-IF($E36=BQ$3,$G36,0)+IF($H36=BQ$3,$J36,0) | BR36: =-IF($E36=BR$3,$G36,0)+IF($H36=BR$3,$J36,0) | BS36: =-IF($E36=BS$3,$G36,0)+IF($H36=BS$3,$J36,0) | BT36: =-IF($E36=BT$3,$G36,0)+IF($H36=BT$3,$J36,0) | BU36: =+G36-J36 | BV36: =-IF($E36=BV$3,$G36,0)+IF($H36=BV$3,$J36,0)
B37: 1 | C37: 24 | D37: 楽天 ナビ保護フィルム | E37: 523 | F37: =IF(E37="","",IF(ISNA(VLOOKUP(E37,科目コード表!$C$4:$D$67,2,FALSE)),"該当科目なし",VLOOKUP(E37,科目コード表!$C$4:$D$67,2,FALSE))) | G37: 1280 | I37: =IF(H37="","",IF(ISNA(VLOOKUP(H37,科目コード表!$C$4:$D$67,2,FALSE)),"該当科目なし",VLOOKUP(H37,科目コード表!$C$4:$D$67,2,FALSE))) | L37: =IF($E37=L$3,$G37,0)-IF($H37=L$3,$J37,0) | M37: =IF($E37=M$3,$G37,0)-IF($H37=M$3,$J37,0) | N37: =IF($E37=N$3,$G37,0)-IF($H37=N$3,$J37,0) | O37: =IF($E37=O$3,$G37,0)-IF($H37=O$3,$J37,0) | P37: =IF($E37=P$3,$G37,0)-IF($H37=P$3,$J37,0) | Q37: =IF($E37=Q$3,$G37,0)-IF($H37=Q$3,$J37,0) | R37: =IF($E37=R$3,$G37,0)-IF($H37=R$3,$J37,0) | S37: =IF($E37=S$3,$G37,0)-IF($H37=S$3,$J37,0) | ... AL37: =IF($E37=AL$3,$G37,0)-IF($H37=AL$3,$J37,0) | AM37: =-IF($E37=AM$3,$G37,0)+IF($H37=AM$3,$J37,0) | AN37: =-IF($E37=AN$3,$G37,0)+IF($H37=AN$3,$J37,0) | AO37: =-IF($E37=AO$3,$G37,0)+IF($H37=AO$3,$J37,0) | AP37: =IF($E37=AP$3,$G37,0)-IF($H37=AP$3,$J37,0) | AQ37: =IF($E37=AQ$3,$G37,0)-IF($H37=AQ$3,$J37,0) | AR37: =IF($E37=AR$3,$G37,0)-IF($H37=AR$3,$J37,0) | AS37: =IF($E37=AS$3,$G37,0)-IF($H37=AS$3,$J37,0) | AT37: =IF($E37=AT$3,$G37,0)-IF($H37=AT$3,$J37,0) | AU37: =IF($E37=AU$3,$G37,0)-IF($H37=AU$3,$J37,0) | AV37: =IF($E37=AV$3,$G37,0)-IF($H37=AV$3,$J37,0) | AW37: =IF($E37=AW$3,$G37,0)-IF($H37=AW$3,$J37,0) | ... BK37: =IF($E37=BK$3,$G37,0)-IF($H37=BK$3,$J37,0) | BL37: =-IF($E37=BL$3,$G37,0)+IF($H37=BL$3,$J37,0) | BM37: =-IF($E37=BM$3,$G37,0)+IF($H37=BM$3,$J37,0) | BN37: =-IF($E37=BN$3,$G37,0)+IF($H37=BN$3,$J37,0) | BO37: =-IF($E37=BO$3,$G37,0)+IF($H37=BO$3,$J37,0) | BP37: =-IF($E37=BP$3,$G37,0)+IF($H37=BP$3,$J37,0) | BQ37: =-IF($E37=BQ$3,$G37,0)+IF($H37=BQ$3,$J37,0) | BR37: =-IF($E37=BR$3,$G37,0)+IF($H37=BR$3,$J37,0) | BS37: =-IF($E37=BS$3,$G37,0)+IF($H37=BS$3,$J37,0) | BT37: =-IF($E37=BT$3,$G37,0)+IF($H37=BT$3,$J37,0) | BU37: =+G37-J37 | BV37: =-IF($E37=BV$3,$G37,0)+IF($H37=BV$3,$J37,0)
B38: 1 | C38: 25 | D38: スマホスタンド ホルダー | E38: 523 | F38: =IF(E38="","",IF(ISNA(VLOOKUP(E38,科目コード表!$C$4:$D$67,2,FALSE)),"該当科目なし",VLOOKUP(E38,科目コード表!$C$4:$D$67,2,FALSE))) | G38: 899 | I38: =IF(H38="","",IF(ISNA(VLOOKUP(H38,科目コード表!$C$4:$D$67,2,FALSE)),"該当科目なし",VLOOKUP(H38,科目コード表!$C$4:$D$67,2,FALSE))) | L38: =IF($E38=L$3,$G38,0)-IF($H38=L$3,$J38,0) | M38: =IF($E38=M$3,$G38,0)-IF($H38=M$3,$J38,0) | N38: =IF($E38=N$3,$G38,0)-IF($H38=N$3,$J38,0) | O38: =IF($E38=O$3,$G38,0)-IF($H38=O$3,$J38,0) | P38: =IF($E38=P$3,$G38,0)-IF($H38=P$3,$J38,0) | Q38: =IF($E38=Q$3,$G38,0)-IF($H38=Q$3,$J38,0) | R38: =IF($E38=R$3,$G38,0)-IF($H38=R$3,$J38,0) | S38: =IF($E38=S$3,$G38,0)-IF($H38=S$3,$J38,0) | ... AL38: =IF($E38=AL$3,$G38,0)-IF($H38=AL$3,$J38,0) | AM38: =-IF($E38=AM$3,$G38,0)+IF($H38=AM$3,$J38,0) | AN38: =-IF($E38=AN$3,$G38,0)+IF($H38=AN$3,$J38,0) | AO38: =-IF($E38=AO$3,$G38,0)+IF($H38=AO$3,$J38,0) | AP38: =IF($E38=AP$3,$G38,0)-IF($H38=AP$3,$J38,0) | AQ38: =IF($E38=AQ$3,$G38,0)-IF($H38=AQ$3,$J38,0) | AR38: =IF($E38=AR$3,$G38,0)-IF($H38=AR$3,$J38,0) | AS38: =IF($E38=AS$3,$G38,0)-IF($H38=AS$3,$J38,0) | AT38: =IF($E38=AT$3,$G38,0)-IF($H38=AT$3,$J38,0) | AU38: =IF($E38=AU$3,$G38,0)-IF($H38=AU$3,$J38,0) | AV38: =IF($E38=AV$3,$G38,0)-IF($H38=AV$3,$J38,0) | AW38: =IF($E38=AW$3,$G38,0)-IF($H38=AW$3,$J38,0) | ... BK38: =IF($E38=BK$3,$G38,0)-IF($H38=BK$3,$J38,0) | BL38: =-IF($E38=BL$3,$G38,0)+IF($H38=BL$3,$J38,0) | BM38: =-IF($E38=BM$3,$G38,0)+IF($H38=BM$3,$J38,0) | BN38: =-IF($E38=BN$3,$G38,0)+IF($H38=BN$3,$J38,0) | BO38: =-IF($E38=BO$3,$G38,0)+IF($H38=BO$3,$J38,0) | BP38: =-IF($E38=BP$3,$G38,0)+IF($H38=BP$3,$J38,0) | BQ38: =-IF($E38=BQ$3,$G38,0)+IF($H38=BQ$3,$J38,0) | BR38: =-IF($E38=BR$3,$G38,0)+IF($H38=BR$3,$J38,0) | BS38: =-IF($E38=BS$3,$G38,0)+IF($H38=BS$3,$J38,0) | BT38: =-IF($E38=BT$3,$G38,0)+IF($H38=BT$3,$J38,0) | BU38: =+G38-J38 | BV38: =-IF($E38=BV$3,$G38,0)+IF($H38=BV$3,$J38,0)
... B42: 1 | C42: 29 | D42: エポス さくらインターネット | E42: 525 | F42: =IF(E42="","",IF(ISNA(VLOOKUP(E42,科目コード表!$C$4:$D$67,2,FALSE)),"該当科目なし",VLOOKUP(E42,科目コード表!$C$4:$D$67,2,FALSE))) | G42: 7700 | I42: =IF(H42="","",IF(ISNA(VLOOKUP(H42,科目コード表!$C$4:$D$67,2,FALSE)),"該当科目なし",VLOOKUP(H42,科目コード表!$C$4:$D$67,2,FALSE))) | L42: =IF($E42=L$3,$G42,0)-IF($H42=L$3,$J42,0) | M42: =IF($E42=M$3,$G42,0)-IF($H42=M$3,$J42,0) | N42: =IF($E42=N$3,$G42,0)-IF($H42=N$3,$J42,0) | O42: =IF($E42=O$3,$G42,0)-IF($H42=O$3,$J42,0) | P42: =IF($E42=P$3,$G42,0)-IF($H42=P$3,$J42,0) | Q42: =IF($E42=Q$3,$G42,0)-IF($H42=Q$3,$J42,0) | R42: =IF($E42=R$3,$G42,0)-IF($H42=R$3,$J42,0) | S42: =IF($E42=S$3,$G42,0)-IF($H42=S$3,$J42,0) | ... AL42: =IF($E42=AL$3,$G42,0)-IF($H42=AL$3,$J42,0) | AM42: =-IF($E42=AM$3,$G42,0)+IF($H42=AM$3,$J42,0) | AN42: =-IF($E42=AN$3,$G42,0)+IF($H42=AN$3,$J42,0) | AO42: =-IF($E42=AO$3,$G42,0)+IF($H42=AO$3,$J42,0) | AP42: =IF($E42=AP$3,$G42,0)-IF($H42=AP$3,$J42,0) | AQ42: =IF($E42=AQ$3,$G42,0)-IF($H42=AQ$3,$J42,0) | AR42: =IF($E42=AR$3,$G42,0)-IF($H42=AR$3,$J42,0) | AS42: =IF($E42=AS$3,$G42,0)-IF($H42=AS$3,$J42,0) | AT42: =IF($E42=AT$3,$G42,0)-IF($H42=AT$3,$J42,0) | AU42: =IF($E42=AU$3,$G42,0)-IF($H42=AU$3,$J42,0) | AV42: =IF($E42=AV$3,$G42,0)-IF($H42=AV$3,$J42,0) | AW42: =IF($E42=AW$3,$G42,0)-IF($H42=AW$3,$J42,0) | ... BK42: =IF($E42=BK$3,$G42,0)-IF($H42=BK$3,$J42,0) | BL42: =-IF($E42=BL$3,$G42,0)+IF($H42=BL$3,$J42,0) | BM42: =-IF($E42=BM$3,$G42,0)+IF($H42=BM$3,$J42,0) | BN42: =-IF($E42=BN$3,$G42,0)+IF($H42=BN$3,$J42,0) | BO42: =-IF($E42=BO$3,$G42,0)+IF($H42=BO$3,$J42,0) | BP42: =-IF($E42=BP$3,$G42,0)+IF($H42=BP$3,$J42,0) | BQ42: =-IF($E42=BQ$3,$G42,0)+IF($H42=BQ$3,$J42,0) | BR42: =-IF($E42=BR$3,$G42,0)+IF($H42=BR$3,$J42,0) | BS42: =-IF($E42=BS$3,$G42,0)+IF($H42=BS$3,$J42,0) | BT42: =-IF($E42=BT$3,$G42,0)+IF($H42=BT$3,$J42,0) | BU42: =+G42-J42 | BV42: =-IF($E42=BV$3,$G42,0)+IF($H42=BV$3,$J42,0)
B43: 1 | C43: 30 | D43: セレサ川崎 BASIS入金 | F43: =IF(E43="","",IF(ISNA(VLOOKUP(E43,科目コード表!$C$4:$D$67,2,FALSE)),"該当科目なし",VLOOKUP(E43,科目コード表!$C$4:$D$67,2,FALSE))) | H43: 107 | I43: =IF(H43="","",IF(ISNA(VLOOKUP(H43,科目コード表!$C$4:$D$67,2,FALSE)),"該当科目なし",VLOOKUP(H43,科目コード表!$C$4:$D$67,2,FALSE))) | J43: 1237500 | L43: =IF($E43=L$3,$G43,0)-IF($H43=L$3,$J43,0) | M43: =IF($E43=M$3,$G43,0)-IF($H43=M$3,$J43,0) | N43: =IF($E43=N$3,$G43,0)-IF($H43=N$3,$J43,0) | O43: =IF($E43=O$3,$G43,0)-IF($H43=O$3,$J43,0) | P43: =IF($E43=P$3,$G43,0)-IF($H43=P$3,$J43,0) | Q43: =IF($E43=Q$3,$G43,0)-IF($H43=Q$3,$J43,0) | R43: =IF($E43=R$3,$G43,0)-IF($H43=R$3,$J43,0) | S43: =IF($E43=S$3,$G43,0)-IF($H43=S$3,$J43,0) | ... AL43: =IF($E43=AL$3,$G43,0)-IF($H43=AL$3,$J43,0) | AM43: =-IF($E43=AM$3,$G43,0)+IF($H43=AM$3,$J43,0) | AN43: =-IF($E43=AN$3,$G43,0)+IF($H43=AN$3,$J43,0) | AO43: =-IF($E43=AO$3,$G43,0)+IF($H43=AO$3,$J43,0) | AP43: =IF($E43=AP$3,$G43,0)-IF($H43=AP$3,$J43,0) | AQ43: =IF($E43=AQ$3,$G43,0)-IF($H43=AQ$3,$J43,0) | AR43: =IF($E43=AR$3,$G43,0)-IF($H43=AR$3,$J43,0) | AS43: =IF($E43=AS$3,$G43,0)-IF($H43=AS$3,$J43,0) | AT43: =IF($E43=AT$3,$G43,0)-IF($H43=AT$3,$J43,0) | AU43: =IF($E43=AU$3,$G43,0)-IF($H43=AU$3,$J43,0) | AV43: =IF($E43=AV$3,$G43,0)-IF($H43=AV$3,$J43,0) | AW43: =IF($E43=AW$3,$G43,0)-IF($H43=AW$3,$J43,0) | ... BK43: =IF($E43=BK$3,$G43,0)-IF($H43=BK$3,$J43,0) | BL43: =-IF($E43=BL$3,$G43,0)+IF($H43=BL$3,$J43,0) | BM43: =-IF($E43=BM$3,$G43,0)+IF($H43=BM$3,$J43,0) | BN43: =-IF($E43=BN$3,$G43,0)+IF($H43=BN$3,$J43,0) | BO43: =-IF($E43=BO$3,$G43,0)+IF($H43=BO$3,$J43,0) | BP43: =-IF($E43=BP$3,$G43,0)+IF($H43=BP$3,$J43,0) | BQ43: =-IF($E43=BQ$3,$G43,0)+IF($H43=BQ$3,$J43,0) | BR43: =-IF($E43=BR$3,$G43,0)+IF($H43=BR$3,$J43,0) | BS43: =-IF($E43=BS$3,$G43,0)+IF($H43=BS$3,$J43,0) | BT43: =-IF($E43=BT$3,$G43,0)+IF($H43=BT$3,$J43,0) | BU43: =+G43-J43 | BV43: =-IF($E43=BV$3,$G43,0)+IF($H43=BV$3,$J43,0)
B44: 1 | C44: 31 | D44: 売上 小樽商科大学後援会 | E44: 107 | F44: =IF(E44="","",IF(ISNA(VLOOKUP(E44,科目コード表!$C$4:$D$67,2,FALSE)),"該当科目なし",VLOOKUP(E44,科目コード表!$C$4:$D$67,2,FALSE))) | G44: 11000 | H44: 401 | I44: =IF(H44="","",IF(ISNA(VLOOKUP(H44,科目コード表!$C$4:$D$67,2,FALSE)),"該当科目なし",VLOOKUP(H44,科目コード表!$C$4:$D$67,2,FALSE))) | J44: 11000 | L44: =IF($E44=L$3,$G44,0)-IF($H44=L$3,$J44,0) | M44: =IF($E44=M$3,$G44,0)-IF($H44=M$3,$J44,0) | N44: =IF($E44=N$3,$G44,0)-IF($H44=N$3,$J44,0) | O44: =IF($E44=O$3,$G44,0)-IF($H44=O$3,$J44,0) | P44: =IF($E44=P$3,$G44,0)-IF($H44=P$3,$J44,0) | Q44: =IF($E44=Q$3,$G44,0)-IF($H44=Q$3,$J44,0) | R44: =IF($E44=R$3,$G44,0)-IF($H44=R$3,$J44,0) | S44: =IF($E44=S$3,$G44,0)-IF($H44=S$3,$J44,0) | ... AL44: =IF($E44=AL$3,$G44,0)-IF($H44=AL$3,$J44,0) | AM44: =-IF($E44=AM$3,$G44,0)+IF($H44=AM$3,$J44,0) | AN44: =-IF($E44=AN$3,$G44,0)+IF($H44=AN$3,$J44,0) | AO44: =-IF($E44=AO$3,$G44,0)+IF($H44=AO$3,$J44,0) | AP44: =IF($E44=AP$3,$G44,0)-IF($H44=AP$3,$J44,0) | AQ44: =IF($E44=AQ$3,$G44,0)-IF($H44=AQ$3,$J44,0) | AR44: =IF($E44=AR$3,$G44,0)-IF($H44=AR$3,$J44,0) | AS44: =IF($E44=AS$3,$G44,0)-IF($H44=AS$3,$J44,0) | AT44: =IF($E44=AT$3,$G44,0)-IF($H44=AT$3,$J44,0) | AU44: =IF($E44=AU$3,$G44,0)-IF($H44=AU$3,$J44,0) | AV44: =IF($E44=AV$3,$G44,0)-IF($H44=AV$3,$J44,0) | AW44: =IF($E44=AW$3,$G44,0)-IF($H44=AW$3,$J44,0) | ... BK44: =IF($E44=BK$3,$G44,0)-IF($H44=BK$3,$J44,0) | BL44: =-IF($E44=BL$3,$G44,0)+IF($H44=BL$3,$J44,0) | BM44: =-IF($E44=BM$3,$G44,0)+IF($H44=BM$3,$J44,0) | BN44: =-IF($E44=BN$3,$G44,0)+IF($H44=BN$3,$J44,0) | BO44: =-IF($E44=BO$3,$G44,0)+IF($H44=BO$3,$J44,0) | BP44: =-IF($E44=BP$3,$G44,0)+IF($H44=BP$3,$J44,0) | BQ44: =-IF($E44=BQ$3,$G44,0)+IF($H44=BQ$3,$J44,0) | BR44: =-IF($E44=BR$3,$G44,0)+IF($H44=BR$3,$J44,0) | BS44: =-IF($E44=BS$3,$G44,0)+IF($H44=BS$3,$J44,0) | BT44: =-IF($E44=BT$3,$G44,0)+IF($H44=BT$3,$J44,0) | BU44: =+G44-J44 | BV44: =-IF($E44=BV$3,$G44,0)+IF($H44=BV$3,$J44,0)
B45: 1 | C45: 31 | D45: 売上 ユーユー | E45: 107 | F45: =IF(E45="","",IF(ISNA(VLOOKUP(E45,科目コード表!$C$4:$D$67,2,FALSE)),"該当科目なし",VLOOKUP(E45,科目コード表!$C$4:$D$67,2,FALSE))) | G45: 100000 | H45: 401 | I45: =IF(H45="","",IF(ISNA(VLOOKUP(H45,科目コード表!$C$4:$D$67,2,FALSE)),"該当科目なし",VLOOKUP(H45,科目コード表!$C$4:$D$67,2,FALSE))) | J45: 100000 | L45: =IF($E45=L$3,$G45,0)-IF($H45=L$3,$J45,0) | M45: =IF($E45=M$3,$G45,0)-IF($H45=M$3,$J45,0) | N45: =IF($E45=N$3,$G45,0)-IF($H45=N$3,$J45,0) | O45: =IF($E45=O$3,$G45,0)-IF($H45=O$3,$J45,0) | P45: =IF($E45=P$3,$G45,0)-IF($H45=P$3,$J45,0) | Q45: =IF($E45=Q$3,$G45,0)-IF($H45=Q$3,$J45,0) | R45: =IF($E45=R$3,$G45,0)-IF($H45=R$3,$J45,0) | S45: =IF($E45=S$3,$G45,0)-IF($H45=S$3,$J45,0) | ... AL45: =IF($E45=AL$3,$G45,0)-IF($H45=AL$3,$J45,0) | AM45: =-IF($E45=AM$3,$G45,0)+IF($H45=AM$3,$J45,0) | AN45: =-IF($E45=AN$3,$G45,0)+IF($H45=AN$3,$J45,0) | AO45: =-IF($E45=AO$3,$G45,0)+IF($H45=AO$3,$J45,0) | AP45: =IF($E45=AP$3,$G45,0)-IF($H45=AP$3,$J45,0) | AQ45: =IF($E45=AQ$3,$G45,0)-IF($H45=AQ$3,$J45,0) | AR45: =IF($E45=AR$3,$G45,0)-IF($H45=AR$3,$J45,0) | AS45: =IF($E45=AS$3,$G45,0)-IF($H45=AS$3,$J45,0) | AT45: =IF($E45=AT$3,$G45,0)-IF($H45=AT$3,$J45,0) | AU45: =IF($E45=AU$3,$G45,0)-IF($H45=AU$3,$J45,0) | AV45: =IF($E45=AV$3,$G45,0)-IF($H45=AV$3,$J45,0) | AW45: =IF($E45=AW$3,$G45,0)-IF($H45=AW$3,$J45,0) | ... BK45: =IF($E45=BK$3,$G45,0)-IF($H45=BK$3,$J45,0) | BL45: =-IF($E45=BL$3,$G45,0)+IF($H45=BL$3,$J45,0) | BM45: =-IF($E45=BM$3,$G45,0)+IF($H45=BM$3,$J45,0) | BN45: =-IF($E45=BN$3,$G45,0)+IF($H45=BN$3,$J45,0) | BO45: =-IF($E45=BO$3,$G45,0)+IF($H45=BO$3,$J45,0) | BP45: =-IF($E45=BP$3,$G45,0)+IF($H45=BP$3,$J45,0) | BQ45: =-IF($E45=BQ$3,$G45,0)+IF($H45=BQ$3,$J45,0) | BR45: =-IF($E45=BR$3,$G45,0)+IF($H45=BR$3,$J45,0) | BS45: =-IF($E45=BS$3,$G45,0)+IF($H45=BS$3,$J45,0) | BT45: =-IF($E45=BT$3,$G45,0)+IF($H45=BT$3,$J45,0) | BU45: =+G45-J45 | BV45: =-IF($E45=BV$3,$G45,0)+IF($H45=BV$3,$J45,0)
B46: 2 | C46: 2 | D46: 中尾洋一へ地代振込 | E46: 520 | F46: =IF(E46="","",IF(ISNA(VLOOKUP(E46,科目コード表!$C$4:$D$67,2,FALSE)),"該当科目なし",VLOOKUP(E46,科目コード表!$C$4:$D$67,2,FALSE))) | G46: 20000 | I46: =IF(H46="","",IF(ISNA(VLOOKUP(H46,科目コード表!$C$4:$D$67,2,FALSE)),"該当科目なし",VLOOKUP(H46,科目コード表!$C$4:$D$67,2,FALSE))) | L46: =IF($E46=L$3,$G46,0)-IF($H46=L$3,$J46,0) | M46: =IF($E46=M$3,$G46,0)-IF($H46=M$3,$J46,0) | N46: =IF($E46=N$3,$G46,0)-IF($H46=N$3,$J46,0) | O46: =IF($E46=O$3,$G46,0)-IF($H46=O$3,$J46,0) | P46: =IF($E46=P$3,$G46,0)-IF($H46=P$3,$J46,0) | Q46: =IF($E46=Q$3,$G46,0)-IF($H46=Q$3,$J46,0) | R46: =IF($E46=R$3,$G46,0)-IF($H46=R$3,$J46,0) | S46: =IF($E46=S$3,$G46,0)-IF($H46=S$3,$J46,0) | ... AL46: =IF($E46=AL$3,$G46,0)-IF($H46=AL$3,$J46,0) | AM46: =-IF($E46=AM$3,$G46,0)+IF($H46=AM$3,$J46,0) | AN46: =-IF($E46=AN$3,$G46,0)+IF($H46=AN$3,$J46,0) | AO46: =-IF($E46=AO$3,$G46,0)+IF($H46=AO$3,$J46,0) | AP46: =IF($E46=AP$3,$G46,0)-IF($H46=AP$3,$J46,0) | AQ46: =IF($E46=AQ$3,$G46,0)-IF($H46=AQ$3,$J46,0) | AR46: =IF($E46=AR$3,$G46,0)-IF($H46=AR$3,$J46,0) | AS46: =IF($E46=AS$3,$G46,0)-IF($H46=AS$3,$J46,0) | AT46: =IF($E46=AT$3,$G46,0)-IF($H46=AT$3,$J46,0) | AU46: =IF($E46=AU$3,$G46,0)-IF($H46=AU$3,$J46,0) | AV46: =IF($E46=AV$3,$G46,0)-IF($H46=AV$3,$J46,0) | AW46: =IF($E46=AW$3,$G46,0)-IF($H46=AW$3,$J46,0) | ... BK46: =IF($E46=BK$3,$G46,0)-IF($H46=BK$3,$J46,0) | BL46: =-IF($E46=BL$3,$G46,0)+IF($H46=BL$3,$J46,0) | BM46: =-IF($E46=BM$3,$G46,0)+IF($H46=BM$3,$J46,0) | BN46: =-IF($E46=BN$3,$G46,0)+IF($H46=BN$3,$J46,0) | BO46: =-IF($E46=BO$3,$G46,0)+IF($H46=BO$3,$J46,0) | BP46: =-IF($E46=BP$3,$G46,0)+IF($H46=BP$3,$J46,0) | BQ46: =-IF($E46=BQ$3,$G46,0)+IF($H46=BQ$3,$J46,0) | BR46: =-IF($E46=BR$3,$G46,0)+IF($H46=BR$3,$J46,0) | BS46: =-IF($E46=BS$3,$G46,0)+IF($H46=BS$3,$J46,0) | BT46: =-IF($E46=BT$3,$G46,0)+IF($H46=BT$3,$J46,0) | BU46: =+G46-J46 | BV46: =-IF($E46=BV$3,$G46,0)+IF($H46=BV$3,$J46,0)
B47: 2 | C47: 3 | D47: エポス 水道料金 | E47: 507 | F47: =IF(E47="","",IF(ISNA(VLOOKUP(E47,科目コード表!$C$4:$D$67,2,FALSE)),"該当科目なし",VLOOKUP(E47,科目コード表!$C$4:$D$67,2,FALSE))) | G47: 2618 | I47: =IF(H47="","",IF(ISNA(VLOOKUP(H47,科目コード表!$C$4:$D$67,2,FALSE)),"該当科目なし",VLOOKUP(H47,科目コード表!$C$4:$D$67,2,FALSE))) | L47: =IF($E47=L$3,$G47,0)-IF($H47=L$3,$J47,0) | M47: =IF($E47=M$3,$G47,0)-IF($H47=M$3,$J47,0) | N47: =IF($E47=N$3,$G47,0)-IF($H47=N$3,$J47,0) | O47: =IF($E47=O$3,$G47,0)-IF($H47=O$3,$J47,0) | P47: =IF($E47=P$3,$G47,0)-IF($H47=P$3,$J47,0) | Q47: =IF($E47=Q$3,$G47,0)-IF($H47=Q$3,$J47,0) | R47: =IF($E47=R$3,$G47,0)-IF($H47=R$3,$J47,0) | S47: =IF($E47=S$3,$G47,0)-IF($H47=S$3,$J47,0) | ... AL47: =IF($E47=AL$3,$G47,0)-IF($H47=AL$3,$J47,0) | AM47: =-IF($E47=AM$3,$G47,0)+IF($H47=AM$3,$J47,0) | AN47: =-IF($E47=AN$3,$G47,0)+IF($H47=AN$3,$J47,0) | AO47: =-IF($E47=AO$3,$G47,0)+IF($H47=AO$3,$J47,0) | AP47: =IF($E47=AP$3,$G47,0)-IF($H47=AP$3,$J47,0) | AQ47: =IF($E47=AQ$3,$G47,0)-IF($H47=AQ$3,$J47,0) | AR47: =IF($E47=AR$3,$G47,0)-IF($H47=AR$3,$J47,0) | AS47: =IF($E47=AS$3,$G47,0)-IF($H47=AS$3,$J47,0) | AT47: =IF($E47=AT$3,$G47,0)-IF($H47=AT$3,$J47,0) | AU47: =IF($E47=AU$3,$G47,0)-IF($H47=AU$3,$J47,0) | AV47: =IF($E47=AV$3,$G47,0)-IF($H47=AV$3,$J47,0) | AW47: =IF($E47=AW$3,$G47,0)-IF($H47=AW$3,$J47,0) | ... BK47: =IF($E47=BK$3,$G47,0)-IF($H47=BK$3,$J47,0) | BL47: =-IF($E47=BL$3,$G47,0)+IF($H47=BL$3,$J47,0) | BM47: =-IF($E47=BM$3,$G47,0)+IF($H47=BM$3,$J47,0) | BN47: =-IF($E47=BN$3,$G47,0)+IF($H47=BN$3,$J47,0) | BO47: =-IF($E47=BO$3,$G47,0)+IF($H47=BO$3,$J47,0) | BP47: =-IF($E47=BP$3,$G47,0)+IF($H47=BP$3,$J47,0) | BQ47: =-IF($E47=BQ$3,$G47,0)+IF($H47=BQ$3,$J47,0) | BR47: =-IF($E47=BR$3,$G47,0)+IF($H47=BR$3,$J47,0) | BS47: =-IF($E47=BS$3,$G47,0)+IF($H47=BS$3,$J47,0) | BT47: =-IF($E47=BT$3,$G47,0)+IF($H47=BT$3,$J47,0) | BU47: =+G47-J47 | BV47: =-IF($E47=BV$3,$G47,0)+IF($H47=BV$3,$J47,0)
B48: 2 | C48: 6 | D48: 年金生活者・定年退職者のための確定申告 | E48: 524 | F48: =IF(E48="","",IF(ISNA(VLOOKUP(E48,科目コード表!$C$4:$D$67,2,FALSE)),"該当科目なし",VLOOKUP(E48,科目コード表!$C$4:$D$67,2,FALSE))) | G48: 1650 | I48: =IF(H48="","",IF(ISNA(VLOOKUP(H48,科目コード表!$C$4:$D$67,2,FALSE)),"該当科目なし",VLOOKUP(H48,科目コード表!$C$4:$D$67,2,FALSE))) | L48: =IF($E48=L$3,$G48,0)-IF($H48=L$3,$J48,0) | M48: =IF($E48=M$3,$G48,0)-IF($H48=M$3,$J48,0) | N48: =IF($E48=N$3,$G48,0)-IF($H48=N$3,$J48,0) | O48: =IF($E48=O$3,$G48,0)-IF($H48=O$3,$J48,0) | P48: =IF($E48=P$3,$G48,0)-IF($H48=P$3,$J48,0) | Q48: =IF($E48=Q$3,$G48,0)-IF($H48=Q$3,$J48,0) | R48: =IF($E48=R$3,$G48,0)-IF($H48=R$3,$J48,0) | S48: =IF($E48=S$3,$G48,0)-IF($H48=S$3,$J48,0) | ... AL48: =IF($E48=AL$3,$G48,0)-IF($H48=AL$3,$J48,0) | AM48: =-IF($E48=AM$3,$G48,0)+IF($H48=AM$3,$J48,0) | AN48: =-IF($E48=AN$3,$G48,0)+IF($H48=AN$3,$J48,0) | AO48: =-IF($E48=AO$3,$G48,0)+IF($H48=AO$3,$J48,0) | AP48: =IF($E48=AP$3,$G48,0)-IF($H48=AP$3,$J48,0) | AQ48: =IF($E48=AQ$3,$G48,0)-IF($H48=AQ$3,$J48,0) | AR48: =IF($E48=AR$3,$G48,0)-IF($H48=AR$3,$J48,0) | AS48: =IF($E48=AS$3,$G48,0)-IF($H48=AS$3,$J48,0) | AT48: =IF($E48=AT$3,$G48,0)-IF($H48=AT$3,$J48,0) | AU48: =IF($E48=AU$3,$G48,0)-IF($H48=AU$3,$J48,0) | AV48: =IF($E48=AV$3,$G48,0)-IF($H48=AV$3,$J48,0) | AW48: =IF($E48=AW$3,$G48,0)-IF($H48=AW$3,$J48,0) | ... BK48: =IF($E48=BK$3,$G48,0)-IF($H48=BK$3,$J48,0) | BL48: =-IF($E48=BL$3,$G48,0)+IF($H48=BL$3,$J48,0) | BM48: =-IF($E48=BM$3,$G48,0)+IF($H48=BM$3,$J48,0) | BN48: =-IF($E48=BN$3,$G48,0)+IF($H48=BN$3,$J48,0) | BO48: =-IF($E48=BO$3,$G48,0)+IF($H48=BO$3,$J48,0) | BP48: =-IF($E48=BP$3,$G48,0)+IF($H48=BP$3,$J48,0) | BQ48: =-IF($E48=BQ$3,$G48,0)+IF($H48=BQ$3,$J48,0) | BR48: =-IF($E48=BR$3,$G48,0)+IF($H48=BR$3,$J48,0) | BS48: =-IF($E48=BS$3,$G48,0)+IF($H48=BS$3,$J48,0) | BT48: =-IF($E48=BT$3,$G48,0)+IF($H48=BT$3,$J48,0) | BU48: =+G48-J48 | BV48: =-IF($E48=BV$3,$G48,0)+IF($H48=BV$3,$J48,0)
B49: 2 | C49: 10 | D49: 水切りワイパー | E49: 523 | F49: =IF(E49="","",IF(ISNA(VLOOKUP(E49,科目コード表!$C$4:$D$67,2,FALSE)),"該当科目なし",VLOOKUP(E49,科目コード表!$C$4:$D$67,2,FALSE))) | G49: 729 | I49: =IF(H49="","",IF(ISNA(VLOOKUP(H49,科目コード表!$C$4:$D$67,2,FALSE)),"該当科目なし",VLOOKUP(H49,科目コード表!$C$4:$D$67,2,FALSE))) | L49: =IF($E49=L$3,$G49,0)-IF($H49=L$3,$J49,0) | M49: =IF($E49=M$3,$G49,0)-IF($H49=M$3,$J49,0) | N49: =IF($E49=N$3,$G49,0)-IF($H49=N$3,$J49,0) | O49: =IF($E49=O$3,$G49,0)-IF($H49=O$3,$J49,0) | P49: =IF($E49=P$3,$G49,0)-IF($H49=P$3,$J49,0) | Q49: =IF($E49=Q$3,$G49,0)-IF($H49=Q$3,$J49,0) | R49: =IF($E49=R$3,$G49,0)-IF($H49=R$3,$J49,0) | S49: =IF($E49=S$3,$G49,0)-IF($H49=S$3,$J49,0) | ... AL49: =IF($E49=AL$3,$G49,0)-IF($H49=AL$3,$J49,0) | AM49: =-IF($E49=AM$3,$G49,0)+IF($H49=AM$3,$J49,0) | AN49: =-IF($E49=AN$3,$G49,0)+IF($H49=AN$3,$J49,0) | AO49: =-IF($E49=AO$3,$G49,0)+IF($H49=AO$3,$J49,0) | AP49: =IF($E49=AP$3,$G49,0)-IF($H49=AP$3,$J49,0) | AQ49: =IF($E49=AQ$3,$G49,0)-IF($H49=AQ$3,$J49,0) | AR49: =IF($E49=AR$3,$G49,0)-IF($H49=AR$3,$J49,0) | AS49: =IF($E49=AS$3,$G49,0)-IF($H49=AS$3,$J49,0) | AT49: =IF($E49=AT$3,$G49,0)-IF($H49=AT$3,$J49,0) | AU49: =IF($E49=AU$3,$G49,0)-IF($H49=AU$3,$J49,0) | AV49: =IF($E49=AV$3,$G49,0)-IF($H49=AV$3,$J49,0) | AW49: =IF($E49=AW$3,$G49,0)-IF($H49=AW$3,$J49,0) | ... BK49: =IF($E49=BK$3,$G49,0)-IF($H49=BK$3,$J49,0) | BL49: =-IF($E49=BL$3,$G49,0)+IF($H49=BL$3,$J49,0) | BM49: =-IF($E49=BM$3,$G49,0)+IF($H49=BM$3,$J49,0) | BN49: =-IF($E49=BN$3,$G49,0)+IF($H49=BN$3,$J49,0) | BO49: =-IF($E49=BO$3,$G49,0)+IF($H49=BO$3,$J49,0) | BP49: =-IF($E49=BP$3,$G49,0)+IF($H49=BP$3,$J49,0) | BQ49: =-IF($E49=BQ$3,$G49,0)+IF($H49=BQ$3,$J49,0) | BR49: =-IF($E49=BR$3,$G49,0)+IF($H49=BR$3,$J49,0) | BS49: =-IF($E49=BS$3,$G49,0)+IF($H49=BS$3,$J49,0) | BT49: =-IF($E49=BT$3,$G49,0)+IF($H49=BT$3,$J49,0) | BU49: =+G49-J49 | BV49: =-IF($E49=BV$3,$G49,0)+IF($H49=BV$3,$J49,0)
B50: 2 | C50: 13 | D50: セレサ川崎 ユーユー入金 | F50: =IF(E50="","",IF(ISNA(VLOOKUP(E50,科目コード表!$C$4:$D$67,2,FALSE)),"該当科目なし",VLOOKUP(E50,科目コード表!$C$4:$D$67,2,FALSE))) | H50: 107 | I50: =IF(H50="","",IF(ISNA(VLOOKUP(H50,科目コード表!$C$4:$D$67,2,FALSE)),"該当科目なし",VLOOKUP(H50,科目コード表!$C$4:$D$67,2,FALSE))) | J50: 100000 | L50: =IF($E50=L$3,$G50,0)-IF($H50=L$3,$J50,0) | M50: =IF($E50=M$3,$G50,0)-IF($H50=M$3,$J50,0) | N50: =IF($E50=N$3,$G50,0)-IF($H50=N$3,$J50,0) | O50: =IF($E50=O$3,$G50,0)-IF($H50=O$3,$J50,0) | P50: =IF($E50=P$3,$G50,0)-IF($H50=P$3,$J50,0) | Q50: =IF($E50=Q$3,$G50,0)-IF($H50=Q$3,$J50,0) | R50: =IF($E50=R$3,$G50,0)-IF($H50=R$3,$J50,0) | S50: =IF($E50=S$3,$G50,0)-IF($H50=S$3,$J50,0) | ... AL50: =IF($E50=AL$3,$G50,0)-IF($H50=AL$3,$J50,0) | AM50: =-IF($E50=AM$3,$G50,0)+IF($H50=AM$3,$J50,0) | AN50: =-IF($E50=AN$3,$G50,0)+IF($H50=AN$3,$J50,0) | AO50: =-IF($E50=AO$3,$G50,0)+IF($H50=AO$3,$J50,0) | AP50: =IF($E50=AP$3,$G50,0)-IF($H50=AP$3,$J50,0) | AQ50: =IF($E50=AQ$3,$G50,0)-IF($H50=AQ$3,$J50,0) | AR50: =IF($E50=AR$3,$G50,0)-IF($H50=AR$3,$J50,0) | AS50: =IF($E50=AS$3,$G50,0)-IF($H50=AS$3,$J50,0) | AT50: =IF($E50=AT$3,$G50,0)-IF($H50=AT$3,$J50,0) | AU50: =IF($E50=AU$3,$G50,0)-IF($H50=AU$3,$J50,0) | AV50: =IF($E50=AV$3,$G50,0)-IF($H50=AV$3,$J50,0) | AW50: =IF($E50=AW$3,$G50,0)-IF($H50=AW$3,$J50,0) | ... BK50: =IF($E50=BK$3,$G50,0)-IF($H50=BK$3,$J50,0) | BL50: =-IF($E50=BL$3,$G50,0)+IF($H50=BL$3,$J50,0) | BM50: =-IF($E50=BM$3,$G50,0)+IF($H50=BM$3,$J50,0) | BN50: =-IF($E50=BN$3,$G50,0)+IF($H50=BN$3,$J50,0) | BO50: =-IF($E50=BO$3,$G50,0)+IF($H50=BO$3,$J50,0) | BP50: =-IF($E50=BP$3,$G50,0)+IF($H50=BP$3,$J50,0) | BQ50: =-IF($E50=BQ$3,$G50,0)+IF($H50=BQ$3,$J50,0) | BR50: =-IF($E50=BR$3,$G50,0)+IF($H50=BR$3,$J50,0) | BS50: =-IF($E50=BS$3,$G50,0)+IF($H50=BS$3,$J50,0) | BT50: =-IF($E50=BT$3,$G50,0)+IF($H50=BT$3,$J50,0) | BU50: =+G50-J50 | BV50: =-IF($E50=BV$3,$G50,0)+IF($H50=BV$3,$J50,0)
B51: 2 | C51: 14 | D51: ニャーベトナム交際費 | E51: 511 | F51: =IF(E51="","",IF(ISNA(VLOOKUP(E51,科目コード表!$C$4:$D$67,2,FALSE)),"該当科目なし",VLOOKUP(E51,科目コード表!$C$4:$D$67,2,FALSE))) | G51: 8500 | I51: =IF(H51="","",IF(ISNA(VLOOKUP(H51,科目コード表!$C$4:$D$67,2,FALSE)),"該当科目なし",VLOOKUP(H51,科目コード表!$C$4:$D$67,2,FALSE))) | L51: =IF($E51=L$3,$G51,0)-IF($H51=L$3,$J51,0) | M51: =IF($E51=M$3,$G51,0)-IF($H51=M$3,$J51,0) | N51: =IF($E51=N$3,$G51,0)-IF($H51=N$3,$J51,0) | O51: =IF($E51=O$3,$G51,0)-IF($H51=O$3,$J51,0) | P51: =IF($E51=P$3,$G51,0)-IF($H51=P$3,$J51,0) | Q51: =IF($E51=Q$3,$G51,0)-IF($H51=Q$3,$J51,0) | R51: =IF($E51=R$3,$G51,0)-IF($H51=R$3,$J51,0) | S51: =IF($E51=S$3,$G51,0)-IF($H51=S$3,$J51,0) | ... AL51: =IF($E51=AL$3,$G51,0)-IF($H51=AL$3,$J51,0) | AM51: =-IF($E51=AM$3,$G51,0)+IF($H51=AM$3,$J51,0) | AN51: =-IF($E51=AN$3,$G51,0)+IF($H51=AN$3,$J51,0) | AO51: =-IF($E51=AO$3,$G51,0)+IF($H51=AO$3,$J51,0) | AP51: =IF($E51=AP$3,$G51,0)-IF($H51=AP$3,$J51,0) | AQ51: =IF($E51=AQ$3,$G51,0)-IF($H51=AQ$3,$J51,0) | AR51: =IF($E51=AR$3,$G51,0)-IF($H51=AR$3,$J51,0) | AS51: =IF($E51=AS$3,$G51,0)-IF($H51=AS$3,$J51,0) | AT51: =IF($E51=AT$3,$G51,0)-IF($H51=AT$3,$J51,0) | AU51: =IF($E51=AU$3,$G51,0)-IF($H51=AU$3,$J51,0) | AV51: =IF($E51=AV$3,$G51,0)-IF($H51=AV$3,$J51,0) | AW51: =IF($E51=AW$3,$G51,0)-IF($H51=AW$3,$J51,0) | ... BK51: =IF($E51=BK$3,$G51,0)-IF($H51=BK$3,$J51,0) | BL51: =-IF($E51=BL$3,$G51,0)+IF($H51=BL$3,$J51,0) | BM51: =-IF($E51=BM$3,$G51,0)+IF($H51=BM$3,$J51,0) | BN51: =-IF($E51=BN$3,$G51,0)+IF($H51=BN$3,$J51,0) | BO51: =-IF($E51=BO$3,$G51,0)+IF($H51=BO$3,$J51,0) | BP51: =-IF($E51=BP$3,$G51,0)+IF($H51=BP$3,$J51,0) | BQ51: =-IF($E51=BQ$3,$G51,0)+IF($H51=BQ$3,$J51,0) | BR51: =-IF($E51=BR$3,$G51,0)+IF($H51=BR$3,$J51,0) | BS51: =-IF($E51=BS$3,$G51,0)+IF($H51=BS$3,$J51,0) | BT51: =-IF($E51=BT$3,$G51,0)+IF($H51=BT$3,$J51,0) | BU51: =+G51-J51 | BV51: =-IF($E51=BV$3,$G51,0)+IF($H51=BV$3,$J51,0)
B52: 2 | C52: 16 | D52: 駐車場代 | E52: 523 | F52: =IF(E52="","",IF(ISNA(VLOOKUP(E52,科目コード表!$C$4:$D$67,2,FALSE)),"該当科目なし",VLOOKUP(E52,科目コード表!$C$4:$D$67,2,FALSE))) | G52: 200 | I52: =IF(H52="","",IF(ISNA(VLOOKUP(H52,科目コード表!$C$4:$D$67,2,FALSE)),"該当科目なし",VLOOKUP(H52,科目コード表!$C$4:$D$67,2,FALSE))) | L52: =IF($E52=L$3,$G52,0)-IF($H52=L$3,$J52,0) | M52: =IF($E52=M$3,$G52,0)-IF($H52=M$3,$J52,0) | N52: =IF($E52=N$3,$G52,0)-IF($H52=N$3,$J52,0) | O52: =IF($E52=O$3,$G52,0)-IF($H52=O$3,$J52,0) | P52: =IF($E52=P$3,$G52,0)-IF($H52=P$3,$J52,0) | Q52: =IF($E52=Q$3,$G52,0)-IF($H52=Q$3,$J52,0) | R52: =IF($E52=R$3,$G52,0)-IF($H52=R$3,$J52,0) | S52: =IF($E52=S$3,$G52,0)-IF($H52=S$3,$J52,0) | ... AL52: =IF($E52=AL$3,$G52,0)-IF($H52=AL$3,$J52,0) | AM52: =-IF($E52=AM$3,$G52,0)+IF($H52=AM$3,$J52,0) | AN52: =-IF($E52=AN$3,$G52,0)+IF($H52=AN$3,$J52,0) | AO52: =-IF($E52=AO$3,$G52,0)+IF($H52=AO$3,$J52,0) | AP52: =IF($E52=AP$3,$G52,0)-IF($H52=AP$3,$J52,0) | AQ52: =IF($E52=AQ$3,$G52,0)-IF($H52=AQ$3,$J52,0) | AR52: =IF($E52=AR$3,$G52,0)-IF($H52=AR$3,$J52,0) | AS52: =IF($E52=AS$3,$G52,0)-IF($H52=AS$3,$J52,0) | AT52: =IF($E52=AT$3,$G52,0)-IF($H52=AT$3,$J52,0) | AU52: =IF($E52=AU$3,$G52,0)-IF($H52=AU$3,$J52,0) | AV52: =IF($E52=AV$3,$G52,0)-IF($H52=AV$3,$J52,0) | AW52: =IF($E52=AW$3,$G52,0)-IF($H52=AW$3,$J52,0) | ... BK52: =IF($E52=BK$3,$G52,0)-IF($H52=BK$3,$J52,0) | BL52: =-IF($E52=BL$3,$G52,0)+IF($H52=BL$3,$J52,0) | BM52: =-IF($E52=BM$3,$G52,0)+IF($H52=BM$3,$J52,0) | BN52: =-IF($E52=BN$3,$G52,0)+IF($H52=BN$3,$J52,0) | BO52: =-IF($E52=BO$3,$G52,0)+IF($H52=BO$3,$J52,0) | BP52: =-IF($E52=BP$3,$G52,0)+IF($H52=BP$3,$J52,0) | BQ52: =-IF($E52=BQ$3,$G52,0)+IF($H52=BQ$3,$J52,0) | BR52: =-IF($E52=BR$3,$G52,0)+IF($H52=BR$3,$J52,0) | BS52: =-IF($E52=BS$3,$G52,0)+IF($H52=BS$3,$J52,0) | BT52: =-IF($E52=BT$3,$G52,0)+IF($H52=BT$3,$J52,0) | BU52: =+G52-J52 | BV52: =-IF($E52=BV$3,$G52,0)+IF($H52=BV$3,$J52,0)
B53: 2 | C53: 16 | D53: Kindle Unlimited会費 | E53: 524 | F53: =IF(E53="","",IF(ISNA(VLOOKUP(E53,科目コード表!$C$4:$D$67,2,FALSE)),"該当科目なし",VLOOKUP(E53,科目コード表!$C$4:$D$67,2,FALSE))) | G53: 980 | I53: =IF(H53="","",IF(ISNA(VLOOKUP(H53,科目コード表!$C$4:$D$67,2,FALSE)),"該当科目なし",VLOOKUP(H53,科目コード表!$C$4:$D$67,2,FALSE))) | L53: =IF($E53=L$3,$G53,0)-IF($H53=L$3,$J53,0) | M53: =IF($E53=M$3,$G53,0)-IF($H53=M$3,$J53,0) | N53: =IF($E53=N$3,$G53,0)-IF($H53=N$3,$J53,0) | O53: =IF($E53=O$3,$G53,0)-IF($H53=O$3,$J53,0) | P53: =IF($E53=P$3,$G53,0)-IF($H53=P$3,$J53,0) | Q53: =IF($E53=Q$3,$G53,0)-IF($H53=Q$3,$J53,0) | R53: =IF($E53=R$3,$G53,0)-IF($H53=R$3,$J53,0) | S53: =IF($E53=S$3,$G53,0)-IF($H53=S$3,$J53,0) | ... AL53: =IF($E53=AL$3,$G53,0)-IF($H53=AL$3,$J53,0) | AM53: =-IF($E53=AM$3,$G53,0)+IF($H53=AM$3,$J53,0) | AN53: =-IF($E53=AN$3,$G53,0)+IF($H53=AN$3,$J53,0) | AO53: =-IF($E53=AO$3,$G53,0)+IF($H53=AO$3,$J53,0) | AP53: =IF($E53=AP$3,$G53,0)-IF($H53=AP$3,$J53,0) | AQ53: =IF($E53=AQ$3,$G53,0)-IF($H53=AQ$3,$J53,0) | AR53: =IF($E53=AR$3,$G53,0)-IF($H53=AR$3,$J53,0) | AS53: =IF($E53=AS$3,$G53,0)-IF($H53=AS$3,$J53,0) | AT53: =IF($E53=AT$3,$G53,0)-IF($H53=AT$3,$J53,0) | AU53: =IF($E53=AU$3,$G53,0)-IF($H53=AU$3,$J53,0) | AV53: =IF($E53=AV$3,$G53,0)-IF($H53=AV$3,$J53,0) | AW53: =IF($E53=AW$3,$G53,0)-IF($H53=AW$3,$J53,0) | ... BK53: =IF($E53=BK$3,$G53,0)-IF($H53=BK$3,$J53,0) | BL53: =-IF($E53=BL$3,$G53,0)+IF($H53=BL$3,$J53,0) | BM53: =-IF($E53=BM$3,$G53,0)+IF($H53=BM$3,$J53,0) | BN53: =-IF($E53=BN$3,$G53,0)+IF($H53=BN$3,$J53,0) | BO53: =-IF($E53=BO$3,$G53,0)+IF($H53=BO$3,$J53,0) | BP53: =-IF($E53=BP$3,$G53,0)+IF($H53=BP$3,$J53,0) | BQ53: =-IF($E53=BQ$3,$G53,0)+IF($H53=BQ$3,$J53,0) | BR53: =-IF($E53=BR$3,$G53,0)+IF($H53=BR$3,$J53,0) | BS53: =-IF($E53=BS$3,$G53,0)+IF($H53=BS$3,$J53,0) | BT53: =-IF($E53=BT$3,$G53,0)+IF($H53=BT$3,$J53,0) | BU53: =+G53-J53 | BV53: =-IF($E53=BV$3,$G53,0)+IF($H53=BV$3,$J53,0)
B54: 2 | C54: 18 | D54: M.2 NVMe SSD 外付けケース | E54: 514 | F54: =IF(E54="","",IF(ISNA(VLOOKUP(E54,科目コード表!$C$4:$D$67,2,FALSE)),"該当科目なし",VLOOKUP(E54,科目コード表!$C$4:$D$67,2,FALSE))) | G54: 1602 | I54: =IF(H54="","",IF(ISNA(VLOOKUP(H54,科目コード表!$C$4:$D$67,2,FALSE)),"該当科目なし",VLOOKUP(H54,科目コード表!$C$4:$D$67,2,FALSE))) | L54: =IF($E54=L$3,$G54,0)-IF($H54=L$3,$J54,0) | M54: =IF($E54=M$3,$G54,0)-IF($H54=M$3,$J54,0) | N54: =IF($E54=N$3,$G54,0)-IF($H54=N$3,$J54,0) | O54: =IF($E54=O$3,$G54,0)-IF($H54=O$3,$J54,0) | P54: =IF($E54=P$3,$G54,0)-IF($H54=P$3,$J54,0) | Q54: =IF($E54=Q$3,$G54,0)-IF($H54=Q$3,$J54,0) | R54: =IF($E54=R$3,$G54,0)-IF($H54=R$3,$J54,0) | S54: =IF($E54=S$3,$G54,0)-IF($H54=S$3,$J54,0) | ... AL54: =IF($E54=AL$3,$G54,0)-IF($H54=AL$3,$J54,0) | AM54: =-IF($E54=AM$3,$G54,0)+IF($H54=AM$3,$J54,0) | AN54: =-IF($E54=AN$3,$G54,0)+IF($H54=AN$3,$J54,0) | AO54: =-IF($E54=AO$3,$G54,0)+IF($H54=AO$3,$J54,0) | AP54: =IF($E54=AP$3,$G54,0)-IF($H54=AP$3,$J54,0) | AQ54: =IF($E54=AQ$3,$G54,0)-IF($H54=AQ$3,$J54,0) | AR54: =IF($E54=AR$3,$G54,0)-IF($H54=AR$3,$J54,0) | AS54: =IF($E54=AS$3,$G54,0)-IF($H54=AS$3,$J54,0) | AT54: =IF($E54=AT$3,$G54,0)-IF($H54=AT$3,$J54,0) | AU54: =IF($E54=AU$3,$G54,0)-IF($H54=AU$3,$J54,0) | AV54: =IF($E54=AV$3,$G54,0)-IF($H54=AV$3,$J54,0) | AW54: =IF($E54=AW$3,$G54,0)-IF($H54=AW$3,$J54,0) | ... BK54: =IF($E54=BK$3,$G54,0)-IF($H54=BK$3,$J54,0) | BL54: =-IF($E54=BL$3,$G54,0)+IF($H54=BL$3,$J54,0) | BM54: =-IF($E54=BM$3,$G54,0)+IF($H54=BM$3,$J54,0) | BN54: =-IF($E54=BN$3,$G54,0)+IF($H54=BN$3,$J54,0) | BO54: =-IF($E54=BO$3,$G54,0)+IF($H54=BO$3,$J54,0) | BP54: =-IF($E54=BP$3,$G54,0)+IF($H54=BP$3,$J54,0) | BQ54: =-IF($E54=BQ$3,$G54,0)+IF($H54=BQ$3,$J54,0) | BR54: =-IF($E54=BR$3,$G54,0)+IF($H54=BR$3,$J54,0) | BS54: =-IF($E54=BS$3,$G54,0)+IF($H54=BS$3,$J54,0) | BT54: =-IF($E54=BT$3,$G54,0)+IF($H54=BT$3,$J54,0) | BU54: =+G54-J54 | BV54: =-IF($E54=BV$3,$G54,0)+IF($H54=BV$3,$J54,0)
B55: 2 | C55: 18 | D55: エポス Github | E55: 525 | F55: =IF(E55="","",IF(ISNA(VLOOKUP(E55,科目コード表!$C$4:$D$67,2,FALSE)),"該当科目なし",VLOOKUP(E55,科目コード表!$C$4:$D$67,2,FALSE))) | G55: 1758 | I55: =IF(H55="","",IF(ISNA(VLOOKUP(H55,科目コード表!$C$4:$D$67,2,FALSE)),"該当科目なし",VLOOKUP(H55,科目コード表!$C$4:$D$67,2,FALSE))) | L55: =IF($E55=L$3,$G55,0)-IF($H55=L$3,$J55,0) | M55: =IF($E55=M$3,$G55,0)-IF($H55=M$3,$J55,0) | N55: =IF($E55=N$3,$G55,0)-IF($H55=N$3,$J55,0) | O55: =IF($E55=O$3,$G55,0)-IF($H55=O$3,$J55,0) | P55: =IF($E55=P$3,$G55,0)-IF($H55=P$3,$J55,0) | Q55: =IF($E55=Q$3,$G55,0)-IF($H55=Q$3,$J55,0) | R55: =IF($E55=R$3,$G55,0)-IF($H55=R$3,$J55,0) | S55: =IF($E55=S$3,$G55,0)-IF($H55=S$3,$J55,0) | ... AL55: =IF($E55=AL$3,$G55,0)-IF($H55=AL$3,$J55,0) | AM55: =-IF($E55=AM$3,$G55,0)+IF($H55=AM$3,$J55,0) | AN55: =-IF($E55=AN$3,$G55,0)+IF($H55=AN$3,$J55,0) | AO55: =-IF($E55=AO$3,$G55,0)+IF($H55=AO$3,$J55,0) | AP55: =IF($E55=AP$3,$G55,0)-IF($H55=AP$3,$J55,0) | AQ55: =IF($E55=AQ$3,$G55,0)-IF($H55=AQ$3,$J55,0) | AR55: =IF($E55=AR$3,$G55,0)-IF($H55=AR$3,$J55,0) | AS55: =IF($E55=AS$3,$G55,0)-IF($H55=AS$3,$J55,0) | AT55: =IF($E55=AT$3,$G55,0)-IF($H55=AT$3,$J55,0) | AU55: =IF($E55=AU$3,$G55,0)-IF($H55=AU$3,$J55,0) | AV55: =IF($E55=AV$3,$G55,0)-IF($H55=AV$3,$J55,0) | AW55: =IF($E55=AW$3,$G55,0)-IF($H55=AW$3,$J55,0) | ... BK55: =IF($E55=BK$3,$G55,0)-IF($H55=BK$3,$J55,0) | BL55: =-IF($E55=BL$3,$G55,0)+IF($H55=BL$3,$J55,0) | BM55: =-IF($E55=BM$3,$G55,0)+IF($H55=BM$3,$J55,0) | BN55: =-IF($E55=BN$3,$G55,0)+IF($H55=BN$3,$J55,0) | BO55: =-IF($E55=BO$3,$G55,0)+IF($H55=BO$3,$J55,0) | BP55: =-IF($E55=BP$3,$G55,0)+IF($H55=BP$3,$J55,0) | BQ55: =-IF($E55=BQ$3,$G55,0)+IF($H55=BQ$3,$J55,0) | BR55: =-IF($E55=BR$3,$G55,0)+IF($H55=BR$3,$J55,0) | BS55: =-IF($E55=BS$3,$G55,0)+IF($H55=BS$3,$J55,0) | BT55: =-IF($E55=BT$3,$G55,0)+IF($H55=BT$3,$J55,0) | BU55: =+G55-J55 | BV55: =-IF($E55=BV$3,$G55,0)+IF($H55=BV$3,$J55,0)
B56: 2 | C56: 20 | D56: エポス Microsoft | E56: 525 | F56: =IF(E56="","",IF(ISNA(VLOOKUP(E56,科目コード表!$C$4:$D$67,2,FALSE)),"該当科目なし",VLOOKUP(E56,科目コード表!$C$4:$D$67,2,FALSE))) | G56: 2856 | I56: =IF(H56="","",IF(ISNA(VLOOKUP(H56,科目コード表!$C$4:$D$67,2,FALSE)),"該当科目なし",VLOOKUP(H56,科目コード表!$C$4:$D$67,2,FALSE))) | L56: =IF($E56=L$3,$G56,0)-IF($H56=L$3,$J56,0) | M56: =IF($E56=M$3,$G56,0)-IF($H56=M$3,$J56,0) | N56: =IF($E56=N$3,$G56,0)-IF($H56=N$3,$J56,0) | O56: =IF($E56=O$3,$G56,0)-IF($H56=O$3,$J56,0) | P56: =IF($E56=P$3,$G56,0)-IF($H56=P$3,$J56,0) | Q56: =IF($E56=Q$3,$G56,0)-IF($H56=Q$3,$J56,0) | R56: =IF($E56=R$3,$G56,0)-IF($H56=R$3,$J56,0) | S56: =IF($E56=S$3,$G56,0)-IF($H56=S$3,$J56,0) | ... AL56: =IF($E56=AL$3,$G56,0)-IF($H56=AL$3,$J56,0) | AM56: =-IF($E56=AM$3,$G56,0)+IF($H56=AM$3,$J56,0) | AN56: =-IF($E56=AN$3,$G56,0)+IF($H56=AN$3,$J56,0) | AO56: =-IF($E56=AO$3,$G56,0)+IF($H56=AO$3,$J56,0) | AP56: =IF($E56=AP$3,$G56,0)-IF($H56=AP$3,$J56,0) | AQ56: =IF($E56=AQ$3,$G56,0)-IF($H56=AQ$3,$J56,0) | AR56: =IF($E56=AR$3,$G56,0)-IF($H56=AR$3,$J56,0) | AS56: =IF($E56=AS$3,$G56,0)-IF($H56=AS$3,$J56,0) | AT56: =IF($E56=AT$3,$G56,0)-IF($H56=AT$3,$J56,0) | AU56: =IF($E56=AU$3,$G56,0)-IF($H56=AU$3,$J56,0) | AV56: =IF($E56=AV$3,$G56,0)-IF($H56=AV$3,$J56,0) | AW56: =IF($E56=AW$3,$G56,0)-IF($H56=AW$3,$J56,0) | ... BK56: =IF($E56=BK$3,$G56,0)-IF($H56=BK$3,$J56,0) | BL56: =-IF($E56=BL$3,$G56,0)+IF($H56=BL$3,$J56,0) | BM56: =-IF($E56=BM$3,$G56,0)+IF($H56=BM$3,$J56,0) | BN56: =-IF($E56=BN$3,$G56,0)+IF($H56=BN$3,$J56,0) | BO56: =-IF($E56=BO$3,$G56,0)+IF($H56=BO$3,$J56,0) | BP56: =-IF($E56=BP$3,$G56,0)+IF($H56=BP$3,$J56,0) | BQ56: =-IF($E56=BQ$3,$G56,0)+IF($H56=BQ$3,$J56,0) | BR56: =-IF($E56=BR$3,$G56,0)+IF($H56=BR$3,$J56,0) | BS56: =-IF($E56=BS$3,$G56,0)+IF($H56=BS$3,$J56,0) | BT56: =-IF($E56=BT$3,$G56,0)+IF($H56=BT$3,$J56,0) | BU56: =+G56-J56 | BV56: =-IF($E56=BV$3,$G56,0)+IF($H56=BV$3,$J56,0)
B57: 2 | C57: 22 | D57: BigBoy交際費 | E57: 511 | F57: =IF(E57="","",IF(ISNA(VLOOKUP(E57,科目コード表!$C$4:$D$67,2,FALSE)),"該当科目なし",VLOOKUP(E57,科目コード表!$C$4:$D$67,2,FALSE))) | G57: 7854 | I57: =IF(H57="","",IF(ISNA(VLOOKUP(H57,科目コード表!$C$4:$D$67,2,FALSE)),"該当科目なし",VLOOKUP(H57,科目コード表!$C$4:$D$67,2,FALSE))) | L57: =IF($E57=L$3,$G57,0)-IF($H57=L$3,$J57,0) | M57: =IF($E57=M$3,$G57,0)-IF($H57=M$3,$J57,0) | N57: =IF($E57=N$3,$G57,0)-IF($H57=N$3,$J57,0) | O57: =IF($E57=O$3,$G57,0)-IF($H57=O$3,$J57,0) | P57: =IF($E57=P$3,$G57,0)-IF($H57=P$3,$J57,0) | Q57: =IF($E57=Q$3,$G57,0)-IF($H57=Q$3,$J57,0) | R57: =IF($E57=R$3,$G57,0)-IF($H57=R$3,$J57,0) | S57: =IF($E57=S$3,$G57,0)-IF($H57=S$3,$J57,0) | ... AL57: =IF($E57=AL$3,$G57,0)-IF($H57=AL$3,$J57,0) | AM57: =-IF($E57=AM$3,$G57,0)+IF($H57=AM$3,$J57,0) | AN57: =-IF($E57=AN$3,$G57,0)+IF($H57=AN$3,$J57,0) | AO57: =-IF($E57=AO$3,$G57,0)+IF($H57=AO$3,$J57,0) | AP57: =IF($E57=AP$3,$G57,0)-IF($H57=AP$3,$J57,0) | AQ57: =IF($E57=AQ$3,$G57,0)-IF($H57=AQ$3,$J57,0) | AR57: =IF($E57=AR$3,$G57,0)-IF($H57=AR$3,$J57,0) | AS57: =IF($E57=AS$3,$G57,0)-IF($H57=AS$3,$J57,0) | AT57: =IF($E57=AT$3,$G57,0)-IF($H57=AT$3,$J57,0) | AU57: =IF($E57=AU$3,$G57,0)-IF($H57=AU$3,$J57,0) | AV57: =IF($E57=AV$3,$G57,0)-IF($H57=AV$3,$J57,0) | AW57: =IF($E57=AW$3,$G57,0)-IF($H57=AW$3,$J57,0) | ... BK57: =IF($E57=BK$3,$G57,0)-IF($H57=BK$3,$J57,0) | BL57: =-IF($E57=BL$3,$G57,0)+IF($H57=BL$3,$J57,0) | BM57: =-IF($E57=BM$3,$G57,0)+IF($H57=BM$3,$J57,0) | BN57: =-IF($E57=BN$3,$G57,0)+IF($H57=BN$3,$J57,0) | BO57: =-IF($E57=BO$3,$G57,0)+IF($H57=BO$3,$J57,0) | BP57: =-IF($E57=BP$3,$G57,0)+IF($H57=BP$3,$J57,0) | BQ57: =-IF($E57=BQ$3,$G57,0)+IF($H57=BQ$3,$J57,0) | BR57: =-IF($E57=BR$3,$G57,0)+IF($H57=BR$3,$J57,0) | BS57: =-IF($E57=BS$3,$G57,0)+IF($H57=BS$3,$J57,0) | BT57: =-IF($E57=BT$3,$G57,0)+IF($H57=BT$3,$J57,0) | BU57: =+G57-J57 | BV57: =-IF($E57=BV$3,$G57,0)+IF($H57=BV$3,$J57,0)
B58: 2 | C58: 24 | D58: ScanSnap購入 | E58: 514 | F58: =IF(E58="","",IF(ISNA(VLOOKUP(E58,科目コード表!$C$4:$D$67,2,FALSE)),"該当科目なし",VLOOKUP(E58,科目コード表!$C$4:$D$67,2,FALSE))) | G58: 31800 | I58: =IF(H58="","",IF(ISNA(VLOOKUP(H58,科目コード表!$C$4:$D$67,2,FALSE)),"該当科目なし",VLOOKUP(H58,科目コード表!$C$4:$D$67,2,FALSE))) | L58: =IF($E58=L$3,$G58,0)-IF($H58=L$3,$J58,0) | M58: =IF($E58=M$3,$G58,0)-IF($H58=M$3,$J58,0) | N58: =IF($E58=N$3,$G58,0)-IF($H58=N$3,$J58,0) | O58: =IF($E58=O$3,$G58,0)-IF($H58=O$3,$J58,0) | P58: =IF($E58=P$3,$G58,0)-IF($H58=P$3,$J58,0) | Q58: =IF($E58=Q$3,$G58,0)-IF($H58=Q$3,$J58,0) | R58: =IF($E58=R$3,$G58,0)-IF($H58=R$3,$J58,0) | S58: =IF($E58=S$3,$G58,0)-IF($H58=S$3,$J58,0) | ... AL58: =IF($E58=AL$3,$G58,0)-IF($H58=AL$3,$J58,0) | AM58: =-IF($E58=AM$3,$G58,0)+IF($H58=AM$3,$J58,0) | AN58: =-IF($E58=AN$3,$G58,0)+IF($H58=AN$3,$J58,0) | AO58: =-IF($E58=AO$3,$G58,0)+IF($H58=AO$3,$J58,0) | AP58: =IF($E58=AP$3,$G58,0)-IF($H58=AP$3,$J58,0) | AQ58: =IF($E58=AQ$3,$G58,0)-IF($H58=AQ$3,$J58,0) | AR58: =IF($E58=AR$3,$G58,0)-IF($H58=AR$3,$J58,0) | AS58: =IF($E58=AS$3,$G58,0)-IF($H58=AS$3,$J58,0) | AT58: =IF($E58=AT$3,$G58,0)-IF($H58=AT$3,$J58,0) | AU58: =IF($E58=AU$3,$G58,0)-IF($H58=AU$3,$J58,0) | AV58: =IF($E58=AV$3,$G58,0)-IF($H58=AV$3,$J58,0) | AW58: =IF($E58=AW$3,$G58,0)-IF($H58=AW$3,$J58,0) | ... BK58: =IF($E58=BK$3,$G58,0)-IF($H58=BK$3,$J58,0) | BL58: =-IF($E58=BL$3,$G58,0)+IF($H58=BL$3,$J58,0) | BM58: =-IF($E58=BM$3,$G58,0)+IF($H58=BM$3,$J58,0) | BN58: =-IF($E58=BN$3,$G58,0)+IF($H58=BN$3,$J58,0) | BO58: =-IF($E58=BO$3,$G58,0)+IF($H58=BO$3,$J58,0) | BP58: =-IF($E58=BP$3,$G58,0)+IF($H58=BP$3,$J58,0) | BQ58: =-IF($E58=BQ$3,$G58,0)+IF($H58=BQ$3,$J58,0) | BR58: =-IF($E58=BR$3,$G58,0)+IF($H58=BR$3,$J58,0) | BS58: =-IF($E58=BS$3,$G58,0)+IF($H58=BS$3,$J58,0) | BT58: =-IF($E58=BT$3,$G58,0)+IF($H58=BT$3,$J58,0) | BU58: =+G58-J58 | BV58: =-IF($E58=BV$3,$G58,0)+IF($H58=BV$3,$J58,0)
B59: 2 | C59: 25 | D59: Power Automate for desktop業務自動化最強レシピ RPAツールによる自動化＆効率化ノウハウ | E59: 524 | F59: =IF(E59="","",IF(ISNA(VLOOKUP(E59,科目コード表!$C$4:$D$67,2,FALSE)),"該当科目なし",VLOOKUP(E59,科目コード表!$C$4:$D$67,2,FALSE))) | G59: 3300 | I59: =IF(H59="","",IF(ISNA(VLOOKUP(H59,科目コード表!$C$4:$D$67,2,FALSE)),"該当科目なし",VLOOKUP(H59,科目コード表!$C$4:$D$67,2,FALSE))) | L59: =IF($E59=L$3,$G59,0)-IF($H59=L$3,$J59,0) | M59: =IF($E59=M$3,$G59,0)-IF($H59=M$3,$J59,0) | N59: =IF($E59=N$3,$G59,0)-IF($H59=N$3,$J59,0) | O59: =IF($E59=O$3,$G59,0)-IF($H59=O$3,$J59,0) | P59: =IF($E59=P$3,$G59,0)-IF($H59=P$3,$J59,0) | Q59: =IF($E59=Q$3,$G59,0)-IF($H59=Q$3,$J59,0) | R59: =IF($E59=R$3,$G59,0)-IF($H59=R$3,$J59,0) | S59: =IF($E59=S$3,$G59,0)-IF($H59=S$3,$J59,0) | ... AL59: =IF($E59=AL$3,$G59,0)-IF($H59=AL$3,$J59,0) | AM59: =-IF($E59=AM$3,$G59,0)+IF($H59=AM$3,$J59,0) | AN59: =-IF($E59=AN$3,$G59,0)+IF($H59=AN$3,$J59,0) | AO59: =-IF($E59=AO$3,$G59,0)+IF($H59=AO$3,$J59,0) | AP59: =IF($E59=AP$3,$G59,0)-IF($H59=AP$3,$J59,0) | AQ59: =IF($E59=AQ$3,$G59,0)-IF($H59=AQ$3,$J59,0) | AR59: =IF($E59=AR$3,$G59,0)-IF($H59=AR$3,$J59,0) | AS59: =IF($E59=AS$3,$G59,0)-IF($H59=AS$3,$J59,0) | AT59: =IF($E59=AT$3,$G59,0)-IF($H59=AT$3,$J59,0) | AU59: =IF($E59=AU$3,$G59,0)-IF($H59=AU$3,$J59,0) | AV59: =IF($E59=AV$3,$G59,0)-IF($H59=AV$3,$J59,0) | AW59: =IF($E59=AW$3,$G59,0)-IF($H59=AW$3,$J59,0) | ... BK59: =IF($E59=BK$3,$G59,0)-IF($H59=BK$3,$J59,0) | BL59: =-IF($E59=BL$3,$G59,0)+IF($H59=BL$3,$J59,0) | BM59: =-IF($E59=BM$3,$G59,0)+IF($H59=BM$3,$J59,0) | BN59: =-IF($E59=BN$3,$G59,0)+IF($H59=BN$3,$J59,0) | BO59: =-IF($E59=BO$3,$G59,0)+IF($H59=BO$3,$J59,0) | BP59: =-IF($E59=BP$3,$G59,0)+IF($H59=BP$3,$J59,0) | BQ59: =-IF($E59=BQ$3,$G59,0)+IF($H59=BQ$3,$J59,0) | BR59: =-IF($E59=BR$3,$G59,0)+IF($H59=BR$3,$J59,0) | BS59: =-IF($E59=BS$3,$G59,0)+IF($H59=BS$3,$J59,0) | BT59: =-IF($E59=BT$3,$G59,0)+IF($H59=BT$3,$J59,0) | BU59: =+G59-J59 | BV59: =-IF($E59=BV$3,$G59,0)+IF($H59=BV$3,$J59,0)
B60: 2 | C60: 27 | D60: 杉村太蔵の推し株「骨太」投資術 | E60: 524 | F60: =IF(E60="","",IF(ISNA(VLOOKUP(E60,科目コード表!$C$4:$D$67,2,FALSE)),"該当科目なし",VLOOKUP(E60,科目コード表!$C$4:$D$67,2,FALSE))) | G60: 1800 | I60: =IF(H60="","",IF(ISNA(VLOOKUP(H60,科目コード表!$C$4:$D$67,2,FALSE)),"該当科目なし",VLOOKUP(H60,科目コード表!$C$4:$D$67,2,FALSE))) | L60: =IF($E60=L$3,$G60,0)-IF($H60=L$3,$J60,0) | M60: =IF($E60=M$3,$G60,0)-IF($H60=M$3,$J60,0) | N60: =IF($E60=N$3,$G60,0)-IF($H60=N$3,$J60,0) | O60: =IF($E60=O$3,$G60,0)-IF($H60=O$3,$J60,0) | P60: =IF($E60=P$3,$G60,0)-IF($H60=P$3,$J60,0) | Q60: =IF($E60=Q$3,$G60,0)-IF($H60=Q$3,$J60,0) | R60: =IF($E60=R$3,$G60,0)-IF($H60=R$3,$J60,0) | S60: =IF($E60=S$3,$G60,0)-IF($H60=S$3,$J60,0) | ... AL60: =IF($E60=AL$3,$G60,0)-IF($H60=AL$3,$J60,0) | AM60: =-IF($E60=AM$3,$G60,0)+IF($H60=AM$3,$J60,0) | AN60: =-IF($E60=AN$3,$G60,0)+IF($H60=AN$3,$J60,0) | AO60: =-IF($E60=AO$3,$G60,0)+IF($H60=AO$3,$J60,0) | AP60: =IF($E60=AP$3,$G60,0)-IF($H60=AP$3,$J60,0) | AQ60: =IF($E60=AQ$3,$G60,0)-IF($H60=AQ$3,$J60,0) | AR60: =IF($E60=AR$3,$G60,0)-IF($H60=AR$3,$J60,0) | AS60: =IF($E60=AS$3,$G60,0)-IF($H60=AS$3,$J60,0) | AT60: =IF($E60=AT$3,$G60,0)-IF($H60=AT$3,$J60,0) | AU60: =IF($E60=AU$3,$G60,0)-IF($H60=AU$3,$J60,0) | AV60: =IF($E60=AV$3,$G60,0)-IF($H60=AV$3,$J60,0) | AW60: =IF($E60=AW$3,$G60,0)-IF($H60=AW$3,$J60,0) | ... BK60: =IF($E60=BK$3,$G60,0)-IF($H60=BK$3,$J60,0) | BL60: =-IF($E60=BL$3,$G60,0)+IF($H60=BL$3,$J60,0) | BM60: =-IF($E60=BM$3,$G60,0)+IF($H60=BM$3,$J60,0) | BN60: =-IF($E60=BN$3,$G60,0)+IF($H60=BN$3,$J60,0) | BO60: =-IF($E60=BO$3,$G60,0)+IF($H60=BO$3,$J60,0) | BP60: =-IF($E60=BP$3,$G60,0)+IF($H60=BP$3,$J60,0) | BQ60: =-IF($E60=BQ$3,$G60,0)+IF($H60=BQ$3,$J60,0) | BR60: =-IF($E60=BR$3,$G60,0)+IF($H60=BR$3,$J60,0) | BS60: =-IF($E60=BS$3,$G60,0)+IF($H60=BS$3,$J60,0) | BT60: =-IF($E60=BT$3,$G60,0)+IF($H60=BT$3,$J60,0) | BU60: =+G60-J60 | BV60: =-IF($E60=BV$3,$G60,0)+IF($H60=BV$3,$J60,0)
B61: 2 | C61: 27 | D61: 会社四季報プロ500 2026年春号 | E61: 524 | F61: =IF(E61="","",IF(ISNA(VLOOKUP(E61,科目コード表!$C$4:$D$67,2,FALSE)),"該当科目なし",VLOOKUP(E61,科目コード表!$C$4:$D$67,2,FALSE))) | G61: 1880 | I61: =IF(H61="","",IF(ISNA(VLOOKUP(H61,科目コード表!$C$4:$D$67,2,FALSE)),"該当科目なし",VLOOKUP(H61,科目コード表!$C$4:$D$67,2,FALSE))) | L61: =IF($E61=L$3,$G61,0)-IF($H61=L$3,$J61,0) | M61: =IF($E61=M$3,$G61,0)-IF($H61=M$3,$J61,0) | N61: =IF($E61=N$3,$G61,0)-IF($H61=N$3,$J61,0) | O61: =IF($E61=O$3,$G61,0)-IF($H61=O$3,$J61,0) | P61: =IF($E61=P$3,$G61,0)-IF($H61=P$3,$J61,0) | Q61: =IF($E61=Q$3,$G61,0)-IF($H61=Q$3,$J61,0) | R61: =IF($E61=R$3,$G61,0)-IF($H61=R$3,$J61,0) | S61: =IF($E61=S$3,$G61,0)-IF($H61=S$3,$J61,0) | ... AL61: =IF($E61=AL$3,$G61,0)-IF($H61=AL$3,$J61,0) | AM61: =-IF($E61=AM$3,$G61,0)+IF($H61=AM$3,$J61,0) | AN61: =-IF($E61=AN$3,$G61,0)+IF($H61=AN$3,$J61,0) | AO61: =-IF($E61=AO$3,$G61,0)+IF($H61=AO$3,$J61,0) | AP61: =IF($E61=AP$3,$G61,0)-IF($H61=AP$3,$J61,0) | AQ61: =IF($E61=AQ$3,$G61,0)-IF($H61=AQ$3,$J61,0) | AR61: =IF($E61=AR$3,$G61,0)-IF($H61=AR$3,$J61,0) | AS61: =IF($E61=AS$3,$G61,0)-IF($H61=AS$3,$J61,0) | AT61: =IF($E61=AT$3,$G61,0)-IF($H61=AT$3,$J61,0) | AU61: =IF($E61=AU$3,$G61,0)-IF($H61=AU$3,$J61,0) | AV61: =IF($E61=AV$3,$G61,0)-IF($H61=AV$3,$J61,0) | AW61: =IF($E61=AW$3,$G61,0)-IF($H61=AW$3,$J61,0) | ... BK61: =IF($E61=BK$3,$G61,0)-IF($H61=BK$3,$J61,0) | BL61: =-IF($E61=BL$3,$G61,0)+IF($H61=BL$3,$J61,0) | BM61: =-IF($E61=BM$3,$G61,0)+IF($H61=BM$3,$J61,0) | BN61: =-IF($E61=BN$3,$G61,0)+IF($H61=BN$3,$J61,0) | BO61: =-IF($E61=BO$3,$G61,0)+IF($H61=BO$3,$J61,0) | BP61: =-IF($E61=BP$3,$G61,0)+IF($H61=BP$3,$J61,0) | BQ61: =-IF($E61=BQ$3,$G61,0)+IF($H61=BQ$3,$J61,0) | BR61: =-IF($E61=BR$3,$G61,0)+IF($H61=BR$3,$J61,0) | BS61: =-IF($E61=BS$3,$G61,0)+IF($H61=BS$3,$J61,0) | BT61: =-IF($E61=BT$3,$G61,0)+IF($H61=BT$3,$J61,0) | BU61: =+G61-J61 | BV61: =-IF($E61=BV$3,$G61,0)+IF($H61=BV$3,$J61,0)
B62: 2 | C62: 27 | D62: エミン流「会社四季報」最強の読み方 | E62: 524 | F62: =IF(E62="","",IF(ISNA(VLOOKUP(E62,科目コード表!$C$4:$D$67,2,FALSE)),"該当科目なし",VLOOKUP(E62,科目コード表!$C$4:$D$67,2,FALSE))) | G62: 1683 | I62: =IF(H62="","",IF(ISNA(VLOOKUP(H62,科目コード表!$C$4:$D$67,2,FALSE)),"該当科目なし",VLOOKUP(H62,科目コード表!$C$4:$D$67,2,FALSE))) | L62: =IF($E62=L$3,$G62,0)-IF($H62=L$3,$J62,0) | M62: =IF($E62=M$3,$G62,0)-IF($H62=M$3,$J62,0) | N62: =IF($E62=N$3,$G62,0)-IF($H62=N$3,$J62,0) | O62: =IF($E62=O$3,$G62,0)-IF($H62=O$3,$J62,0) | P62: =IF($E62=P$3,$G62,0)-IF($H62=P$3,$J62,0) | Q62: =IF($E62=Q$3,$G62,0)-IF($H62=Q$3,$J62,0) | R62: =IF($E62=R$3,$G62,0)-IF($H62=R$3,$J62,0) | S62: =IF($E62=S$3,$G62,0)-IF($H62=S$3,$J62,0) | ... AL62: =IF($E62=AL$3,$G62,0)-IF($H62=AL$3,$J62,0) | AM62: =-IF($E62=AM$3,$G62,0)+IF($H62=AM$3,$J62,0) | AN62: =-IF($E62=AN$3,$G62,0)+IF($H62=AN$3,$J62,0) | AO62: =-IF($E62=AO$3,$G62,0)+IF($H62=AO$3,$J62,0) | AP62: =IF($E62=AP$3,$G62,0)-IF($H62=AP$3,$J62,0) | AQ62: =IF($E62=AQ$3,$G62,0)-IF($H62=AQ$3,$J62,0) | AR62: =IF($E62=AR$3,$G62,0)-IF($H62=AR$3,$J62,0) | AS62: =IF($E62=AS$3,$G62,0)-IF($H62=AS$3,$J62,0) | AT62: =IF($E62=AT$3,$G62,0)-IF($H62=AT$3,$J62,0) | AU62: =IF($E62=AU$3,$G62,0)-IF($H62=AU$3,$J62,0) | AV62: =IF($E62=AV$3,$G62,0)-IF($H62=AV$3,$J62,0) | AW62: =IF($E62=AW$3,$G62,0)-IF($H62=AW$3,$J62,0) | ... BK62: =IF($E62=BK$3,$G62,0)-IF($H62=BK$3,$J62,0) | BL62: =-IF($E62=BL$3,$G62,0)+IF($H62=BL$3,$J62,0) | BM62: =-IF($E62=BM$3,$G62,0)+IF($H62=BM$3,$J62,0) | BN62: =-IF($E62=BN$3,$G62,0)+IF($H62=BN$3,$J62,0) | BO62: =-IF($E62=BO$3,$G62,0)+IF($H62=BO$3,$J62,0) | BP62: =-IF($E62=BP$3,$G62,0)+IF($H62=BP$3,$J62,0) | BQ62: =-IF($E62=BQ$3,$G62,0)+IF($H62=BQ$3,$J62,0) | BR62: =-IF($E62=BR$3,$G62,0)+IF($H62=BR$3,$J62,0) | BS62: =-IF($E62=BS$3,$G62,0)+IF($H62=BS$3,$J62,0) | BT62: =-IF($E62=BT$3,$G62,0)+IF($H62=BT$3,$J62,0) | BU62: =+G62-J62 | BV62: =-IF($E62=BV$3,$G62,0)+IF($H62=BV$3,$J62,0)
B63: 2 | C63: 27 | D63: 高速取引・AI・アルゴのやっかいな値動きに負けない 弱者でも勝ち続ける「株」投資術 | E63: 524 | F63: =IF(E63="","",IF(ISNA(VLOOKUP(E63,科目コード表!$C$4:$D$67,2,FALSE)),"該当科目なし",VLOOKUP(E63,科目コード表!$C$4:$D$67,2,FALSE))) | G63: 1725 | I63: =IF(H63="","",IF(ISNA(VLOOKUP(H63,科目コード表!$C$4:$D$67,2,FALSE)),"該当科目なし",VLOOKUP(H63,科目コード表!$C$4:$D$67,2,FALSE))) | L63: =IF($E63=L$3,$G63,0)-IF($H63=L$3,$J63,0) | M63: =IF($E63=M$3,$G63,0)-IF($H63=M$3,$J63,0) | N63: =IF($E63=N$3,$G63,0)-IF($H63=N$3,$J63,0) | O63: =IF($E63=O$3,$G63,0)-IF($H63=O$3,$J63,0) | P63: =IF($E63=P$3,$G63,0)-IF($H63=P$3,$J63,0) | Q63: =IF($E63=Q$3,$G63,0)-IF($H63=Q$3,$J63,0) | R63: =IF($E63=R$3,$G63,0)-IF($H63=R$3,$J63,0) | S63: =IF($E63=S$3,$G63,0)-IF($H63=S$3,$J63,0) | ... AL63: =IF($E63=AL$3,$G63,0)-IF($H63=AL$3,$J63,0) | AM63: =-IF($E63=AM$3,$G63,0)+IF($H63=AM$3,$J63,0) | AN63: =-IF($E63=AN$3,$G63,0)+IF($H63=AN$3,$J63,0) | AO63: =-IF($E63=AO$3,$G63,0)+IF($H63=AO$3,$J63,0) | AP63: =IF($E63=AP$3,$G63,0)-IF($H63=AP$3,$J63,0) | AQ63: =IF($E63=AQ$3,$G63,0)-IF($H63=AQ$3,$J63,0) | AR63: =IF($E63=AR$3,$G63,0)-IF($H63=AR$3,$J63,0) | AS63: =IF($E63=AS$3,$G63,0)-IF($H63=AS$3,$J63,0) | AT63: =IF($E63=AT$3,$G63,0)-IF($H63=AT$3,$J63,0) | AU63: =IF($E63=AU$3,$G63,0)-IF($H63=AU$3,$J63,0) | AV63: =IF($E63=AV$3,$G63,0)-IF($H63=AV$3,$J63,0) | AW63: =IF($E63=AW$3,$G63,0)-IF($H63=AW$3,$J63,0) | ... BK63: =IF($E63=BK$3,$G63,0)-IF($H63=BK$3,$J63,0) | BL63: =-IF($E63=BL$3,$G63,0)+IF($H63=BL$3,$J63,0) | BM63: =-IF($E63=BM$3,$G63,0)+IF($H63=BM$3,$J63,0) | BN63: =-IF($E63=BN$3,$G63,0)+IF($H63=BN$3,$J63,0) | BO63: =-IF($E63=BO$3,$G63,0)+IF($H63=BO$3,$J63,0) | BP63: =-IF($E63=BP$3,$G63,0)+IF($H63=BP$3,$J63,0) | BQ63: =-IF($E63=BQ$3,$G63,0)+IF($H63=BQ$3,$J63,0) | BR63: =-IF($E63=BR$3,$G63,0)+IF($H63=BR$3,$J63,0) | BS63: =-IF($E63=BS$3,$G63,0)+IF($H63=BS$3,$J63,0) | BT63: =-IF($E63=BT$3,$G63,0)+IF($H63=BT$3,$J63,0) | BU63: =+G63-J63 | BV63: =-IF($E63=BV$3,$G63,0)+IF($H63=BV$3,$J63,0)
B64: 2 | C64: 28 | D64: 売上 小樽商科大学後援会 | E64: 107 | F64: =IF(E64="","",IF(ISNA(VLOOKUP(E64,科目コード表!$C$4:$D$67,2,FALSE)),"該当科目なし",VLOOKUP(E64,科目コード表!$C$4:$D$67,2,FALSE))) | G64: 11000 | H64: 401 | I64: =IF(H64="","",IF(ISNA(VLOOKUP(H64,科目コード表!$C$4:$D$67,2,FALSE)),"該当科目なし",VLOOKUP(H64,科目コード表!$C$4:$D$67,2,FALSE))) | J64: 11000 | L64: =IF($E64=L$3,$G64,0)-IF($H64=L$3,$J64,0) | M64: =IF($E64=M$3,$G64,0)-IF($H64=M$3,$J64,0) | N64: =IF($E64=N$3,$G64,0)-IF($H64=N$3,$J64,0) | O64: =IF($E64=O$3,$G64,0)-IF($H64=O$3,$J64,0) | P64: =IF($E64=P$3,$G64,0)-IF($H64=P$3,$J64,0) | Q64: =IF($E64=Q$3,$G64,0)-IF($H64=Q$3,$J64,0) | R64: =IF($E64=R$3,$G64,0)-IF($H64=R$3,$J64,0) | S64: =IF($E64=S$3,$G64,0)-IF($H64=S$3,$J64,0) | ... AL64: =IF($E64=AL$3,$G64,0)-IF($H64=AL$3,$J64,0) | AM64: =-IF($E64=AM$3,$G64,0)+IF($H64=AM$3,$J64,0) | AN64: =-IF($E64=AN$3,$G64,0)+IF($H64=AN$3,$J64,0) | AO64: =-IF($E64=AO$3,$G64,0)+IF($H64=AO$3,$J64,0) | AP64: =IF($E64=AP$3,$G64,0)-IF($H64=AP$3,$J64,0) | AQ64: =IF($E64=AQ$3,$G64,0)-IF($H64=AQ$3,$J64,0) | AR64: =IF($E64=AR$3,$G64,0)-IF($H64=AR$3,$J64,0) | AS64: =IF($E64=AS$3,$G64,0)-IF($H64=AS$3,$J64,0) | AT64: =IF($E64=AT$3,$G64,0)-IF($H64=AT$3,$J64,0) | AU64: =IF($E64=AU$3,$G64,0)-IF($H64=AU$3,$J64,0) | AV64: =IF($E64=AV$3,$G64,0)-IF($H64=AV$3,$J64,0) | AW64: =IF($E64=AW$3,$G64,0)-IF($H64=AW$3,$J64,0) | ... BK64: =IF($E64=BK$3,$G64,0)-IF($H64=BK$3,$J64,0) | BL64: =-IF($E64=BL$3,$G64,0)+IF($H64=BL$3,$J64,0) | BM64: =-IF($E64=BM$3,$G64,0)+IF($H64=BM$3,$J64,0) | BN64: =-IF($E64=BN$3,$G64,0)+IF($H64=BN$3,$J64,0) | BO64: =-IF($E64=BO$3,$G64,0)+IF($H64=BO$3,$J64,0) | BP64: =-IF($E64=BP$3,$G64,0)+IF($H64=BP$3,$J64,0) | BQ64: =-IF($E64=BQ$3,$G64,0)+IF($H64=BQ$3,$J64,0) | BR64: =-IF($E64=BR$3,$G64,0)+IF($H64=BR$3,$J64,0) | BS64: =-IF($E64=BS$3,$G64,0)+IF($H64=BS$3,$J64,0) | BT64: =-IF($E64=BT$3,$G64,0)+IF($H64=BT$3,$J64,0) | BU64: =+G64-J64 | BV64: =-IF($E64=BV$3,$G64,0)+IF($H64=BV$3,$J64,0)
B65: 2 | C65: 28 | D65: 売上 ユーユー | E65: 107 | F65: =IF(E65="","",IF(ISNA(VLOOKUP(E65,科目コード表!$C$4:$D$67,2,FALSE)),"該当科目なし",VLOOKUP(E65,科目コード表!$C$4:$D$67,2,FALSE))) | G65: 100000 | H65: 401 | I65: =IF(H65="","",IF(ISNA(VLOOKUP(H65,科目コード表!$C$4:$D$67,2,FALSE)),"該当科目なし",VLOOKUP(H65,科目コード表!$C$4:$D$67,2,FALSE))) | J65: 100000 | L65: =IF($E65=L$3,$G65,0)-IF($H65=L$3,$J65,0) | M65: =IF($E65=M$3,$G65,0)-IF($H65=M$3,$J65,0) | N65: =IF($E65=N$3,$G65,0)-IF($H65=N$3,$J65,0) | O65: =IF($E65=O$3,$G65,0)-IF($H65=O$3,$J65,0) | P65: =IF($E65=P$3,$G65,0)-IF($H65=P$3,$J65,0) | Q65: =IF($E65=Q$3,$G65,0)-IF($H65=Q$3,$J65,0) | R65: =IF($E65=R$3,$G65,0)-IF($H65=R$3,$J65,0) | S65: =IF($E65=S$3,$G65,0)-IF($H65=S$3,$J65,0) | ... AL65: =IF($E65=AL$3,$G65,0)-IF($H65=AL$3,$J65,0) | AM65: =-IF($E65=AM$3,$G65,0)+IF($H65=AM$3,$J65,0) | AN65: =-IF($E65=AN$3,$G65,0)+IF($H65=AN$3,$J65,0) | AO65: =-IF($E65=AO$3,$G65,0)+IF($H65=AO$3,$J65,0) | AP65: =IF($E65=AP$3,$G65,0)-IF($H65=AP$3,$J65,0) | AQ65: =IF($E65=AQ$3,$G65,0)-IF($H65=AQ$3,$J65,0) | AR65: =IF($E65=AR$3,$G65,0)-IF($H65=AR$3,$J65,0) | AS65: =IF($E65=AS$3,$G65,0)-IF($H65=AS$3,$J65,0) | AT65: =IF($E65=AT$3,$G65,0)-IF($H65=AT$3,$J65,0) | AU65: =IF($E65=AU$3,$G65,0)-IF($H65=AU$3,$J65,0) | AV65: =IF($E65=AV$3,$G65,0)-IF($H65=AV$3,$J65,0) | AW65: =IF($E65=AW$3,$G65,0)-IF($H65=AW$3,$J65,0) | ... BK65: =IF($E65=BK$3,$G65,0)-IF($H65=BK$3,$J65,0) | BL65: =-IF($E65=BL$3,$G65,0)+IF($H65=BL$3,$J65,0) | BM65: =-IF($E65=BM$3,$G65,0)+IF($H65=BM$3,$J65,0) | BN65: =-IF($E65=BN$3,$G65,0)+IF($H65=BN$3,$J65,0) | BO65: =-IF($E65=BO$3,$G65,0)+IF($H65=BO$3,$J65,0) | BP65: =-IF($E65=BP$3,$G65,0)+IF($H65=BP$3,$J65,0) | BQ65: =-IF($E65=BQ$3,$G65,0)+IF($H65=BQ$3,$J65,0) | BR65: =-IF($E65=BR$3,$G65,0)+IF($H65=BR$3,$J65,0) | BS65: =-IF($E65=BS$3,$G65,0)+IF($H65=BS$3,$J65,0) | BT65: =-IF($E65=BT$3,$G65,0)+IF($H65=BT$3,$J65,0) | BU65: =+G65-J65 | BV65: =-IF($E65=BV$3,$G65,0)+IF($H65=BV$3,$J65,0)
B66: 2 | C66: 28 | D66: Interface(インターフェース) 2026年4月号 | E66: 524 | F66: =IF(E66="","",IF(ISNA(VLOOKUP(E66,科目コード表!$C$4:$D$67,2,FALSE)),"該当科目なし",VLOOKUP(E66,科目コード表!$C$4:$D$67,2,FALSE))) | G66: 1430 | I66: =IF(H66="","",IF(ISNA(VLOOKUP(H66,科目コード表!$C$4:$D$67,2,FALSE)),"該当科目なし",VLOOKUP(H66,科目コード表!$C$4:$D$67,2,FALSE))) | L66: =IF($E66=L$3,$G66,0)-IF($H66=L$3,$J66,0) | M66: =IF($E66=M$3,$G66,0)-IF($H66=M$3,$J66,0) | N66: =IF($E66=N$3,$G66,0)-IF($H66=N$3,$J66,0) | O66: =IF($E66=O$3,$G66,0)-IF($H66=O$3,$J66,0) | P66: =IF($E66=P$3,$G66,0)-IF($H66=P$3,$J66,0) | Q66: =IF($E66=Q$3,$G66,0)-IF($H66=Q$3,$J66,0) | R66: =IF($E66=R$3,$G66,0)-IF($H66=R$3,$J66,0) | S66: =IF($E66=S$3,$G66,0)-IF($H66=S$3,$J66,0) | ... AL66: =IF($E66=AL$3,$G66,0)-IF($H66=AL$3,$J66,0) | AM66: =-IF($E66=AM$3,$G66,0)+IF($H66=AM$3,$J66,0) | AN66: =-IF($E66=AN$3,$G66,0)+IF($H66=AN$3,$J66,0) | AO66: =-IF($E66=AO$3,$G66,0)+IF($H66=AO$3,$J66,0) | AP66: =IF($E66=AP$3,$G66,0)-IF($H66=AP$3,$J66,0) | AQ66: =IF($E66=AQ$3,$G66,0)-IF($H66=AQ$3,$J66,0) | AR66: =IF($E66=AR$3,$G66,0)-IF($H66=AR$3,$J66,0) | AS66: =IF($E66=AS$3,$G66,0)-IF($H66=AS$3,$J66,0) | AT66: =IF($E66=AT$3,$G66,0)-IF($H66=AT$3,$J66,0) | AU66: =IF($E66=AU$3,$G66,0)-IF($H66=AU$3,$J66,0) | AV66: =IF($E66=AV$3,$G66,0)-IF($H66=AV$3,$J66,0) | AW66: =IF($E66=AW$3,$G66,0)-IF($H66=AW$3,$J66,0) | ... BK66: =IF($E66=BK$3,$G66,0)-IF($H66=BK$3,$J66,0) | BL66: =-IF($E66=BL$3,$G66,0)+IF($H66=BL$3,$J66,0) | BM66: =-IF($E66=BM$3,$G66,0)+IF($H66=BM$3,$J66,0) | BN66: =-IF($E66=BN$3,$G66,0)+IF($H66=BN$3,$J66,0) | BO66: =-IF($E66=BO$3,$G66,0)+IF($H66=BO$3,$J66,0) | BP66: =-IF($E66=BP$3,$G66,0)+IF($H66=BP$3,$J66,0) | BQ66: =-IF($E66=BQ$3,$G66,0)+IF($H66=BQ$3,$J66,0) | BR66: =-IF($E66=BR$3,$G66,0)+IF($H66=BR$3,$J66,0) | BS66: =-IF($E66=BS$3,$G66,0)+IF($H66=BS$3,$J66,0) | BT66: =-IF($E66=BT$3,$G66,0)+IF($H66=BT$3,$J66,0) | BU66: =+G66-J66 | BV66: =-IF($E66=BV$3,$G66,0)+IF($H66=BV$3,$J66,0)
B67: 2 | C67: 28 | D67: Interface(インターフェース) 2026年3月号 | E67: 524 | F67: =IF(E67="","",IF(ISNA(VLOOKUP(E67,科目コード表!$C$4:$D$67,2,FALSE)),"該当科目なし",VLOOKUP(E67,科目コード表!$C$4:$D$67,2,FALSE))) | G67: 1430 | I67: =IF(H67="","",IF(ISNA(VLOOKUP(H67,科目コード表!$C$4:$D$67,2,FALSE)),"該当科目なし",VLOOKUP(H67,科目コード表!$C$4:$D$67,2,FALSE))) | L67: =IF($E67=L$3,$G67,0)-IF($H67=L$3,$J67,0) | M67: =IF($E67=M$3,$G67,0)-IF($H67=M$3,$J67,0) | N67: =IF($E67=N$3,$G67,0)-IF($H67=N$3,$J67,0) | O67: =IF($E67=O$3,$G67,0)-IF($H67=O$3,$J67,0) | P67: =IF($E67=P$3,$G67,0)-IF($H67=P$3,$J67,0) | Q67: =IF($E67=Q$3,$G67,0)-IF($H67=Q$3,$J67,0) | R67: =IF($E67=R$3,$G67,0)-IF($H67=R$3,$J67,0) | S67: =IF($E67=S$3,$G67,0)-IF($H67=S$3,$J67,0) | ... AL67: =IF($E67=AL$3,$G67,0)-IF($H67=AL$3,$J67,0) | AM67: =-IF($E67=AM$3,$G67,0)+IF($H67=AM$3,$J67,0) | AN67: =-IF($E67=AN$3,$G67,0)+IF($H67=AN$3,$J67,0) | AO67: =-IF($E67=AO$3,$G67,0)+IF($H67=AO$3,$J67,0) | AP67: =IF($E67=AP$3,$G67,0)-IF($H67=AP$3,$J67,0) | AQ67: =IF($E67=AQ$3,$G67,0)-IF($H67=AQ$3,$J67,0) | AR67: =IF($E67=AR$3,$G67,0)-IF($H67=AR$3,$J67,0) | AS67: =IF($E67=AS$3,$G67,0)-IF($H67=AS$3,$J67,0) | AT67: =IF($E67=AT$3,$G67,0)-IF($H67=AT$3,$J67,0) | AU67: =IF($E67=AU$3,$G67,0)-IF($H67=AU$3,$J67,0) | AV67: =IF($E67=AV$3,$G67,0)-IF($H67=AV$3,$J67,0) | AW67: =IF($E67=AW$3,$G67,0)-IF($H67=AW$3,$J67,0) | ... BK67: =IF($E67=BK$3,$G67,0)-IF($H67=BK$3,$J67,0) | BL67: =-IF($E67=BL$3,$G67,0)+IF($H67=BL$3,$J67,0) | BM67: =-IF($E67=BM$3,$G67,0)+IF($H67=BM$3,$J67,0) | BN67: =-IF($E67=BN$3,$G67,0)+IF($H67=BN$3,$J67,0) | BO67: =-IF($E67=BO$3,$G67,0)+IF($H67=BO$3,$J67,0) | BP67: =-IF($E67=BP$3,$G67,0)+IF($H67=BP$3,$J67,0) | BQ67: =-IF($E67=BQ$3,$G67,0)+IF($H67=BQ$3,$J67,0) | BR67: =-IF($E67=BR$3,$G67,0)+IF($H67=BR$3,$J67,0) | BS67: =-IF($E67=BS$3,$G67,0)+IF($H67=BS$3,$J67,0) | BT67: =-IF($E67=BT$3,$G67,0)+IF($H67=BT$3,$J67,0) | BU67: =+G67-J67 | BV67: =-IF($E67=BV$3,$G67,0)+IF($H67=BV$3,$J67,0)
B68: 2 | C68: 28 | D68: Interface(インターフェース) 2025年12号 | E68: 524 | F68: =IF(E68="","",IF(ISNA(VLOOKUP(E68,科目コード表!$C$4:$D$67,2,FALSE)),"該当科目なし",VLOOKUP(E68,科目コード表!$C$4:$D$67,2,FALSE))) | G68: 1430 | I68: =IF(H68="","",IF(ISNA(VLOOKUP(H68,科目コード表!$C$4:$D$67,2,FALSE)),"該当科目なし",VLOOKUP(H68,科目コード表!$C$4:$D$67,2,FALSE))) | L68: =IF($E68=L$3,$G68,0)-IF($H68=L$3,$J68,0) | M68: =IF($E68=M$3,$G68,0)-IF($H68=M$3,$J68,0) | N68: =IF($E68=N$3,$G68,0)-IF($H68=N$3,$J68,0) | O68: =IF($E68=O$3,$G68,0)-IF($H68=O$3,$J68,0) | P68: =IF($E68=P$3,$G68,0)-IF($H68=P$3,$J68,0) | Q68: =IF($E68=Q$3,$G68,0)-IF($H68=Q$3,$J68,0) | R68: =IF($E68=R$3,$G68,0)-IF($H68=R$3,$J68,0) | S68: =IF($E68=S$3,$G68,0)-IF($H68=S$3,$J68,0) | ... AL68: =IF($E68=AL$3,$G68,0)-IF($H68=AL$3,$J68,0) | AM68: =-IF($E68=AM$3,$G68,0)+IF($H68=AM$3,$J68,0) | AN68: =-IF($E68=AN$3,$G68,0)+IF($H68=AN$3,$J68,0) | AO68: =-IF($E68=AO$3,$G68,0)+IF($H68=AO$3,$J68,0) | AP68: =IF($E68=AP$3,$G68,0)-IF($H68=AP$3,$J68,0) | AQ68: =IF($E68=AQ$3,$G68,0)-IF($H68=AQ$3,$J68,0) | AR68: =IF($E68=AR$3,$G68,0)-IF($H68=AR$3,$J68,0) | AS68: =IF($E68=AS$3,$G68,0)-IF($H68=AS$3,$J68,0) | AT68: =IF($E68=AT$3,$G68,0)-IF($H68=AT$3,$J68,0) | AU68: =IF($E68=AU$3,$G68,0)-IF($H68=AU$3,$J68,0) | AV68: =IF($E68=AV$3,$G68,0)-IF($H68=AV$3,$J68,0) | AW68: =IF($E68=AW$3,$G68,0)-IF($H68=AW$3,$J68,0) | ... BK68: =IF($E68=BK$3,$G68,0)-IF($H68=BK$3,$J68,0) | BL68: =-IF($E68=BL$3,$G68,0)+IF($H68=BL$3,$J68,0) | BM68: =-IF($E68=BM$3,$G68,0)+IF($H68=BM$3,$J68,0) | BN68: =-IF($E68=BN$3,$G68,0)+IF($H68=BN$3,$J68,0) | BO68: =-IF($E68=BO$3,$G68,0)+IF($H68=BO$3,$J68,0) | BP68: =-IF($E68=BP$3,$G68,0)+IF($H68=BP$3,$J68,0) | BQ68: =-IF($E68=BQ$3,$G68,0)+IF($H68=BQ$3,$J68,0) | BR68: =-IF($E68=BR$3,$G68,0)+IF($H68=BR$3,$J68,0) | BS68: =-IF($E68=BS$3,$G68,0)+IF($H68=BS$3,$J68,0) | BT68: =-IF($E68=BT$3,$G68,0)+IF($H68=BT$3,$J68,0) | BU68: =+G68-J68 | BV68: =-IF($E68=BV$3,$G68,0)+IF($H68=BV$3,$J68,0)
B69: 2 | C69: 28 | D69: Interface(インターフェース) 2026年 1月号 | E69: 524 | F69: =IF(E69="","",IF(ISNA(VLOOKUP(E69,科目コード表!$C$4:$D$67,2,FALSE)),"該当科目なし",VLOOKUP(E69,科目コード表!$C$4:$D$67,2,FALSE))) | G69: 1430 | I69: =IF(H69="","",IF(ISNA(VLOOKUP(H69,科目コード表!$C$4:$D$67,2,FALSE)),"該当科目なし",VLOOKUP(H69,科目コード表!$C$4:$D$67,2,FALSE))) | L69: =IF($E69=L$3,$G69,0)-IF($H69=L$3,$J69,0) | M69: =IF($E69=M$3,$G69,0)-IF($H69=M$3,$J69,0) | N69: =IF($E69=N$3,$G69,0)-IF($H69=N$3,$J69,0) | O69: =IF($E69=O$3,$G69,0)-IF($H69=O$3,$J69,0) | P69: =IF($E69=P$3,$G69,0)-IF($H69=P$3,$J69,0) | Q69: =IF($E69=Q$3,$G69,0)-IF($H69=Q$3,$J69,0) | R69: =IF($E69=R$3,$G69,0)-IF($H69=R$3,$J69,0) | S69: =IF($E69=S$3,$G69,0)-IF($H69=S$3,$J69,0) | ... AL69: =IF($E69=AL$3,$G69,0)-IF($H69=AL$3,$J69,0) | AM69: =-IF($E69=AM$3,$G69,0)+IF($H69=AM$3,$J69,0) | AN69: =-IF($E69=AN$3,$G69,0)+IF($H69=AN$3,$J69,0) | AO69: =-IF($E69=AO$3,$G69,0)+IF($H69=AO$3,$J69,0) | AP69: =IF($E69=AP$3,$G69,0)-IF($H69=AP$3,$J69,0) | AQ69: =IF($E69=AQ$3,$G69,0)-IF($H69=AQ$3,$J69,0) | AR69: =IF($E69=AR$3,$G69,0)-IF($H69=AR$3,$J69,0) | AS69: =IF($E69=AS$3,$G69,0)-IF($H69=AS$3,$J69,0) | AT69: =IF($E69=AT$3,$G69,0)-IF($H69=AT$3,$J69,0) | AU69: =IF($E69=AU$3,$G69,0)-IF($H69=AU$3,$J69,0) | AV69: =IF($E69=AV$3,$G69,0)-IF($H69=AV$3,$J69,0) | AW69: =IF($E69=AW$3,$G69,0)-IF($H69=AW$3,$J69,0) | ... BK69: =IF($E69=BK$3,$G69,0)-IF($H69=BK$3,$J69,0) | BL69: =-IF($E69=BL$3,$G69,0)+IF($H69=BL$3,$J69,0) | BM69: =-IF($E69=BM$3,$G69,0)+IF($H69=BM$3,$J69,0) | BN69: =-IF($E69=BN$3,$G69,0)+IF($H69=BN$3,$J69,0) | BO69: =-IF($E69=BO$3,$G69,0)+IF($H69=BO$3,$J69,0) | BP69: =-IF($E69=BP$3,$G69,0)+IF($H69=BP$3,$J69,0) | BQ69: =-IF($E69=BQ$3,$G69,0)+IF($H69=BQ$3,$J69,0) | BR69: =-IF($E69=BR$3,$G69,0)+IF($H69=BR$3,$J69,0) | BS69: =-IF($E69=BS$3,$G69,0)+IF($H69=BS$3,$J69,0) | BT69: =-IF($E69=BT$3,$G69,0)+IF($H69=BT$3,$J69,0) | BU69: =+G69-J69 | BV69: =-IF($E69=BV$3,$G69,0)+IF($H69=BV$3,$J69,0)
B70: 2 | C70: 28 | D70: Interface(インターフェース) 2026年2月号 | E70: 524 | F70: =IF(E70="","",IF(ISNA(VLOOKUP(E70,科目コード表!$C$4:$D$67,2,FALSE)),"該当科目なし",VLOOKUP(E70,科目コード表!$C$4:$D$67,2,FALSE))) | G70: 1490 | I70: =IF(H70="","",IF(ISNA(VLOOKUP(H70,科目コード表!$C$4:$D$67,2,FALSE)),"該当科目なし",VLOOKUP(H70,科目コード表!$C$4:$D$67,2,FALSE))) | L70: =IF($E70=L$3,$G70,0)-IF($H70=L$3,$J70,0) | M70: =IF($E70=M$3,$G70,0)-IF($H70=M$3,$J70,0) | N70: =IF($E70=N$3,$G70,0)-IF($H70=N$3,$J70,0) | O70: =IF($E70=O$3,$G70,0)-IF($H70=O$3,$J70,0) | P70: =IF($E70=P$3,$G70,0)-IF($H70=P$3,$J70,0) | Q70: =IF($E70=Q$3,$G70,0)-IF($H70=Q$3,$J70,0) | R70: =IF($E70=R$3,$G70,0)-IF($H70=R$3,$J70,0) | S70: =IF($E70=S$3,$G70,0)-IF($H70=S$3,$J70,0) | ... AL70: =IF($E70=AL$3,$G70,0)-IF($H70=AL$3,$J70,0) | AM70: =-IF($E70=AM$3,$G70,0)+IF($H70=AM$3,$J70,0) | AN70: =-IF($E70=AN$3,$G70,0)+IF($H70=AN$3,$J70,0) | AO70: =-IF($E70=AO$3,$G70,0)+IF($H70=AO$3,$J70,0) | AP70: =IF($E70=AP$3,$G70,0)-IF($H70=AP$3,$J70,0) | AQ70: =IF($E70=AQ$3,$G70,0)-IF($H70=AQ$3,$J70,0) | AR70: =IF($E70=AR$3,$G70,0)-IF($H70=AR$3,$J70,0) | AS70: =IF($E70=AS$3,$G70,0)-IF($H70=AS$3,$J70,0) | AT70: =IF($E70=AT$3,$G70,0)-IF($H70=AT$3,$J70,0) | AU70: =IF($E70=AU$3,$G70,0)-IF($H70=AU$3,$J70,0) | AV70: =IF($E70=AV$3,$G70,0)-IF($H70=AV$3,$J70,0) | AW70: =IF($E70=AW$3,$G70,0)-IF($H70=AW$3,$J70,0) | ... BK70: =IF($E70=BK$3,$G70,0)-IF($H70=BK$3,$J70,0) | BL70: =-IF($E70=BL$3,$G70,0)+IF($H70=BL$3,$J70,0) | BM70: =-IF($E70=BM$3,$G70,0)+IF($H70=BM$3,$J70,0) | BN70: =-IF($E70=BN$3,$G70,0)+IF($H70=BN$3,$J70,0) | BO70: =-IF($E70=BO$3,$G70,0)+IF($H70=BO$3,$J70,0) | BP70: =-IF($E70=BP$3,$G70,0)+IF($H70=BP$3,$J70,0) | BQ70: =-IF($E70=BQ$3,$G70,0)+IF($H70=BQ$3,$J70,0) | BR70: =-IF($E70=BR$3,$G70,0)+IF($H70=BR$3,$J70,0) | BS70: =-IF($E70=BS$3,$G70,0)+IF($H70=BS$3,$J70,0) | BT70: =-IF($E70=BT$3,$G70,0)+IF($H70=BT$3,$J70,0) | BU70: =+G70-J70 | BV70: =-IF($E70=BV$3,$G70,0)+IF($H70=BV$3,$J70,0)
B71: 2 | C71: 28 | D71: 売上BASIS | E71: 107 | F71: =IF(E71="","",IF(ISNA(VLOOKUP(E71,科目コード表!$C$4:$D$67,2,FALSE)),"該当科目なし",VLOOKUP(E71,科目コード表!$C$4:$D$67,2,FALSE))) | G71: 770000 | H71: 401 | I71: =IF(H71="","",IF(ISNA(VLOOKUP(H71,科目コード表!$C$4:$D$67,2,FALSE)),"該当科目なし",VLOOKUP(H71,科目コード表!$C$4:$D$67,2,FALSE))) | J71: 770000 | L71: =IF($E71=L$3,$G71,0)-IF($H71=L$3,$J71,0) | M71: =IF($E71=M$3,$G71,0)-IF($H71=M$3,$J71,0) | N71: =IF($E71=N$3,$G71,0)-IF($H71=N$3,$J71,0) | O71: =IF($E71=O$3,$G71,0)-IF($H71=O$3,$J71,0) | P71: =IF($E71=P$3,$G71,0)-IF($H71=P$3,$J71,0) | Q71: =IF($E71=Q$3,$G71,0)-IF($H71=Q$3,$J71,0) | R71: =IF($E71=R$3,$G71,0)-IF($H71=R$3,$J71,0) | S71: =IF($E71=S$3,$G71,0)-IF($H71=S$3,$J71,0) | ... AL71: =IF($E71=AL$3,$G71,0)-IF($H71=AL$3,$J71,0) | AM71: =-IF($E71=AM$3,$G71,0)+IF($H71=AM$3,$J71,0) | AN71: =-IF($E71=AN$3,$G71,0)+IF($H71=AN$3,$J71,0) | AO71: =-IF($E71=AO$3,$G71,0)+IF($H71=AO$3,$J71,0) | AP71: =IF($E71=AP$3,$G71,0)-IF($H71=AP$3,$J71,0) | AQ71: =IF($E71=AQ$3,$G71,0)-IF($H71=AQ$3,$J71,0) | AR71: =IF($E71=AR$3,$G71,0)-IF($H71=AR$3,$J71,0) | AS71: =IF($E71=AS$3,$G71,0)-IF($H71=AS$3,$J71,0) | AT71: =IF($E71=AT$3,$G71,0)-IF($H71=AT$3,$J71,0) | AU71: =IF($E71=AU$3,$G71,0)-IF($H71=AU$3,$J71,0) | AV71: =IF($E71=AV$3,$G71,0)-IF($H71=AV$3,$J71,0) | AW71: =IF($E71=AW$3,$G71,0)-IF($H71=AW$3,$J71,0) | ... BK71: =IF($E71=BK$3,$G71,0)-IF($H71=BK$3,$J71,0) | BL71: =-IF($E71=BL$3,$G71,0)+IF($H71=BL$3,$J71,0) | BM71: =-IF($E71=BM$3,$G71,0)+IF($H71=BM$3,$J71,0) | BN71: =-IF($E71=BN$3,$G71,0)+IF($H71=BN$3,$J71,0) | BO71: =-IF($E71=BO$3,$G71,0)+IF($H71=BO$3,$J71,0) | BP71: =-IF($E71=BP$3,$G71,0)+IF($H71=BP$3,$J71,0) | BQ71: =-IF($E71=BQ$3,$G71,0)+IF($H71=BQ$3,$J71,0) | BR71: =-IF($E71=BR$3,$G71,0)+IF($H71=BR$3,$J71,0) | BS71: =-IF($E71=BS$3,$G71,0)+IF($H71=BS$3,$J71,0) | BT71: =-IF($E71=BT$3,$G71,0)+IF($H71=BT$3,$J71,0) | BU71: =+G71-J71 | BV71: =-IF($E71=BV$3,$G71,0)+IF($H71=BV$3,$J71,0)
B72: 2 | C72: 29 | D72: エポス さくらインターネット | E72: 525 | F72: =IF(E72="","",IF(ISNA(VLOOKUP(E72,科目コード表!$C$4:$D$67,2,FALSE)),"該当科目なし",VLOOKUP(E72,科目コード表!$C$4:$D$67,2,FALSE))) | G72: 3220 | I72: =IF(H72="","",IF(ISNA(VLOOKUP(H72,科目コード表!$C$4:$D$67,2,FALSE)),"該当科目なし",VLOOKUP(H72,科目コード表!$C$4:$D$67,2,FALSE))) | L72: =IF($E72=L$3,$G72,0)-IF($H72=L$3,$J72,0) | M72: =IF($E72=M$3,$G72,0)-IF($H72=M$3,$J72,0) | N72: =IF($E72=N$3,$G72,0)-IF($H72=N$3,$J72,0) | O72: =IF($E72=O$3,$G72,0)-IF($H72=O$3,$J72,0) | P72: =IF($E72=P$3,$G72,0)-IF($H72=P$3,$J72,0) | Q72: =IF($E72=Q$3,$G72,0)-IF($H72=Q$3,$J72,0) | R72: =IF($E72=R$3,$G72,0)-IF($H72=R$3,$J72,0) | S72: =IF($E72=S$3,$G72,0)-IF($H72=S$3,$J72,0) | ... AL72: =IF($E72=AL$3,$G72,0)-IF($H72=AL$3,$J72,0) | AM72: =-IF($E72=AM$3,$G72,0)+IF($H72=AM$3,$J72,0) | AN72: =-IF($E72=AN$3,$G72,0)+IF($H72=AN$3,$J72,0) | AO72: =-IF($E72=AO$3,$G72,0)+IF($H72=AO$3,$J72,0) | AP72: =IF($E72=AP$3,$G72,0)-IF($H72=AP$3,$J72,0) | AQ72: =IF($E72=AQ$3,$G72,0)-IF($H72=AQ$3,$J72,0) | AR72: =IF($E72=AR$3,$G72,0)-IF($H72=AR$3,$J72,0) | AS72: =IF($E72=AS$3,$G72,0)-IF($H72=AS$3,$J72,0) | AT72: =IF($E72=AT$3,$G72,0)-IF($H72=AT$3,$J72,0) | AU72: =IF($E72=AU$3,$G72,0)-IF($H72=AU$3,$J72,0) | AV72: =IF($E72=AV$3,$G72,0)-IF($H72=AV$3,$J72,0) | AW72: =IF($E72=AW$3,$G72,0)-IF($H72=AW$3,$J72,0) | ... BK72: =IF($E72=BK$3,$G72,0)-IF($H72=BK$3,$J72,0) | BL72: =-IF($E72=BL$3,$G72,0)+IF($H72=BL$3,$J72,0) | BM72: =-IF($E72=BM$3,$G72,0)+IF($H72=BM$3,$J72,0) | BN72: =-IF($E72=BN$3,$G72,0)+IF($H72=BN$3,$J72,0) | BO72: =-IF($E72=BO$3,$G72,0)+IF($H72=BO$3,$J72,0) | BP72: =-IF($E72=BP$3,$G72,0)+IF($H72=BP$3,$J72,0) | BQ72: =-IF($E72=BQ$3,$G72,0)+IF($H72=BQ$3,$J72,0) | BR72: =-IF($E72=BR$3,$G72,0)+IF($H72=BR$3,$J72,0) | BS72: =-IF($E72=BS$3,$G72,0)+IF($H72=BS$3,$J72,0) | BT72: =-IF($E72=BT$3,$G72,0)+IF($H72=BT$3,$J72,0) | BU72: =+G72-J72 | BV72: =-IF($E72=BV$3,$G72,0)+IF($H72=BV$3,$J72,0)
B73: 3 | C73: 2 | D73: 中尾洋一へ地代振込 | E73: 520 | F73: =IF(E73="","",IF(ISNA(VLOOKUP(E73,科目コード表!$C$4:$D$67,2,FALSE)),"該当科目なし",VLOOKUP(E73,科目コード表!$C$4:$D$67,2,FALSE))) | G73: 20000 | I73: =IF(H73="","",IF(ISNA(VLOOKUP(H73,科目コード表!$C$4:$D$67,2,FALSE)),"該当科目なし",VLOOKUP(H73,科目コード表!$C$4:$D$67,2,FALSE))) | L73: =IF($E73=L$3,$G73,0)-IF($H73=L$3,$J73,0) | M73: =IF($E73=M$3,$G73,0)-IF($H73=M$3,$J73,0) | N73: =IF($E73=N$3,$G73,0)-IF($H73=N$3,$J73,0) | O73: =IF($E73=O$3,$G73,0)-IF($H73=O$3,$J73,0) | P73: =IF($E73=P$3,$G73,0)-IF($H73=P$3,$J73,0) | Q73: =IF($E73=Q$3,$G73,0)-IF($H73=Q$3,$J73,0) | R73: =IF($E73=R$3,$G73,0)-IF($H73=R$3,$J73,0) | S73: =IF($E73=S$3,$G73,0)-IF($H73=S$3,$J73,0) | ... AL73: =IF($E73=AL$3,$G73,0)-IF($H73=AL$3,$J73,0) | AM73: =-IF($E73=AM$3,$G73,0)+IF($H73=AM$3,$J73,0) | AN73: =-IF($E73=AN$3,$G73,0)+IF($H73=AN$3,$J73,0) | AO73: =-IF($E73=AO$3,$G73,0)+IF($H73=AO$3,$J73,0) | AP73: =IF($E73=AP$3,$G73,0)-IF($H73=AP$3,$J73,0) | AQ73: =IF($E73=AQ$3,$G73,0)-IF($H73=AQ$3,$J73,0) | AR73: =IF($E73=AR$3,$G73,0)-IF($H73=AR$3,$J73,0) | AS73: =IF($E73=AS$3,$G73,0)-IF($H73=AS$3,$J73,0) | AT73: =IF($E73=AT$3,$G73,0)-IF($H73=AT$3,$J73,0) | AU73: =IF($E73=AU$3,$G73,0)-IF($H73=AU$3,$J73,0) | AV73: =IF($E73=AV$3,$G73,0)-IF($H73=AV$3,$J73,0) | AW73: =IF($E73=AW$3,$G73,0)-IF($H73=AW$3,$J73,0) | ... BK73: =IF($E73=BK$3,$G73,0)-IF($H73=BK$3,$J73,0) | BL73: =-IF($E73=BL$3,$G73,0)+IF($H73=BL$3,$J73,0) | BM73: =-IF($E73=BM$3,$G73,0)+IF($H73=BM$3,$J73,0) | BN73: =-IF($E73=BN$3,$G73,0)+IF($H73=BN$3,$J73,0) | BO73: =-IF($E73=BO$3,$G73,0)+IF($H73=BO$3,$J73,0) | BP73: =-IF($E73=BP$3,$G73,0)+IF($H73=BP$3,$J73,0) | BQ73: =-IF($E73=BQ$3,$G73,0)+IF($H73=BQ$3,$J73,0) | BR73: =-IF($E73=BR$3,$G73,0)+IF($H73=BR$3,$J73,0) | BS73: =-IF($E73=BS$3,$G73,0)+IF($H73=BS$3,$J73,0) | BT73: =-IF($E73=BT$3,$G73,0)+IF($H73=BT$3,$J73,0) | BU73: =+G73-J73 | BV73: =-IF($E73=BV$3,$G73,0)+IF($H73=BV$3,$J73,0)
B74: 3 | C74: 2 | D74: トラスコ中山(TRUSCO) オリコン 薄型軽量折りたたみコンテナ 透明 50L 超軽量 | E74: 514 | F74: =IF(E74="","",IF(ISNA(VLOOKUP(E74,科目コード表!$C$4:$D$67,2,FALSE)),"該当科目なし",VLOOKUP(E74,科目コード表!$C$4:$D$67,2,FALSE))) | G74: 960 | I74: =IF(H74="","",IF(ISNA(VLOOKUP(H74,科目コード表!$C$4:$D$67,2,FALSE)),"該当科目なし",VLOOKUP(H74,科目コード表!$C$4:$D$67,2,FALSE))) | L74: =IF($E74=L$3,$G74,0)-IF($H74=L$3,$J74,0) | M74: =IF($E74=M$3,$G74,0)-IF($H74=M$3,$J74,0) | N74: =IF($E74=N$3,$G74,0)-IF($H74=N$3,$J74,0) | O74: =IF($E74=O$3,$G74,0)-IF($H74=O$3,$J74,0) | P74: =IF($E74=P$3,$G74,0)-IF($H74=P$3,$J74,0) | Q74: =IF($E74=Q$3,$G74,0)-IF($H74=Q$3,$J74,0) | R74: =IF($E74=R$3,$G74,0)-IF($H74=R$3,$J74,0) | S74: =IF($E74=S$3,$G74,0)-IF($H74=S$3,$J74,0) | ... AL74: =IF($E74=AL$3,$G74,0)-IF($H74=AL$3,$J74,0) | AM74: =-IF($E74=AM$3,$G74,0)+IF($H74=AM$3,$J74,0) | AN74: =-IF($E74=AN$3,$G74,0)+IF($H74=AN$3,$J74,0) | AO74: =-IF($E74=AO$3,$G74,0)+IF($H74=AO$3,$J74,0) | AP74: =IF($E74=AP$3,$G74,0)-IF($H74=AP$3,$J74,0) | AQ74: =IF($E74=AQ$3,$G74,0)-IF($H74=AQ$3,$J74,0) | AR74: =IF($E74=AR$3,$G74,0)-IF($H74=AR$3,$J74,0) | AS74: =IF($E74=AS$3,$G74,0)-IF($H74=AS$3,$J74,0) | AT74: =IF($E74=AT$3,$G74,0)-IF($H74=AT$3,$J74,0) | AU74: =IF($E74=AU$3,$G74,0)-IF($H74=AU$3,$J74,0) | AV74: =IF($E74=AV$3,$G74,0)-IF($H74=AV$3,$J74,0) | AW74: =IF($E74=AW$3,$G74,0)-IF($H74=AW$3,$J74,0) | ... BK74: =IF($E74=BK$3,$G74,0)-IF($H74=BK$3,$J74,0) | BL74: =-IF($E74=BL$3,$G74,0)+IF($H74=BL$3,$J74,0) | BM74: =-IF($E74=BM$3,$G74,0)+IF($H74=BM$3,$J74,0) | BN74: =-IF($E74=BN$3,$G74,0)+IF($H74=BN$3,$J74,0) | BO74: =-IF($E74=BO$3,$G74,0)+IF($H74=BO$3,$J74,0) | BP74: =-IF($E74=BP$3,$G74,0)+IF($H74=BP$3,$J74,0) | BQ74: =-IF($E74=BQ$3,$G74,0)+IF($H74=BQ$3,$J74,0) | BR74: =-IF($E74=BR$3,$G74,0)+IF($H74=BR$3,$J74,0) | BS74: =-IF($E74=BS$3,$G74,0)+IF($H74=BS$3,$J74,0) | BT74: =-IF($E74=BT$3,$G74,0)+IF($H74=BT$3,$J74,0) | BU74: =+G74-J74 | BV74: =-IF($E74=BV$3,$G74,0)+IF($H74=BV$3,$J74,0)
B75: 3 | C75: 5 | D75: 2月分 電気料金 | E75: 507 | F75: =IF(E75="","",IF(ISNA(VLOOKUP(E75,科目コード表!$C$4:$D$67,2,FALSE)),"該当科目なし",VLOOKUP(E75,科目コード表!$C$4:$D$67,2,FALSE))) | G75: 10343 | I75: =IF(H75="","",IF(ISNA(VLOOKUP(H75,科目コード表!$C$4:$D$67,2,FALSE)),"該当科目なし",VLOOKUP(H75,科目コード表!$C$4:$D$67,2,FALSE))) | L75: =IF($E75=L$3,$G75,0)-IF($H75=L$3,$J75,0) | M75: =IF($E75=M$3,$G75,0)-IF($H75=M$3,$J75,0) | N75: =IF($E75=N$3,$G75,0)-IF($H75=N$3,$J75,0) | O75: =IF($E75=O$3,$G75,0)-IF($H75=O$3,$J75,0) | P75: =IF($E75=P$3,$G75,0)-IF($H75=P$3,$J75,0) | Q75: =IF($E75=Q$3,$G75,0)-IF($H75=Q$3,$J75,0) | R75: =IF($E75=R$3,$G75,0)-IF($H75=R$3,$J75,0) | S75: =IF($E75=S$3,$G75,0)-IF($H75=S$3,$J75,0) | ... AL75: =IF($E75=AL$3,$G75,0)-IF($H75=AL$3,$J75,0) | AM75: =-IF($E75=AM$3,$G75,0)+IF($H75=AM$3,$J75,0) | AN75: =-IF($E75=AN$3,$G75,0)+IF($H75=AN$3,$J75,0) | AO75: =-IF($E75=AO$3,$G75,0)+IF($H75=AO$3,$J75,0) | AP75: =IF($E75=AP$3,$G75,0)-IF($H75=AP$3,$J75,0) | AQ75: =IF($E75=AQ$3,$G75,0)-IF($H75=AQ$3,$J75,0) | AR75: =IF($E75=AR$3,$G75,0)-IF($H75=AR$3,$J75,0) | AS75: =IF($E75=AS$3,$G75,0)-IF($H75=AS$3,$J75,0) | AT75: =IF($E75=AT$3,$G75,0)-IF($H75=AT$3,$J75,0) | AU75: =IF($E75=AU$3,$G75,0)-IF($H75=AU$3,$J75,0) | AV75: =IF($E75=AV$3,$G75,0)-IF($H75=AV$3,$J75,0) | AW75: =IF($E75=AW$3,$G75,0)-IF($H75=AW$3,$J75,0) | ... BK75: =IF($E75=BK$3,$G75,0)-IF($H75=BK$3,$J75,0) | BL75: =-IF($E75=BL$3,$G75,0)+IF($H75=BL$3,$J75,0) | BM75: =-IF($E75=BM$3,$G75,0)+IF($H75=BM$3,$J75,0) | BN75: =-IF($E75=BN$3,$G75,0)+IF($H75=BN$3,$J75,0) | BO75: =-IF($E75=BO$3,$G75,0)+IF($H75=BO$3,$J75,0) | BP75: =-IF($E75=BP$3,$G75,0)+IF($H75=BP$3,$J75,0) | BQ75: =-IF($E75=BQ$3,$G75,0)+IF($H75=BQ$3,$J75,0) | BR75: =-IF($E75=BR$3,$G75,0)+IF($H75=BR$3,$J75,0) | BS75: =-IF($E75=BS$3,$G75,0)+IF($H75=BS$3,$J75,0) | BT75: =-IF($E75=BT$3,$G75,0)+IF($H75=BT$3,$J75,0) | BU75: =+G75-J75 | BV75: =-IF($E75=BV$3,$G75,0)+IF($H75=BV$3,$J75,0)
B76: 3 | C76: 6 | D76: やよいの青色申告 26 通常版＜令和7年分確定申告対応＞ | E76: 514 | F76: =IF(E76="","",IF(ISNA(VLOOKUP(E76,科目コード表!$C$4:$D$67,2,FALSE)),"該当科目なし",VLOOKUP(E76,科目コード表!$C$4:$D$67,2,FALSE))) | G76: 13409 | I76: =IF(H76="","",IF(ISNA(VLOOKUP(H76,科目コード表!$C$4:$D$67,2,FALSE)),"該当科目なし",VLOOKUP(H76,科目コード表!$C$4:$D$67,2,FALSE))) | L76: =IF($E76=L$3,$G76,0)-IF($H76=L$3,$J76,0) | M76: =IF($E76=M$3,$G76,0)-IF($H76=M$3,$J76,0) | N76: =IF($E76=N$3,$G76,0)-IF($H76=N$3,$J76,0) | O76: =IF($E76=O$3,$G76,0)-IF($H76=O$3,$J76,0) | P76: =IF($E76=P$3,$G76,0)-IF($H76=P$3,$J76,0) | Q76: =IF($E76=Q$3,$G76,0)-IF($H76=Q$3,$J76,0) | R76: =IF($E76=R$3,$G76,0)-IF($H76=R$3,$J76,0) | S76: =IF($E76=S$3,$G76,0)-IF($H76=S$3,$J76,0) | ... AL76: =IF($E76=AL$3,$G76,0)-IF($H76=AL$3,$J76,0) | AM76: =-IF($E76=AM$3,$G76,0)+IF($H76=AM$3,$J76,0) | AN76: =-IF($E76=AN$3,$G76,0)+IF($H76=AN$3,$J76,0) | AO76: =-IF($E76=AO$3,$G76,0)+IF($H76=AO$3,$J76,0) | AP76: =IF($E76=AP$3,$G76,0)-IF($H76=AP$3,$J76,0) | AQ76: =IF($E76=AQ$3,$G76,0)-IF($H76=AQ$3,$J76,0) | AR76: =IF($E76=AR$3,$G76,0)-IF($H76=AR$3,$J76,0) | AS76: =IF($E76=AS$3,$G76,0)-IF($H76=AS$3,$J76,0) | AT76: =IF($E76=AT$3,$G76,0)-IF($H76=AT$3,$J76,0) | AU76: =IF($E76=AU$3,$G76,0)-IF($H76=AU$3,$J76,0) | AV76: =IF($E76=AV$3,$G76,0)-IF($H76=AV$3,$J76,0) | AW76: =IF($E76=AW$3,$G76,0)-IF($H76=AW$3,$J76,0) | ... BK76: =IF($E76=BK$3,$G76,0)-IF($H76=BK$3,$J76,0) | BL76: =-IF($E76=BL$3,$G76,0)+IF($H76=BL$3,$J76,0) | BM76: =-IF($E76=BM$3,$G76,0)+IF($H76=BM$3,$J76,0) | BN76: =-IF($E76=BN$3,$G76,0)+IF($H76=BN$3,$J76,0) | BO76: =-IF($E76=BO$3,$G76,0)+IF($H76=BO$3,$J76,0) | BP76: =-IF($E76=BP$3,$G76,0)+IF($H76=BP$3,$J76,0) | BQ76: =-IF($E76=BQ$3,$G76,0)+IF($H76=BQ$3,$J76,0) | BR76: =-IF($E76=BR$3,$G76,0)+IF($H76=BR$3,$J76,0) | BS76: =-IF($E76=BS$3,$G76,0)+IF($H76=BS$3,$J76,0) | BT76: =-IF($E76=BT$3,$G76,0)+IF($H76=BT$3,$J76,0) | BU76: =+G76-J76 | BV76: =-IF($E76=BV$3,$G76,0)+IF($H76=BV$3,$J76,0)
B77: 3 | C77: 6 | D77: Cartist 新型シエンタ 10系 に適用 MXP フロアマット 5人乗り用 3Dフロアマット カーマット セカンドマット SIENTA MXPL10G/15G MXPC10G 2022年8月～現行 防水マット 滑り防止 耐汚れ TPE素材 立体カーマット 車種専用設計 取付簡単 カスタムパーツ アクセサリー カー用品 4PCSセット | E77: 523 | F77: =IF(E77="","",IF(ISNA(VLOOKUP(E77,科目コード表!$C$4:$D$67,2,FALSE)),"該当科目なし",VLOOKUP(E77,科目コード表!$C$4:$D$67,2,FALSE))) | G77: 8060 | I77: =IF(H77="","",IF(ISNA(VLOOKUP(H77,科目コード表!$C$4:$D$67,2,FALSE)),"該当科目なし",VLOOKUP(H77,科目コード表!$C$4:$D$67,2,FALSE))) | L77: =IF($E77=L$3,$G77,0)-IF($H77=L$3,$J77,0) | M77: =IF($E77=M$3,$G77,0)-IF($H77=M$3,$J77,0) | N77: =IF($E77=N$3,$G77,0)-IF($H77=N$3,$J77,0) | O77: =IF($E77=O$3,$G77,0)-IF($H77=O$3,$J77,0) | P77: =IF($E77=P$3,$G77,0)-IF($H77=P$3,$J77,0) | Q77: =IF($E77=Q$3,$G77,0)-IF($H77=Q$3,$J77,0) | R77: =IF($E77=R$3,$G77,0)-IF($H77=R$3,$J77,0) | S77: =IF($E77=S$3,$G77,0)-IF($H77=S$3,$J77,0) | ... AL77: =IF($E77=AL$3,$G77,0)-IF($H77=AL$3,$J77,0) | AM77: =-IF($E77=AM$3,$G77,0)+IF($H77=AM$3,$J77,0) | AN77: =-IF($E77=AN$3,$G77,0)+IF($H77=AN$3,$J77,0) | AO77: =-IF($E77=AO$3,$G77,0)+IF($H77=AO$3,$J77,0) | AP77: =IF($E77=AP$3,$G77,0)-IF($H77=AP$3,$J77,0) | AQ77: =IF($E77=AQ$3,$G77,0)-IF($H77=AQ$3,$J77,0) | AR77: =IF($E77=AR$3,$G77,0)-IF($H77=AR$3,$J77,0) | AS77: =IF($E77=AS$3,$G77,0)-IF($H77=AS$3,$J77,0) | AT77: =IF($E77=AT$3,$G77,0)-IF($H77=AT$3,$J77,0) | AU77: =IF($E77=AU$3,$G77,0)-IF($H77=AU$3,$J77,0) | AV77: =IF($E77=AV$3,$G77,0)-IF($H77=AV$3,$J77,0) | AW77: =IF($E77=AW$3,$G77,0)-IF($H77=AW$3,$J77,0) | ... BK77: =IF($E77=BK$3,$G77,0)-IF($H77=BK$3,$J77,0) | BL77: =-IF($E77=BL$3,$G77,0)+IF($H77=BL$3,$J77,0) | BM77: =-IF($E77=BM$3,$G77,0)+IF($H77=BM$3,$J77,0) | BN77: =-IF($E77=BN$3,$G77,0)+IF($H77=BN$3,$J77,0) | BO77: =-IF($E77=BO$3,$G77,0)+IF($H77=BO$3,$J77,0) | BP77: =-IF($E77=BP$3,$G77,0)+IF($H77=BP$3,$J77,0) | BQ77: =-IF($E77=BQ$3,$G77,0)+IF($H77=BQ$3,$J77,0) | BR77: =-IF($E77=BR$3,$G77,0)+IF($H77=BR$3,$J77,0) | BS77: =-IF($E77=BS$3,$G77,0)+IF($H77=BS$3,$J77,0) | BT77: =-IF($E77=BT$3,$G77,0)+IF($H77=BT$3,$J77,0) | BU77: =+G77-J77 | BV77: =-IF($E77=BV$3,$G77,0)+IF($H77=BV$3,$J77,0)
B78: 3 | C78: 8 | D78: ガソリン代 | E78: 523 | F78: =IF(E78="","",IF(ISNA(VLOOKUP(E78,科目コード表!$C$4:$D$67,2,FALSE)),"該当科目なし",VLOOKUP(E78,科目コード表!$C$4:$D$67,2,FALSE))) | G78: 2985 | I78: =IF(H78="","",IF(ISNA(VLOOKUP(H78,科目コード表!$C$4:$D$67,2,FALSE)),"該当科目なし",VLOOKUP(H78,科目コード表!$C$4:$D$67,2,FALSE))) | L78: =IF($E78=L$3,$G78,0)-IF($H78=L$3,$J78,0) | M78: =IF($E78=M$3,$G78,0)-IF($H78=M$3,$J78,0) | N78: =IF($E78=N$3,$G78,0)-IF($H78=N$3,$J78,0) | O78: =IF($E78=O$3,$G78,0)-IF($H78=O$3,$J78,0) | P78: =IF($E78=P$3,$G78,0)-IF($H78=P$3,$J78,0) | Q78: =IF($E78=Q$3,$G78,0)-IF($H78=Q$3,$J78,0) | R78: =IF($E78=R$3,$G78,0)-IF($H78=R$3,$J78,0) | S78: =IF($E78=S$3,$G78,0)-IF($H78=S$3,$J78,0) | ... AL78: =IF($E78=AL$3,$G78,0)-IF($H78=AL$3,$J78,0) | AM78: =-IF($E78=AM$3,$G78,0)+IF($H78=AM$3,$J78,0) | AN78: =-IF($E78=AN$3,$G78,0)+IF($H78=AN$3,$J78,0) | AO78: =-IF($E78=AO$3,$G78,0)+IF($H78=AO$3,$J78,0) | AP78: =IF($E78=AP$3,$G78,0)-IF($H78=AP$3,$J78,0) | AQ78: =IF($E78=AQ$3,$G78,0)-IF($H78=AQ$3,$J78,0) | AR78: =IF($E78=AR$3,$G78,0)-IF($H78=AR$3,$J78,0) | AS78: =IF($E78=AS$3,$G78,0)-IF($H78=AS$3,$J78,0) | AT78: =IF($E78=AT$3,$G78,0)-IF($H78=AT$3,$J78,0) | AU78: =IF($E78=AU$3,$G78,0)-IF($H78=AU$3,$J78,0) | AV78: =IF($E78=AV$3,$G78,0)-IF($H78=AV$3,$J78,0) | AW78: =IF($E78=AW$3,$G78,0)-IF($H78=AW$3,$J78,0) | ... BK78: =IF($E78=BK$3,$G78,0)-IF($H78=BK$3,$J78,0) | BL78: =-IF($E78=BL$3,$G78,0)+IF($H78=BL$3,$J78,0) | BM78: =-IF($E78=BM$3,$G78,0)+IF($H78=BM$3,$J78,0) | BN78: =-IF($E78=BN$3,$G78,0)+IF($H78=BN$3,$J78,0) | BO78: =-IF($E78=BO$3,$G78,0)+IF($H78=BO$3,$J78,0) | BP78: =-IF($E78=BP$3,$G78,0)+IF($H78=BP$3,$J78,0) | BQ78: =-IF($E78=BQ$3,$G78,0)+IF($H78=BQ$3,$J78,0) | BR78: =-IF($E78=BR$3,$G78,0)+IF($H78=BR$3,$J78,0) | BS78: =-IF($E78=BS$3,$G78,0)+IF($H78=BS$3,$J78,0) | BT78: =-IF($E78=BT$3,$G78,0)+IF($H78=BT$3,$J78,0) | BU78: =+G78-J78 | BV78: =-IF($E78=BV$3,$G78,0)+IF($H78=BV$3,$J78,0)
B79: 3 | C79: 8 | D79: 洗車 | E79: 523 | F79: =IF(E79="","",IF(ISNA(VLOOKUP(E79,科目コード表!$C$4:$D$67,2,FALSE)),"該当科目なし",VLOOKUP(E79,科目コード表!$C$4:$D$67,2,FALSE))) | G79: 600 | I79: =IF(H79="","",IF(ISNA(VLOOKUP(H79,科目コード表!$C$4:$D$67,2,FALSE)),"該当科目なし",VLOOKUP(H79,科目コード表!$C$4:$D$67,2,FALSE))) | L79: =IF($E79=L$3,$G79,0)-IF($H79=L$3,$J79,0) | M79: =IF($E79=M$3,$G79,0)-IF($H79=M$3,$J79,0) | N79: =IF($E79=N$3,$G79,0)-IF($H79=N$3,$J79,0) | O79: =IF($E79=O$3,$G79,0)-IF($H79=O$3,$J79,0) | P79: =IF($E79=P$3,$G79,0)-IF($H79=P$3,$J79,0) | Q79: =IF($E79=Q$3,$G79,0)-IF($H79=Q$3,$J79,0) | R79: =IF($E79=R$3,$G79,0)-IF($H79=R$3,$J79,0) | S79: =IF($E79=S$3,$G79,0)-IF($H79=S$3,$J79,0) | ... AL79: =IF($E79=AL$3,$G79,0)-IF($H79=AL$3,$J79,0) | AM79: =-IF($E79=AM$3,$G79,0)+IF($H79=AM$3,$J79,0) | AN79: =-IF($E79=AN$3,$G79,0)+IF($H79=AN$3,$J79,0) | AO79: =-IF($E79=AO$3,$G79,0)+IF($H79=AO$3,$J79,0) | AP79: =IF($E79=AP$3,$G79,0)-IF($H79=AP$3,$J79,0) | AQ79: =IF($E79=AQ$3,$G79,0)-IF($H79=AQ$3,$J79,0) | AR79: =IF($E79=AR$3,$G79,0)-IF($H79=AR$3,$J79,0) | AS79: =IF($E79=AS$3,$G79,0)-IF($H79=AS$3,$J79,0) | AT79: =IF($E79=AT$3,$G79,0)-IF($H79=AT$3,$J79,0) | AU79: =IF($E79=AU$3,$G79,0)-IF($H79=AU$3,$J79,0) | AV79: =IF($E79=AV$3,$G79,0)-IF($H79=AV$3,$J79,0) | AW79: =IF($E79=AW$3,$G79,0)-IF($H79=AW$3,$J79,0) | ... BK79: =IF($E79=BK$3,$G79,0)-IF($H79=BK$3,$J79,0) | BL79: =-IF($E79=BL$3,$G79,0)+IF($H79=BL$3,$J79,0) | BM79: =-IF($E79=BM$3,$G79,0)+IF($H79=BM$3,$J79,0) | BN79: =-IF($E79=BN$3,$G79,0)+IF($H79=BN$3,$J79,0) | BO79: =-IF($E79=BO$3,$G79,0)+IF($H79=BO$3,$J79,0) | BP79: =-IF($E79=BP$3,$G79,0)+IF($H79=BP$3,$J79,0) | BQ79: =-IF($E79=BQ$3,$G79,0)+IF($H79=BQ$3,$J79,0) | BR79: =-IF($E79=BR$3,$G79,0)+IF($H79=BR$3,$J79,0) | BS79: =-IF($E79=BS$3,$G79,0)+IF($H79=BS$3,$J79,0) | BT79: =-IF($E79=BT$3,$G79,0)+IF($H79=BT$3,$J79,0) | BU79: =+G79-J79 | BV79: =-IF($E79=BV$3,$G79,0)+IF($H79=BV$3,$J79,0)
B80: 3 | C80: 9 | D80: 書籍 超シンプルな青色申告、教えてもらいました! | E80: 524 | F80: =IF(E80="","",IF(ISNA(VLOOKUP(E80,科目コード表!$C$4:$D$67,2,FALSE)),"該当科目なし",VLOOKUP(E80,科目コード表!$C$4:$D$67,2,FALSE))) | G80: 1870 | I80: =IF(H80="","",IF(ISNA(VLOOKUP(H80,科目コード表!$C$4:$D$67,2,FALSE)),"該当科目なし",VLOOKUP(H80,科目コード表!$C$4:$D$67,2,FALSE))) | L80: =IF($E80=L$3,$G80,0)-IF($H80=L$3,$J80,0) | M80: =IF($E80=M$3,$G80,0)-IF($H80=M$3,$J80,0) | N80: =IF($E80=N$3,$G80,0)-IF($H80=N$3,$J80,0) | O80: =IF($E80=O$3,$G80,0)-IF($H80=O$3,$J80,0) | P80: =IF($E80=P$3,$G80,0)-IF($H80=P$3,$J80,0) | Q80: =IF($E80=Q$3,$G80,0)-IF($H80=Q$3,$J80,0) | R80: =IF($E80=R$3,$G80,0)-IF($H80=R$3,$J80,0) | S80: =IF($E80=S$3,$G80,0)-IF($H80=S$3,$J80,0) | ... AL80: =IF($E80=AL$3,$G80,0)-IF($H80=AL$3,$J80,0) | AM80: =-IF($E80=AM$3,$G80,0)+IF($H80=AM$3,$J80,0) | AN80: =-IF($E80=AN$3,$G80,0)+IF($H80=AN$3,$J80,0) | AO80: =-IF($E80=AO$3,$G80,0)+IF($H80=AO$3,$J80,0) | AP80: =IF($E80=AP$3,$G80,0)-IF($H80=AP$3,$J80,0) | AQ80: =IF($E80=AQ$3,$G80,0)-IF($H80=AQ$3,$J80,0) | AR80: =IF($E80=AR$3,$G80,0)-IF($H80=AR$3,$J80,0) | AS80: =IF($E80=AS$3,$G80,0)-IF($H80=AS$3,$J80,0) | AT80: =IF($E80=AT$3,$G80,0)-IF($H80=AT$3,$J80,0) | AU80: =IF($E80=AU$3,$G80,0)-IF($H80=AU$3,$J80,0) | AV80: =IF($E80=AV$3,$G80,0)-IF($H80=AV$3,$J80,0) | AW80: =IF($E80=AW$3,$G80,0)-IF($H80=AW$3,$J80,0) | ... BK80: =IF($E80=BK$3,$G80,0)-IF($H80=BK$3,$J80,0) | BL80: =-IF($E80=BL$3,$G80,0)+IF($H80=BL$3,$J80,0) | BM80: =-IF($E80=BM$3,$G80,0)+IF($H80=BM$3,$J80,0) | BN80: =-IF($E80=BN$3,$G80,0)+IF($H80=BN$3,$J80,0) | BO80: =-IF($E80=BO$3,$G80,0)+IF($H80=BO$3,$J80,0) | BP80: =-IF($E80=BP$3,$G80,0)+IF($H80=BP$3,$J80,0) | BQ80: =-IF($E80=BQ$3,$G80,0)+IF($H80=BQ$3,$J80,0) | BR80: =-IF($E80=BR$3,$G80,0)+IF($H80=BR$3,$J80,0) | BS80: =-IF($E80=BS$3,$G80,0)+IF($H80=BS$3,$J80,0) | BT80: =-IF($E80=BT$3,$G80,0)+IF($H80=BT$3,$J80,0) | BU80: =+G80-J80 | BV80: =-IF($E80=BV$3,$G80,0)+IF($H80=BV$3,$J80,0)
B81: 3 | C81: 9 | D81: Kindle超シンプルな青色申告、教えてもらいました！ | E81: 524 | F81: =IF(E81="","",IF(ISNA(VLOOKUP(E81,科目コード表!$C$4:$D$67,2,FALSE)),"該当科目なし",VLOOKUP(E81,科目コード表!$C$4:$D$67,2,FALSE))) | G81: 1515 | I81: =IF(H81="","",IF(ISNA(VLOOKUP(H81,科目コード表!$C$4:$D$67,2,FALSE)),"該当科目なし",VLOOKUP(H81,科目コード表!$C$4:$D$67,2,FALSE))) | L81: =IF($E81=L$3,$G81,0)-IF($H81=L$3,$J81,0) | M81: =IF($E81=M$3,$G81,0)-IF($H81=M$3,$J81,0) | N81: =IF($E81=N$3,$G81,0)-IF($H81=N$3,$J81,0) | O81: =IF($E81=O$3,$G81,0)-IF($H81=O$3,$J81,0) | P81: =IF($E81=P$3,$G81,0)-IF($H81=P$3,$J81,0) | Q81: =IF($E81=Q$3,$G81,0)-IF($H81=Q$3,$J81,0) | R81: =IF($E81=R$3,$G81,0)-IF($H81=R$3,$J81,0) | S81: =IF($E81=S$3,$G81,0)-IF($H81=S$3,$J81,0) | ... AL81: =IF($E81=AL$3,$G81,0)-IF($H81=AL$3,$J81,0) | AM81: =-IF($E81=AM$3,$G81,0)+IF($H81=AM$3,$J81,0) | AN81: =-IF($E81=AN$3,$G81,0)+IF($H81=AN$3,$J81,0) | AO81: =-IF($E81=AO$3,$G81,0)+IF($H81=AO$3,$J81,0) | AP81: =IF($E81=AP$3,$G81,0)-IF($H81=AP$3,$J81,0) | AQ81: =IF($E81=AQ$3,$G81,0)-IF($H81=AQ$3,$J81,0) | AR81: =IF($E81=AR$3,$G81,0)-IF($H81=AR$3,$J81,0) | AS81: =IF($E81=AS$3,$G81,0)-IF($H81=AS$3,$J81,0) | AT81: =IF($E81=AT$3,$G81,0)-IF($H81=AT$3,$J81,0) | AU81: =IF($E81=AU$3,$G81,0)-IF($H81=AU$3,$J81,0) | AV81: =IF($E81=AV$3,$G81,0)-IF($H81=AV$3,$J81,0) | AW81: =IF($E81=AW$3,$G81,0)-IF($H81=AW$3,$J81,0) | ... BK81: =IF($E81=BK$3,$G81,0)-IF($H81=BK$3,$J81,0) | BL81: =-IF($E81=BL$3,$G81,0)+IF($H81=BL$3,$J81,0) | BM81: =-IF($E81=BM$3,$G81,0)+IF($H81=BM$3,$J81,0) | BN81: =-IF($E81=BN$3,$G81,0)+IF($H81=BN$3,$J81,0) | BO81: =-IF($E81=BO$3,$G81,0)+IF($H81=BO$3,$J81,0) | BP81: =-IF($E81=BP$3,$G81,0)+IF($H81=BP$3,$J81,0) | BQ81: =-IF($E81=BQ$3,$G81,0)+IF($H81=BQ$3,$J81,0) | BR81: =-IF($E81=BR$3,$G81,0)+IF($H81=BR$3,$J81,0) | BS81: =-IF($E81=BS$3,$G81,0)+IF($H81=BS$3,$J81,0) | BT81: =-IF($E81=BT$3,$G81,0)+IF($H81=BT$3,$J81,0) | BU81: =+G81-J81 | BV81: =-IF($E81=BV$3,$G81,0)+IF($H81=BV$3,$J81,0)
B82: 3 | C82: 10 | D82: ChatGPTで身につけるGoogle Apps Script | E82: 524 | F82: =IF(E82="","",IF(ISNA(VLOOKUP(E82,科目コード表!$C$4:$D$67,2,FALSE)),"該当科目なし",VLOOKUP(E82,科目コード表!$C$4:$D$67,2,FALSE))) | G82: 2772 | I82: =IF(H82="","",IF(ISNA(VLOOKUP(H82,科目コード表!$C$4:$D$67,2,FALSE)),"該当科目なし",VLOOKUP(H82,科目コード表!$C$4:$D$67,2,FALSE))) | L82: =IF($E82=L$3,$G82,0)-IF($H82=L$3,$J82,0) | M82: =IF($E82=M$3,$G82,0)-IF($H82=M$3,$J82,0) | N82: =IF($E82=N$3,$G82,0)-IF($H82=N$3,$J82,0) | O82: =IF($E82=O$3,$G82,0)-IF($H82=O$3,$J82,0) | P82: =IF($E82=P$3,$G82,0)-IF($H82=P$3,$J82,0) | Q82: =IF($E82=Q$3,$G82,0)-IF($H82=Q$3,$J82,0) | R82: =IF($E82=R$3,$G82,0)-IF($H82=R$3,$J82,0) | S82: =IF($E82=S$3,$G82,0)-IF($H82=S$3,$J82,0) | ... AL82: =IF($E82=AL$3,$G82,0)-IF($H82=AL$3,$J82,0) | AM82: =-IF($E82=AM$3,$G82,0)+IF($H82=AM$3,$J82,0) | AN82: =-IF($E82=AN$3,$G82,0)+IF($H82=AN$3,$J82,0) | AO82: =-IF($E82=AO$3,$G82,0)+IF($H82=AO$3,$J82,0) | AP82: =IF($E82=AP$3,$G82,0)-IF($H82=AP$3,$J82,0) | AQ82: =IF($E82=AQ$3,$G82,0)-IF($H82=AQ$3,$J82,0) | AR82: =IF($E82=AR$3,$G82,0)-IF($H82=AR$3,$J82,0) | AS82: =IF($E82=AS$3,$G82,0)-IF($H82=AS$3,$J82,0) | AT82: =IF($E82=AT$3,$G82,0)-IF($H82=AT$3,$J82,0) | AU82: =IF($E82=AU$3,$G82,0)-IF($H82=AU$3,$J82,0) | AV82: =IF($E82=AV$3,$G82,0)-IF($H82=AV$3,$J82,0) | AW82: =IF($E82=AW$3,$G82,0)-IF($H82=AW$3,$J82,0) | ... BK82: =IF($E82=BK$3,$G82,0)-IF($H82=BK$3,$J82,0) | BL82: =-IF($E82=BL$3,$G82,0)+IF($H82=BL$3,$J82,0) | BM82: =-IF($E82=BM$3,$G82,0)+IF($H82=BM$3,$J82,0) | BN82: =-IF($E82=BN$3,$G82,0)+IF($H82=BN$3,$J82,0) | BO82: =-IF($E82=BO$3,$G82,0)+IF($H82=BO$3,$J82,0) | BP82: =-IF($E82=BP$3,$G82,0)+IF($H82=BP$3,$J82,0) | BQ82: =-IF($E82=BQ$3,$G82,0)+IF($H82=BQ$3,$J82,0) | BR82: =-IF($E82=BR$3,$G82,0)+IF($H82=BR$3,$J82,0) | BS82: =-IF($E82=BS$3,$G82,0)+IF($H82=BS$3,$J82,0) | BT82: =-IF($E82=BT$3,$G82,0)+IF($H82=BT$3,$J82,0) | BU82: =+G82-J82 | BV82: =-IF($E82=BV$3,$G82,0)+IF($H82=BV$3,$J82,0)
B83: 3 | C83: 10 | D83: できる 仕事がはかどるGoogle Apps Script自動処理 全部入り。 | E83: 524 | F83: =IF(E83="","",IF(ISNA(VLOOKUP(E83,科目コード表!$C$4:$D$67,2,FALSE)),"該当科目なし",VLOOKUP(E83,科目コード表!$C$4:$D$67,2,FALSE))) | G83: 1105 | I83: =IF(H83="","",IF(ISNA(VLOOKUP(H83,科目コード表!$C$4:$D$67,2,FALSE)),"該当科目なし",VLOOKUP(H83,科目コード表!$C$4:$D$67,2,FALSE))) | L83: =IF($E83=L$3,$G83,0)-IF($H83=L$3,$J83,0) | M83: =IF($E83=M$3,$G83,0)-IF($H83=M$3,$J83,0) | N83: =IF($E83=N$3,$G83,0)-IF($H83=N$3,$J83,0) | O83: =IF($E83=O$3,$G83,0)-IF($H83=O$3,$J83,0) | P83: =IF($E83=P$3,$G83,0)-IF($H83=P$3,$J83,0) | Q83: =IF($E83=Q$3,$G83,0)-IF($H83=Q$3,$J83,0) | R83: =IF($E83=R$3,$G83,0)-IF($H83=R$3,$J83,0) | S83: =IF($E83=S$3,$G83,0)-IF($H83=S$3,$J83,0) | ... AL83: =IF($E83=AL$3,$G83,0)-IF($H83=AL$3,$J83,0) | AM83: =-IF($E83=AM$3,$G83,0)+IF($H83=AM$3,$J83,0) | AN83: =-IF($E83=AN$3,$G83,0)+IF($H83=AN$3,$J83,0) | AO83: =-IF($E83=AO$3,$G83,0)+IF($H83=AO$3,$J83,0) | AP83: =IF($E83=AP$3,$G83,0)-IF($H83=AP$3,$J83,0) | AQ83: =IF($E83=AQ$3,$G83,0)-IF($H83=AQ$3,$J83,0) | AR83: =IF($E83=AR$3,$G83,0)-IF($H83=AR$3,$J83,0) | AS83: =IF($E83=AS$3,$G83,0)-IF($H83=AS$3,$J83,0) | AT83: =IF($E83=AT$3,$G83,0)-IF($H83=AT$3,$J83,0) | AU83: =IF($E83=AU$3,$G83,0)-IF($H83=AU$3,$J83,0) | AV83: =IF($E83=AV$3,$G83,0)-IF($H83=AV$3,$J83,0) | AW83: =IF($E83=AW$3,$G83,0)-IF($H83=AW$3,$J83,0) | ... BK83: =IF($E83=BK$3,$G83,0)-IF($H83=BK$3,$J83,0) | BL83: =-IF($E83=BL$3,$G83,0)+IF($H83=BL$3,$J83,0) | BM83: =-IF($E83=BM$3,$G83,0)+IF($H83=BM$3,$J83,0) | BN83: =-IF($E83=BN$3,$G83,0)+IF($H83=BN$3,$J83,0) | BO83: =-IF($E83=BO$3,$G83,0)+IF($H83=BO$3,$J83,0) | BP83: =-IF($E83=BP$3,$G83,0)+IF($H83=BP$3,$J83,0) | BQ83: =-IF($E83=BQ$3,$G83,0)+IF($H83=BQ$3,$J83,0) | BR83: =-IF($E83=BR$3,$G83,0)+IF($H83=BR$3,$J83,0) | BS83: =-IF($E83=BS$3,$G83,0)+IF($H83=BS$3,$J83,0) | BT83: =-IF($E83=BT$3,$G83,0)+IF($H83=BT$3,$J83,0) | BU83: =+G83-J83 | BV83: =-IF($E83=BV$3,$G83,0)+IF($H83=BV$3,$J83,0)
... B85: 3 | C85: 10 | D85: ５年で１億貯める株式投資 | E85: 524 | F85: =IF(E85="","",IF(ISNA(VLOOKUP(E85,科目コード表!$C$4:$D$67,2,FALSE)),"該当科目なし",VLOOKUP(E85,科目コード表!$C$4:$D$67,2,FALSE))) | G85: 1870 | I85: =IF(H85="","",IF(ISNA(VLOOKUP(H85,科目コード表!$C$4:$D$67,2,FALSE)),"該当科目なし",VLOOKUP(H85,科目コード表!$C$4:$D$67,2,FALSE))) | L85: =IF($E85=L$3,$G85,0)-IF($H85=L$3,$J85,0) | M85: =IF($E85=M$3,$G85,0)-IF($H85=M$3,$J85,0) | N85: =IF($E85=N$3,$G85,0)-IF($H85=N$3,$J85,0) | O85: =IF($E85=O$3,$G85,0)-IF($H85=O$3,$J85,0) | P85: =IF($E85=P$3,$G85,0)-IF($H85=P$3,$J85,0) | Q85: =IF($E85=Q$3,$G85,0)-IF($H85=Q$3,$J85,0) | R85: =IF($E85=R$3,$G85,0)-IF($H85=R$3,$J85,0) | S85: =IF($E85=S$3,$G85,0)-IF($H85=S$3,$J85,0) | ... AL85: =IF($E85=AL$3,$G85,0)-IF($H85=AL$3,$J85,0) | AM85: =-IF($E85=AM$3,$G85,0)+IF($H85=AM$3,$J85,0) | AN85: =-IF($E85=AN$3,$G85,0)+IF($H85=AN$3,$J85,0) | AO85: =-IF($E85=AO$3,$G85,0)+IF($H85=AO$3,$J85,0) | AP85: =IF($E85=AP$3,$G85,0)-IF($H85=AP$3,$J85,0) | AQ85: =IF($E85=AQ$3,$G85,0)-IF($H85=AQ$3,$J85,0) | AR85: =IF($E85=AR$3,$G85,0)-IF($H85=AR$3,$J85,0) | AS85: =IF($E85=AS$3,$G85,0)-IF($H85=AS$3,$J85,0) | AT85: =IF($E85=AT$3,$G85,0)-IF($H85=AT$3,$J85,0) | AU85: =IF($E85=AU$3,$G85,0)-IF($H85=AU$3,$J85,0) | AV85: =IF($E85=AV$3,$G85,0)-IF($H85=AV$3,$J85,0) | AW85: =IF($E85=AW$3,$G85,0)-IF($H85=AW$3,$J85,0) | ... BK85: =IF($E85=BK$3,$G85,0)-IF($H85=BK$3,$J85,0) | BL85: =-IF($E85=BL$3,$G85,0)+IF($H85=BL$3,$J85,0) | BM85: =-IF($E85=BM$3,$G85,0)+IF($H85=BM$3,$J85,0) | BN85: =-IF($E85=BN$3,$G85,0)+IF($H85=BN$3,$J85,0) | BO85: =-IF($E85=BO$3,$G85,0)+IF($H85=BO$3,$J85,0) | BP85: =-IF($E85=BP$3,$G85,0)+IF($H85=BP$3,$J85,0) | BQ85: =-IF($E85=BQ$3,$G85,0)+IF($H85=BQ$3,$J85,0) | BR85: =-IF($E85=BR$3,$G85,0)+IF($H85=BR$3,$J85,0) | BS85: =-IF($E85=BS$3,$G85,0)+IF($H85=BS$3,$J85,0) | BT85: =-IF($E85=BT$3,$G85,0)+IF($H85=BT$3,$J85,0) | BU85: =+G85-J85 | BV85: =-IF($E85=BV$3,$G85,0)+IF($H85=BV$3,$J85,0)
F86: =IF(E86="","",IF(ISNA(VLOOKUP(E86,科目コード表!$C$4:$D$67,2,FALSE)),"該当科目なし",VLOOKUP(E86,科目コード表!$C$4:$D$67,2,FALSE))) | I86: =IF(H86="","",IF(ISNA(VLOOKUP(H86,科目コード表!$C$4:$D$67,2,FALSE)),"該当科目なし",VLOOKUP(H86,科目コード表!$C$4:$D$67,2,FALSE))) | L86: =IF($E86=L$3,$G86,0)-IF($H86=L$3,$J86,0) | M86: =IF($E86=M$3,$G86,0)-IF($H86=M$3,$J86,0) | N86: =IF($E86=N$3,$G86,0)-IF($H86=N$3,$J86,0) | O86: =IF($E86=O$3,$G86,0)-IF($H86=O$3,$J86,0) | P86: =IF($E86=P$3,$G86,0)-IF($H86=P$3,$J86,0) | Q86: =IF($E86=Q$3,$G86,0)-IF($H86=Q$3,$J86,0) | R86: =IF($E86=R$3,$G86,0)-IF($H86=R$3,$J86,0) | S86: =IF($E86=S$3,$G86,0)-IF($H86=S$3,$J86,0) | ... AL86: =IF($E86=AL$3,$G86,0)-IF($H86=AL$3,$J86,0) | AM86: =-IF($E86=AM$3,$G86,0)+IF($H86=AM$3,$J86,0) | AN86: =-IF($E86=AN$3,$G86,0)+IF($H86=AN$3,$J86,0) | AO86: =-IF($E86=AO$3,$G86,0)+IF($H86=AO$3,$J86,0) | AP86: =IF($E86=AP$3,$G86,0)-IF($H86=AP$3,$J86,0) | AQ86: =IF($E86=AQ$3,$G86,0)-IF($H86=AQ$3,$J86,0) | AR86: =IF($E86=AR$3,$G86,0)-IF($H86=AR$3,$J86,0) | AS86: =IF($E86=AS$3,$G86,0)-IF($H86=AS$3,$J86,0) | AT86: =IF($E86=AT$3,$G86,0)-IF($H86=AT$3,$J86,0) | AU86: =IF($E86=AU$3,$G86,0)-IF($H86=AU$3,$J86,0) | AV86: =IF($E86=AV$3,$G86,0)-IF($H86=AV$3,$J86,0) | AW86: =IF($E86=AW$3,$G86,0)-IF($H86=AW$3,$J86,0) | ... BK86: =IF($E86=BK$3,$G86,0)-IF($H86=BK$3,$J86,0) | BL86: =-IF($E86=BL$3,$G86,0)+IF($H86=BL$3,$J86,0) | BM86: =-IF($E86=BM$3,$G86,0)+IF($H86=BM$3,$J86,0) | BN86: =-IF($E86=BN$3,$G86,0)+IF($H86=BN$3,$J86,0) | BO86: =-IF($E86=BO$3,$G86,0)+IF($H86=BO$3,$J86,0) | BP86: =-IF($E86=BP$3,$G86,0)+IF($H86=BP$3,$J86,0) | BQ86: =-IF($E86=BQ$3,$G86,0)+IF($H86=BQ$3,$J86,0) | BR86: =-IF($E86=BR$3,$G86,0)+IF($H86=BR$3,$J86,0) | BS86: =-IF($E86=BS$3,$G86,0)+IF($H86=BS$3,$J86,0) | BT86: =-IF($E86=BT$3,$G86,0)+IF($H86=BT$3,$J86,0) | BU86: =+G86-J86 | BV86: =-IF($E86=BV$3,$G86,0)+IF($H86=BV$3,$J86,0)
F87: =IF(E87="","",IF(ISNA(VLOOKUP(E87,科目コード表!$C$4:$D$67,2,FALSE)),"該当科目なし",VLOOKUP(E87,科目コード表!$C$4:$D$67,2,FALSE))) | I87: =IF(H87="","",IF(ISNA(VLOOKUP(H87,科目コード表!$C$4:$D$67,2,FALSE)),"該当科目なし",VLOOKUP(H87,科目コード表!$C$4:$D$67,2,FALSE))) | L87: =IF($E87=L$3,$G87,0)-IF($H87=L$3,$J87,0) | M87: =IF($E87=M$3,$G87,0)-IF($H87=M$3,$J87,0) | N87: =IF($E87=N$3,$G87,0)-IF($H87=N$3,$J87,0) | O87: =IF($E87=O$3,$G87,0)-IF($H87=O$3,$J87,0) | P87: =IF($E87=P$3,$G87,0)-IF($H87=P$3,$J87,0) | Q87: =IF($E87=Q$3,$G87,0)-IF($H87=Q$3,$J87,0) | R87: =IF($E87=R$3,$G87,0)-IF($H87=R$3,$J87,0) | S87: =IF($E87=S$3,$G87,0)-IF($H87=S$3,$J87,0) | ... AL87: =IF($E87=AL$3,$G87,0)-IF($H87=AL$3,$J87,0) | AM87: =-IF($E87=AM$3,$G87,0)+IF($H87=AM$3,$J87,0) | AN87: =-IF($E87=AN$3,$G87,0)+IF($H87=AN$3,$J87,0) | AO87: =-IF($E87=AO$3,$G87,0)+IF($H87=AO$3,$J87,0) | AP87: =IF($E87=AP$3,$G87,0)-IF($H87=AP$3,$J87,0) | AQ87: =IF($E87=AQ$3,$G87,0)-IF($H87=AQ$3,$J87,0) | AR87: =IF($E87=AR$3,$G87,0)-IF($H87=AR$3,$J87,0) | AS87: =IF($E87=AS$3,$G87,0)-IF($H87=AS$3,$J87,0) | AT87: =IF($E87=AT$3,$G87,0)-IF($H87=AT$3,$J87,0) | AU87: =IF($E87=AU$3,$G87,0)-IF($H87=AU$3,$J87,0) | AV87: =IF($E87=AV$3,$G87,0)-IF($H87=AV$3,$J87,0) | AW87: =IF($E87=AW$3,$G87,0)-IF($H87=AW$3,$J87,0) | ... BK87: =IF($E87=BK$3,$G87,0)-IF($H87=BK$3,$J87,0) | BL87: =-IF($E87=BL$3,$G87,0)+IF($H87=BL$3,$J87,0) | BM87: =-IF($E87=BM$3,$G87,0)+IF($H87=BM$3,$J87,0) | BN87: =-IF($E87=BN$3,$G87,0)+IF($H87=BN$3,$J87,0) | BO87: =-IF($E87=BO$3,$G87,0)+IF($H87=BO$3,$J87,0) | BP87: =-IF($E87=BP$3,$G87,0)+IF($H87=BP$3,$J87,0) | BQ87: =-IF($E87=BQ$3,$G87,0)+IF($H87=BQ$3,$J87,0) | BR87: =-IF($E87=BR$3,$G87,0)+IF($H87=BR$3,$J87,0) | BS87: =-IF($E87=BS$3,$G87,0)+IF($H87=BS$3,$J87,0) | BT87: =-IF($E87=BT$3,$G87,0)+IF($H87=BT$3,$J87,0) | BU87: =+G87-J87 | BV87: =-IF($E87=BV$3,$G87,0)+IF($H87=BV$3,$J87,0)
F88: =IF(E88="","",IF(ISNA(VLOOKUP(E88,科目コード表!$C$4:$D$67,2,FALSE)),"該当科目なし",VLOOKUP(E88,科目コード表!$C$4:$D$67,2,FALSE))) | I88: =IF(H88="","",IF(ISNA(VLOOKUP(H88,科目コード表!$C$4:$D$67,2,FALSE)),"該当科目なし",VLOOKUP(H88,科目コード表!$C$4:$D$67,2,FALSE))) | L88: =IF($E88=L$3,$G88,0)-IF($H88=L$3,$J88,0) | M88: =IF($E88=M$3,$G88,0)-IF($H88=M$3,$J88,0) | N88: =IF($E88=N$3,$G88,0)-IF($H88=N$3,$J88,0) | O88: =IF($E88=O$3,$G88,0)-IF($H88=O$3,$J88,0) | P88: =IF($E88=P$3,$G88,0)-IF($H88=P$3,$J88,0) | Q88: =IF($E88=Q$3,$G88,0)-IF($H88=Q$3,$J88,0) | R88: =IF($E88=R$3,$G88,0)-IF($H88=R$3,$J88,0) | S88: =IF($E88=S$3,$G88,0)-IF($H88=S$3,$J88,0) | ... AL88: =IF($E88=AL$3,$G88,0)-IF($H88=AL$3,$J88,0) | AM88: =-IF($E88=AM$3,$G88,0)+IF($H88=AM$3,$J88,0) | AN88: =-IF($E88=AN$3,$G88,0)+IF($H88=AN$3,$J88,0) | AO88: =-IF($E88=AO$3,$G88,0)+IF($H88=AO$3,$J88,0) | AP88: =IF($E88=AP$3,$G88,0)-IF($H88=AP$3,$J88,0) | AQ88: =IF($E88=AQ$3,$G88,0)-IF($H88=AQ$3,$J88,0) | AR88: =IF($E88=AR$3,$G88,0)-IF($H88=AR$3,$J88,0) | AS88: =IF($E88=AS$3,$G88,0)-IF($H88=AS$3,$J88,0) | AT88: =IF($E88=AT$3,$G88,0)-IF($H88=AT$3,$J88,0) | AU88: =IF($E88=AU$3,$G88,0)-IF($H88=AU$3,$J88,0) | AV88: =IF($E88=AV$3,$G88,0)-IF($H88=AV$3,$J88,0) | AW88: =IF($E88=AW$3,$G88,0)-IF($H88=AW$3,$J88,0) | ... BK88: =IF($E88=BK$3,$G88,0)-IF($H88=BK$3,$J88,0) | BL88: =-IF($E88=BL$3,$G88,0)+IF($H88=BL$3,$J88,0) | BM88: =-IF($E88=BM$3,$G88,0)+IF($H88=BM$3,$J88,0) | BN88: =-IF($E88=BN$3,$G88,0)+IF($H88=BN$3,$J88,0) | BO88: =-IF($E88=BO$3,$G88,0)+IF($H88=BO$3,$J88,0) | BP88: =-IF($E88=BP$3,$G88,0)+IF($H88=BP$3,$J88,0) | BQ88: =-IF($E88=BQ$3,$G88,0)+IF($H88=BQ$3,$J88,0) | BR88: =-IF($E88=BR$3,$G88,0)+IF($H88=BR$3,$J88,0) | BS88: =-IF($E88=BS$3,$G88,0)+IF($H88=BS$3,$J88,0) | BT88: =-IF($E88=BT$3,$G88,0)+IF($H88=BT$3,$J88,0) | BU88: =+G88-J88 | BV88: =-IF($E88=BV$3,$G88,0)+IF($H88=BV$3,$J88,0)
F89: =IF(E89="","",IF(ISNA(VLOOKUP(E89,科目コード表!$C$4:$D$67,2,FALSE)),"該当科目なし",VLOOKUP(E89,科目コード表!$C$4:$D$67,2,FALSE))) | I89: =IF(H89="","",IF(ISNA(VLOOKUP(H89,科目コード表!$C$4:$D$67,2,FALSE)),"該当科目なし",VLOOKUP(H89,科目コード表!$C$4:$D$67,2,FALSE))) | L89: =IF($E89=L$3,$G89,0)-IF($H89=L$3,$J89,0) | M89: =IF($E89=M$3,$G89,0)-IF($H89=M$3,$J89,0) | N89: =IF($E89=N$3,$G89,0)-IF($H89=N$3,$J89,0) | O89: =IF($E89=O$3,$G89,0)-IF($H89=O$3,$J89,0) | P89: =IF($E89=P$3,$G89,0)-IF($H89=P$3,$J89,0) | Q89: =IF($E89=Q$3,$G89,0)-IF($H89=Q$3,$J89,0) | R89: =IF($E89=R$3,$G89,0)-IF($H89=R$3,$J89,0) | S89: =IF($E89=S$3,$G89,0)-IF($H89=S$3,$J89,0) | ... AL89: =IF($E89=AL$3,$G89,0)-IF($H89=AL$3,$J89,0) | AM89: =-IF($E89=AM$3,$G89,0)+IF($H89=AM$3,$J89,0) | AN89: =-IF($E89=AN$3,$G89,0)+IF($H89=AN$3,$J89,0) | AO89: =-IF($E89=AO$3,$G89,0)+IF($H89=AO$3,$J89,0) | AP89: =IF($E89=AP$3,$G89,0)-IF($H89=AP$3,$J89,0) | AQ89: =IF($E89=AQ$3,$G89,0)-IF($H89=AQ$3,$J89,0) | AR89: =IF($E89=AR$3,$G89,0)-IF($H89=AR$3,$J89,0) | AS89: =IF($E89=AS$3,$G89,0)-IF($H89=AS$3,$J89,0) | AT89: =IF($E89=AT$3,$G89,0)-IF($H89=AT$3,$J89,0) | AU89: =IF($E89=AU$3,$G89,0)-IF($H89=AU$3,$J89,0) | AV89: =IF($E89=AV$3,$G89,0)-IF($H89=AV$3,$J89,0) | AW89: =IF($E89=AW$3,$G89,0)-IF($H89=AW$3,$J89,0) | ... BK89: =IF($E89=BK$3,$G89,0)-IF($H89=BK$3,$J89,0) | BL89: =-IF($E89=BL$3,$G89,0)+IF($H89=BL$3,$J89,0) | BM89: =-IF($E89=BM$3,$G89,0)+IF($H89=BM$3,$J89,0) | BN89: =-IF($E89=BN$3,$G89,0)+IF($H89=BN$3,$J89,0) | BO89: =-IF($E89=BO$3,$G89,0)+IF($H89=BO$3,$J89,0) | BP89: =-IF($E89=BP$3,$G89,0)+IF($H89=BP$3,$J89,0) | BQ89: =-IF($E89=BQ$3,$G89,0)+IF($H89=BQ$3,$J89,0) | BR89: =-IF($E89=BR$3,$G89,0)+IF($H89=BR$3,$J89,0) | BS89: =-IF($E89=BS$3,$G89,0)+IF($H89=BS$3,$J89,0) | BT89: =-IF($E89=BT$3,$G89,0)+IF($H89=BT$3,$J89,0) | BU89: =+G89-J89 | BV89: =-IF($E89=BV$3,$G89,0)+IF($H89=BV$3,$J89,0)
F90: =IF(E90="","",IF(ISNA(VLOOKUP(E90,科目コード表!$C$4:$D$67,2,FALSE)),"該当科目なし",VLOOKUP(E90,科目コード表!$C$4:$D$67,2,FALSE))) | I90: =IF(H90="","",IF(ISNA(VLOOKUP(H90,科目コード表!$C$4:$D$67,2,FALSE)),"該当科目なし",VLOOKUP(H90,科目コード表!$C$4:$D$67,2,FALSE))) | L90: =IF($E90=L$3,$G90,0)-IF($H90=L$3,$J90,0) | M90: =IF($E90=M$3,$G90,0)-IF($H90=M$3,$J90,0) | N90: =IF($E90=N$3,$G90,0)-IF($H90=N$3,$J90,0) | O90: =IF($E90=O$3,$G90,0)-IF($H90=O$3,$J90,0) | P90: =IF($E90=P$3,$G90,0)-IF($H90=P$3,$J90,0) | Q90: =IF($E90=Q$3,$G90,0)-IF($H90=Q$3,$J90,0) | R90: =IF($E90=R$3,$G90,0)-IF($H90=R$3,$J90,0) | S90: =IF($E90=S$3,$G90,0)-IF($H90=S$3,$J90,0) | ... AL90: =IF($E90=AL$3,$G90,0)-IF($H90=AL$3,$J90,0) | AM90: =-IF($E90=AM$3,$G90,0)+IF($H90=AM$3,$J90,0) | AN90: =-IF($E90=AN$3,$G90,0)+IF($H90=AN$3,$J90,0) | AO90: =-IF($E90=AO$3,$G90,0)+IF($H90=AO$3,$J90,0) | AP90: =IF($E90=AP$3,$G90,0)-IF($H90=AP$3,$J90,0) | AQ90: =IF($E90=AQ$3,$G90,0)-IF($H90=AQ$3,$J90,0) | AR90: =IF($E90=AR$3,$G90,0)-IF($H90=AR$3,$J90,0) | AS90: =IF($E90=AS$3,$G90,0)-IF($H90=AS$3,$J90,0) | AT90: =IF($E90=AT$3,$G90,0)-IF($H90=AT$3,$J90,0) | AU90: =IF($E90=AU$3,$G90,0)-IF($H90=AU$3,$J90,0) | AV90: =IF($E90=AV$3,$G90,0)-IF($H90=AV$3,$J90,0) | AW90: =IF($E90=AW$3,$G90,0)-IF($H90=AW$3,$J90,0) | ... BK90: =IF($E90=BK$3,$G90,0)-IF($H90=BK$3,$J90,0) | BL90: =-IF($E90=BL$3,$G90,0)+IF($H90=BL$3,$J90,0) | BM90: =-IF($E90=BM$3,$G90,0)+IF($H90=BM$3,$J90,0) | BN90: =-IF($E90=BN$3,$G90,0)+IF($H90=BN$3,$J90,0) | BO90: =-IF($E90=BO$3,$G90,0)+IF($H90=BO$3,$J90,0) | BP90: =-IF($E90=BP$3,$G90,0)+IF($H90=BP$3,$J90,0) | BQ90: =-IF($E90=BQ$3,$G90,0)+IF($H90=BQ$3,$J90,0) | BR90: =-IF($E90=BR$3,$G90,0)+IF($H90=BR$3,$J90,0) | BS90: =-IF($E90=BS$3,$G90,0)+IF($H90=BS$3,$J90,0) | BT90: =-IF($E90=BT$3,$G90,0)+IF($H90=BT$3,$J90,0) | BU90: =+G90-J90 | BV90: =-IF($E90=BV$3,$G90,0)+IF($H90=BV$3,$J90,0)
F91: =IF(E91="","",IF(ISNA(VLOOKUP(E91,科目コード表!$C$4:$D$67,2,FALSE)),"該当科目なし",VLOOKUP(E91,科目コード表!$C$4:$D$67,2,FALSE))) | I91: =IF(H91="","",IF(ISNA(VLOOKUP(H91,科目コード表!$C$4:$D$67,2,FALSE)),"該当科目なし",VLOOKUP(H91,科目コード表!$C$4:$D$67,2,FALSE))) | L91: =IF($E91=L$3,$G91,0)-IF($H91=L$3,$J91,0) | M91: =IF($E91=M$3,$G91,0)-IF($H91=M$3,$J91,0) | N91: =IF($E91=N$3,$G91,0)-IF($H91=N$3,$J91,0) | O91: =IF($E91=O$3,$G91,0)-IF($H91=O$3,$J91,0) | P91: =IF($E91=P$3,$G91,0)-IF($H91=P$3,$J91,0) | Q91: =IF($E91=Q$3,$G91,0)-IF($H91=Q$3,$J91,0) | R91: =IF($E91=R$3,$G91,0)-IF($H91=R$3,$J91,0) | S91: =IF($E91=S$3,$G91,0)-IF($H91=S$3,$J91,0) | ... AL91: =IF($E91=AL$3,$G91,0)-IF($H91=AL$3,$J91,0) | AM91: =-IF($E91=AM$3,$G91,0)+IF($H91=AM$3,$J91,0) | AN91: =-IF($E91=AN$3,$G91,0)+IF($H91=AN$3,$J91,0) | AO91: =-IF($E91=AO$3,$G91,0)+IF($H91=AO$3,$J91,0) | AP91: =IF($E91=AP$3,$G91,0)-IF($H91=AP$3,$J91,0) | AQ91: =IF($E91=AQ$3,$G91,0)-IF($H91=AQ$3,$J91,0) | AR91: =IF($E91=AR$3,$G91,0)-IF($H91=AR$3,$J91,0) | AS91: =IF($E91=AS$3,$G91,0)-IF($H91=AS$3,$J91,0) | AT91: =IF($E91=AT$3,$G91,0)-IF($H91=AT$3,$J91,0) | AU91: =IF($E91=AU$3,$G91,0)-IF($H91=AU$3,$J91,0) | AV91: =IF($E91=AV$3,$G91,0)-IF($H91=AV$3,$J91,0) | AW91: =IF($E91=AW$3,$G91,0)-IF($H91=AW$3,$J91,0) | ... BK91: =IF($E91=BK$3,$G91,0)-IF($H91=BK$3,$J91,0) | BL91: =-IF($E91=BL$3,$G91,0)+IF($H91=BL$3,$J91,0) | BM91: =-IF($E91=BM$3,$G91,0)+IF($H91=BM$3,$J91,0) | BN91: =-IF($E91=BN$3,$G91,0)+IF($H91=BN$3,$J91,0) | BO91: =-IF($E91=BO$3,$G91,0)+IF($H91=BO$3,$J91,0) | BP91: =-IF($E91=BP$3,$G91,0)+IF($H91=BP$3,$J91,0) | BQ91: =-IF($E91=BQ$3,$G91,0)+IF($H91=BQ$3,$J91,0) | BR91: =-IF($E91=BR$3,$G91,0)+IF($H91=BR$3,$J91,0) | BS91: =-IF($E91=BS$3,$G91,0)+IF($H91=BS$3,$J91,0) | BT91: =-IF($E91=BT$3,$G91,0)+IF($H91=BT$3,$J91,0) | BU91: =+G91-J91 | BV91: =-IF($E91=BV$3,$G91,0)+IF($H91=BV$3,$J91,0)
F92: =IF(E92="","",IF(ISNA(VLOOKUP(E92,科目コード表!$C$4:$D$67,2,FALSE)),"該当科目なし",VLOOKUP(E92,科目コード表!$C$4:$D$67,2,FALSE))) | I92: =IF(H92="","",IF(ISNA(VLOOKUP(H92,科目コード表!$C$4:$D$67,2,FALSE)),"該当科目なし",VLOOKUP(H92,科目コード表!$C$4:$D$67,2,FALSE))) | L92: =IF($E92=L$3,$G92,0)-IF($H92=L$3,$J92,0) | M92: =IF($E92=M$3,$G92,0)-IF($H92=M$3,$J92,0) | N92: =IF($E92=N$3,$G92,0)-IF($H92=N$3,$J92,0) | O92: =IF($E92=O$3,$G92,0)-IF($H92=O$3,$J92,0) | P92: =IF($E92=P$3,$G92,0)-IF($H92=P$3,$J92,0) | Q92: =IF($E92=Q$3,$G92,0)-IF($H92=Q$3,$J92,0) | R92: =IF($E92=R$3,$G92,0)-IF($H92=R$3,$J92,0) | S92: =IF($E92=S$3,$G92,0)-IF($H92=S$3,$J92,0) | ... AL92: =IF($E92=AL$3,$G92,0)-IF($H92=AL$3,$J92,0) | AM92: =-IF($E92=AM$3,$G92,0)+IF($H92=AM$3,$J92,0) | AN92: =-IF($E92=AN$3,$G92,0)+IF($H92=AN$3,$J92,0) | AO92: =-IF($E92=AO$3,$G92,0)+IF($H92=AO$3,$J92,0) | AP92: =IF($E92=AP$3,$G92,0)-IF($H92=AP$3,$J92,0) | AQ92: =IF($E92=AQ$3,$G92,0)-IF($H92=AQ$3,$J92,0) | AR92: =IF($E92=AR$3,$G92,0)-IF($H92=AR$3,$J92,0) | AS92: =IF($E92=AS$3,$G92,0)-IF($H92=AS$3,$J92,0) | AT92: =IF($E92=AT$3,$G92,0)-IF($H92=AT$3,$J92,0) | AU92: =IF($E92=AU$3,$G92,0)-IF($H92=AU$3,$J92,0) | AV92: =IF($E92=AV$3,$G92,0)-IF($H92=AV$3,$J92,0) | AW92: =IF($E92=AW$3,$G92,0)-IF($H92=AW$3,$J92,0) | ... BK92: =IF($E92=BK$3,$G92,0)-IF($H92=BK$3,$J92,0) | BL92: =-IF($E92=BL$3,$G92,0)+IF($H92=BL$3,$J92,0) | BM92: =-IF($E92=BM$3,$G92,0)+IF($H92=BM$3,$J92,0) | BN92: =-IF($E92=BN$3,$G92,0)+IF($H92=BN$3,$J92,0) | BO92: =-IF($E92=BO$3,$G92,0)+IF($H92=BO$3,$J92,0) | BP92: =-IF($E92=BP$3,$G92,0)+IF($H92=BP$3,$J92,0) | BQ92: =-IF($E92=BQ$3,$G92,0)+IF($H92=BQ$3,$J92,0) | BR92: =-IF($E92=BR$3,$G92,0)+IF($H92=BR$3,$J92,0) | BS92: =-IF($E92=BS$3,$G92,0)+IF($H92=BS$3,$J92,0) | BT92: =-IF($E92=BT$3,$G92,0)+IF($H92=BT$3,$J92,0) | BU92: =+G92-J92 | BV92: =-IF($E92=BV$3,$G92,0)+IF($H92=BV$3,$J92,0)
F93: =IF(E93="","",IF(ISNA(VLOOKUP(E93,科目コード表!$C$4:$D$67,2,FALSE)),"該当科目なし",VLOOKUP(E93,科目コード表!$C$4:$D$67,2,FALSE))) | I93: =IF(H93="","",IF(ISNA(VLOOKUP(H93,科目コード表!$C$4:$D$67,2,FALSE)),"該当科目なし",VLOOKUP(H93,科目コード表!$C$4:$D$67,2,FALSE))) | L93: =IF($E93=L$3,$G93,0)-IF($H93=L$3,$J93,0) | M93: =IF($E93=M$3,$G93,0)-IF($H93=M$3,$J93,0) | N93: =IF($E93=N$3,$G93,0)-IF($H93=N$3,$J93,0) | O93: =IF($E93=O$3,$G93,0)-IF($H93=O$3,$J93,0) | P93: =IF($E93=P$3,$G93,0)-IF($H93=P$3,$J93,0) | Q93: =IF($E93=Q$3,$G93,0)-IF($H93=Q$3,$J93,0) | R93: =IF($E93=R$3,$G93,0)-IF($H93=R$3,$J93,0) | S93: =IF($E93=S$3,$G93,0)-IF($H93=S$3,$J93,0) | ... AL93: =IF($E93=AL$3,$G93,0)-IF($H93=AL$3,$J93,0) | AM93: =-IF($E93=AM$3,$G93,0)+IF($H93=AM$3,$J93,0) | AN93: =-IF($E93=AN$3,$G93,0)+IF($H93=AN$3,$J93,0) | AO93: =-IF($E93=AO$3,$G93,0)+IF($H93=AO$3,$J93,0) | AP93: =IF($E93=AP$3,$G93,0)-IF($H93=AP$3,$J93,0) | AQ93: =IF($E93=AQ$3,$G93,0)-IF($H93=AQ$3,$J93,0) | AR93: =IF($E93=AR$3,$G93,0)-IF($H93=AR$3,$J93,0) | AS93: =IF($E93=AS$3,$G93,0)-IF($H93=AS$3,$J93,0) | AT93: =IF($E93=AT$3,$G93,0)-IF($H93=AT$3,$J93,0) | AU93: =IF($E93=AU$3,$G93,0)-IF($H93=AU$3,$J93,0) | AV93: =IF($E93=AV$3,$G93,0)-IF($H93=AV$3,$J93,0) | AW93: =IF($E93=AW$3,$G93,0)-IF($H93=AW$3,$J93,0) | ... BK93: =IF($E93=BK$3,$G93,0)-IF($H93=BK$3,$J93,0) | BL93: =-IF($E93=BL$3,$G93,0)+IF($H93=BL$3,$J93,0) | BM93: =-IF($E93=BM$3,$G93,0)+IF($H93=BM$3,$J93,0) | BN93: =-IF($E93=BN$3,$G93,0)+IF($H93=BN$3,$J93,0) | BO93: =-IF($E93=BO$3,$G93,0)+IF($H93=BO$3,$J93,0) | BP93: =-IF($E93=BP$3,$G93,0)+IF($H93=BP$3,$J93,0) | BQ93: =-IF($E93=BQ$3,$G93,0)+IF($H93=BQ$3,$J93,0) | BR93: =-IF($E93=BR$3,$G93,0)+IF($H93=BR$3,$J93,0) | BS93: =-IF($E93=BS$3,$G93,0)+IF($H93=BS$3,$J93,0) | BT93: =-IF($E93=BT$3,$G93,0)+IF($H93=BT$3,$J93,0) | BU93: =+G93-J93 | BV93: =-IF($E93=BV$3,$G93,0)+IF($H93=BV$3,$J93,0)
F94: =IF(E94="","",IF(ISNA(VLOOKUP(E94,科目コード表!$C$4:$D$67,2,FALSE)),"該当科目なし",VLOOKUP(E94,科目コード表!$C$4:$D$67,2,FALSE))) | I94: =IF(H94="","",IF(ISNA(VLOOKUP(H94,科目コード表!$C$4:$D$67,2,FALSE)),"該当科目なし",VLOOKUP(H94,科目コード表!$C$4:$D$67,2,FALSE))) | L94: =IF($E94=L$3,$G94,0)-IF($H94=L$3,$J94,0) | M94: =IF($E94=M$3,$G94,0)-IF($H94=M$3,$J94,0) | N94: =IF($E94=N$3,$G94,0)-IF($H94=N$3,$J94,0) | O94: =IF($E94=O$3,$G94,0)-IF($H94=O$3,$J94,0) | P94: =IF($E94=P$3,$G94,0)-IF($H94=P$3,$J94,0) | Q94: =IF($E94=Q$3,$G94,0)-IF($H94=Q$3,$J94,0) | R94: =IF($E94=R$3,$G94,0)-IF($H94=R$3,$J94,0) | S94: =IF($E94=S$3,$G94,0)-IF($H94=S$3,$J94,0) | ... AL94: =IF($E94=AL$3,$G94,0)-IF($H94=AL$3,$J94,0) | AM94: =-IF($E94=AM$3,$G94,0)+IF($H94=AM$3,$J94,0) | AN94: =-IF($E94=AN$3,$G94,0)+IF($H94=AN$3,$J94,0) | AO94: =-IF($E94=AO$3,$G94,0)+IF($H94=AO$3,$J94,0) | AP94: =IF($E94=AP$3,$G94,0)-IF($H94=AP$3,$J94,0) | AQ94: =IF($E94=AQ$3,$G94,0)-IF($H94=AQ$3,$J94,0) | AR94: =IF($E94=AR$3,$G94,0)-IF($H94=AR$3,$J94,0) | AS94: =IF($E94=AS$3,$G94,0)-IF($H94=AS$3,$J94,0) | AT94: =IF($E94=AT$3,$G94,0)-IF($H94=AT$3,$J94,0) | AU94: =IF($E94=AU$3,$G94,0)-IF($H94=AU$3,$J94,0) | AV94: =IF($E94=AV$3,$G94,0)-IF($H94=AV$3,$J94,0) | AW94: =IF($E94=AW$3,$G94,0)-IF($H94=AW$3,$J94,0) | ... BK94: =IF($E94=BK$3,$G94,0)-IF($H94=BK$3,$J94,0) | BL94: =-IF($E94=BL$3,$G94,0)+IF($H94=BL$3,$J94,0) | BM94: =-IF($E94=BM$3,$G94,0)+IF($H94=BM$3,$J94,0) | BN94: =-IF($E94=BN$3,$G94,0)+IF($H94=BN$3,$J94,0) | BO94: =-IF($E94=BO$3,$G94,0)+IF($H94=BO$3,$J94,0) | BP94: =-IF($E94=BP$3,$G94,0)+IF($H94=BP$3,$J94,0) | BQ94: =-IF($E94=BQ$3,$G94,0)+IF($H94=BQ$3,$J94,0) | BR94: =-IF($E94=BR$3,$G94,0)+IF($H94=BR$3,$J94,0) | BS94: =-IF($E94=BS$3,$G94,0)+IF($H94=BS$3,$J94,0) | BT94: =-IF($E94=BT$3,$G94,0)+IF($H94=BT$3,$J94,0) | BU94: =+G94-J94 | BV94: =-IF($E94=BV$3,$G94,0)+IF($H94=BV$3,$J94,0)
F95: =IF(E95="","",IF(ISNA(VLOOKUP(E95,科目コード表!$C$4:$D$67,2,FALSE)),"該当科目なし",VLOOKUP(E95,科目コード表!$C$4:$D$67,2,FALSE))) | I95: =IF(H95="","",IF(ISNA(VLOOKUP(H95,科目コード表!$C$4:$D$67,2,FALSE)),"該当科目なし",VLOOKUP(H95,科目コード表!$C$4:$D$67,2,FALSE))) | L95: =IF($E95=L$3,$G95,0)-IF($H95=L$3,$J95,0) | M95: =IF($E95=M$3,$G95,0)-IF($H95=M$3,$J95,0) | N95: =IF($E95=N$3,$G95,0)-IF($H95=N$3,$J95,0) | O95: =IF($E95=O$3,$G95,0)-IF($H95=O$3,$J95,0) | P95: =IF($E95=P$3,$G95,0)-IF($H95=P$3,$J95,0) | Q95: =IF($E95=Q$3,$G95,0)-IF($H95=Q$3,$J95,0) | R95: =IF($E95=R$3,$G95,0)-IF($H95=R$3,$J95,0) | S95: =IF($E95=S$3,$G95,0)-IF($H95=S$3,$J95,0) | ... AL95: =IF($E95=AL$3,$G95,0)-IF($H95=AL$3,$J95,0) | AM95: =-IF($E95=AM$3,$G95,0)+IF($H95=AM$3,$J95,0) | AN95: =-IF($E95=AN$3,$G95,0)+IF($H95=AN$3,$J95,0) | AO95: =-IF($E95=AO$3,$G95,0)+IF($H95=AO$3,$J95,0) | AP95: =IF($E95=AP$3,$G95,0)-IF($H95=AP$3,$J95,0) | AQ95: =IF($E95=AQ$3,$G95,0)-IF($H95=AQ$3,$J95,0) | AR95: =IF($E95=AR$3,$G95,0)-IF($H95=AR$3,$J95,0) | AS95: =IF($E95=AS$3,$G95,0)-IF($H95=AS$3,$J95,0) | AT95: =IF($E95=AT$3,$G95,0)-IF($H95=AT$3,$J95,0) | AU95: =IF($E95=AU$3,$G95,0)-IF($H95=AU$3,$J95,0) | AV95: =IF($E95=AV$3,$G95,0)-IF($H95=AV$3,$J95,0) | AW95: =IF($E95=AW$3,$G95,0)-IF($H95=AW$3,$J95,0) | ... BK95: =IF($E95=BK$3,$G95,0)-IF($H95=BK$3,$J95,0) | BL95: =-IF($E95=BL$3,$G95,0)+IF($H95=BL$3,$J95,0) | BM95: =-IF($E95=BM$3,$G95,0)+IF($H95=BM$3,$J95,0) | BN95: =-IF($E95=BN$3,$G95,0)+IF($H95=BN$3,$J95,0) | BO95: =-IF($E95=BO$3,$G95,0)+IF($H95=BO$3,$J95,0) | BP95: =-IF($E95=BP$3,$G95,0)+IF($H95=BP$3,$J95,0) | BQ95: =-IF($E95=BQ$3,$G95,0)+IF($H95=BQ$3,$J95,0) | BR95: =-IF($E95=BR$3,$G95,0)+IF($H95=BR$3,$J95,0) | BS95: =-IF($E95=BS$3,$G95,0)+IF($H95=BS$3,$J95,0) | BT95: =-IF($E95=BT$3,$G95,0)+IF($H95=BT$3,$J95,0) | BU95: =+G95-J95 | BV95: =-IF($E95=BV$3,$G95,0)+IF($H95=BV$3,$J95,0)
F96: =IF(E96="","",IF(ISNA(VLOOKUP(E96,科目コード表!$C$4:$D$67,2,FALSE)),"該当科目なし",VLOOKUP(E96,科目コード表!$C$4:$D$67,2,FALSE))) | I96: =IF(H96="","",IF(ISNA(VLOOKUP(H96,科目コード表!$C$4:$D$67,2,FALSE)),"該当科目なし",VLOOKUP(H96,科目コード表!$C$4:$D$67,2,FALSE))) | L96: =IF($E96=L$3,$G96,0)-IF($H96=L$3,$J96,0) | M96: =IF($E96=M$3,$G96,0)-IF($H96=M$3,$J96,0) | N96: =IF($E96=N$3,$G96,0)-IF($H96=N$3,$J96,0) | O96: =IF($E96=O$3,$G96,0)-IF($H96=O$3,$J96,0) | P96: =IF($E96=P$3,$G96,0)-IF($H96=P$3,$J96,0) | Q96: =IF($E96=Q$3,$G96,0)-IF($H96=Q$3,$J96,0) | R96: =IF($E96=R$3,$G96,0)-IF($H96=R$3,$J96,0) | S96: =IF($E96=S$3,$G96,0)-IF($H96=S$3,$J96,0) | ... AL96: =IF($E96=AL$3,$G96,0)-IF($H96=AL$3,$J96,0) | AM96: =-IF($E96=AM$3,$G96,0)+IF($H96=AM$3,$J96,0) | AN96: =-IF($E96=AN$3,$G96,0)+IF($H96=AN$3,$J96,0) | AO96: =-IF($E96=AO$3,$G96,0)+IF($H96=AO$3,$J96,0) | AP96: =IF($E96=AP$3,$G96,0)-IF($H96=AP$3,$J96,0) | AQ96: =IF($E96=AQ$3,$G96,0)-IF($H96=AQ$3,$J96,0) | AR96: =IF($E96=AR$3,$G96,0)-IF($H96=AR$3,$J96,0) | AS96: =IF($E96=AS$3,$G96,0)-IF($H96=AS$3,$J96,0) | AT96: =IF($E96=AT$3,$G96,0)-IF($H96=AT$3,$J96,0) | AU96: =IF($E96=AU$3,$G96,0)-IF($H96=AU$3,$J96,0) | AV96: =IF($E96=AV$3,$G96,0)-IF($H96=AV$3,$J96,0) | AW96: =IF($E96=AW$3,$G96,0)-IF($H96=AW$3,$J96,0) | ... BK96: =IF($E96=BK$3,$G96,0)-IF($H96=BK$3,$J96,0) | BL96: =-IF($E96=BL$3,$G96,0)+IF($H96=BL$3,$J96,0) | BM96: =-IF($E96=BM$3,$G96,0)+IF($H96=BM$3,$J96,0) | BN96: =-IF($E96=BN$3,$G96,0)+IF($H96=BN$3,$J96,0) | BO96: =-IF($E96=BO$3,$G96,0)+IF($H96=BO$3,$J96,0) | BP96: =-IF($E96=BP$3,$G96,0)+IF($H96=BP$3,$J96,0) | BQ96: =-IF($E96=BQ$3,$G96,0)+IF($H96=BQ$3,$J96,0) | BR96: =-IF($E96=BR$3,$G96,0)+IF($H96=BR$3,$J96,0) | BS96: =-IF($E96=BS$3,$G96,0)+IF($H96=BS$3,$J96,0) | BT96: =-IF($E96=BT$3,$G96,0)+IF($H96=BT$3,$J96,0) | BU96: =+G96-J96 | BV96: =-IF($E96=BV$3,$G96,0)+IF($H96=BV$3,$J96,0)
F97: =IF(E97="","",IF(ISNA(VLOOKUP(E97,科目コード表!$C$4:$D$67,2,FALSE)),"該当科目なし",VLOOKUP(E97,科目コード表!$C$4:$D$67,2,FALSE))) | I97: =IF(H97="","",IF(ISNA(VLOOKUP(H97,科目コード表!$C$4:$D$67,2,FALSE)),"該当科目なし",VLOOKUP(H97,科目コード表!$C$4:$D$67,2,FALSE))) | L97: =IF($E97=L$3,$G97,0)-IF($H97=L$3,$J97,0) | M97: =IF($E97=M$3,$G97,0)-IF($H97=M$3,$J97,0) | N97: =IF($E97=N$3,$G97,0)-IF($H97=N$3,$J97,0) | O97: =IF($E97=O$3,$G97,0)-IF($H97=O$3,$J97,0) | P97: =IF($E97=P$3,$G97,0)-IF($H97=P$3,$J97,0) | Q97: =IF($E97=Q$3,$G97,0)-IF($H97=Q$3,$J97,0) | R97: =IF($E97=R$3,$G97,0)-IF($H97=R$3,$J97,0) | S97: =IF($E97=S$3,$G97,0)-IF($H97=S$3,$J97,0) | ... AL97: =IF($E97=AL$3,$G97,0)-IF($H97=AL$3,$J97,0) | AM97: =-IF($E97=AM$3,$G97,0)+IF($H97=AM$3,$J97,0) | AN97: =-IF($E97=AN$3,$G97,0)+IF($H97=AN$3,$J97,0) | AO97: =-IF($E97=AO$3,$G97,0)+IF($H97=AO$3,$J97,0) | AP97: =IF($E97=AP$3,$G97,0)-IF($H97=AP$3,$J97,0) | AQ97: =IF($E97=AQ$3,$G97,0)-IF($H97=AQ$3,$J97,0) | AR97: =IF($E97=AR$3,$G97,0)-IF($H97=AR$3,$J97,0) | AS97: =IF($E97=AS$3,$G97,0)-IF($H97=AS$3,$J97,0) | AT97: =IF($E97=AT$3,$G97,0)-IF($H97=AT$3,$J97,0) | AU97: =IF($E97=AU$3,$G97,0)-IF($H97=AU$3,$J97,0) | AV97: =IF($E97=AV$3,$G97,0)-IF($H97=AV$3,$J97,0) | AW97: =IF($E97=AW$3,$G97,0)-IF($H97=AW$3,$J97,0) | ... BK97: =IF($E97=BK$3,$G97,0)-IF($H97=BK$3,$J97,0) | BL97: =-IF($E97=BL$3,$G97,0)+IF($H97=BL$3,$J97,0) | BM97: =-IF($E97=BM$3,$G97,0)+IF($H97=BM$3,$J97,0) | BN97: =-IF($E97=BN$3,$G97,0)+IF($H97=BN$3,$J97,0) | BO97: =-IF($E97=BO$3,$G97,0)+IF($H97=BO$3,$J97,0) | BP97: =-IF($E97=BP$3,$G97,0)+IF($H97=BP$3,$J97,0) | BQ97: =-IF($E97=BQ$3,$G97,0)+IF($H97=BQ$3,$J97,0) | BR97: =-IF($E97=BR$3,$G97,0)+IF($H97=BR$3,$J97,0) | BS97: =-IF($E97=BS$3,$G97,0)+IF($H97=BS$3,$J97,0) | BT97: =-IF($E97=BT$3,$G97,0)+IF($H97=BT$3,$J97,0) | BU97: =+G97-J97 | BV97: =-IF($E97=BV$3,$G97,0)+IF($H97=BV$3,$J97,0)
... F309: =IF(E309="","",IF(ISNA(VLOOKUP(E309,科目コード表!$C$4:$D$67,2,FALSE)),"該当科目なし",VLOOKUP(E309,科目コード表!$C$4:$D$67,2,FALSE))) | I309: =IF(H309="","",IF(ISNA(VLOOKUP(H309,科目コード表!$C$4:$D$67,2,FALSE)),"該当科目なし",VLOOKUP(H309,科目コード表!$C$4:$D$67,2,FALSE))) | L309: =IF($E309=L$3,$G309,0)-IF($H309=L$3,$J309,0) | M309: =IF($E309=M$3,$G309,0)-IF($H309=M$3,$J309,0) | N309: =IF($E309=N$3,$G309,0)-IF($H309=N$3,$J309,0) | O309: =IF($E309=O$3,$G309,0)-IF($H309=O$3,$J309,0) | P309: =IF($E309=P$3,$G309,0)-IF($H309=P$3,$J309,0) | Q309: =IF($E309=Q$3,$G309,0)-IF($H309=Q$3,$J309,0) | R309: =IF($E309=R$3,$G309,0)-IF($H309=R$3,$J309,0) | S309: =IF($E309=S$3,$G309,0)-IF($H309=S$3,$J309,0) | ... AL309: =IF($E309=AL$3,$G309,0)-IF($H309=AL$3,$J309,0) | AM309: =-IF($E309=AM$3,$G309,0)+IF($H309=AM$3,$J309,0) | AN309: =-IF($E309=AN$3,$G309,0)+IF($H309=AN$3,$J309,0) | AO309: =-IF($E309=AO$3,$G309,0)+IF($H309=AO$3,$J309,0) | AP309: =IF($E309=AP$3,$G309,0)-IF($H309=AP$3,$J309,0) | AQ309: =IF($E309=AQ$3,$G309,0)-IF($H309=AQ$3,$J309,0) | AR309: =IF($E309=AR$3,$G309,0)-IF($H309=AR$3,$J309,0) | AS309: =IF($E309=AS$3,$G309,0)-IF($H309=AS$3,$J309,0) | AT309: =IF($E309=AT$3,$G309,0)-IF($H309=AT$3,$J309,0) | AU309: =IF($E309=AU$3,$G309,0)-IF($H309=AU$3,$J309,0) | AV309: =IF($E309=AV$3,$G309,0)-IF($H309=AV$3,$J309,0) | AW309: =IF($E309=AW$3,$G309,0)-IF($H309=AW$3,$J309,0) | ... BK309: =IF($E309=BK$3,$G309,0)-IF($H309=BK$3,$J309,0) | BL309: =-IF($E309=BL$3,$G309,0)+IF($H309=BL$3,$J309,0) | BM309: =-IF($E309=BM$3,$G309,0)+IF($H309=BM$3,$J309,0) | BN309: =-IF($E309=BN$3,$G309,0)+IF($H309=BN$3,$J309,0) | BO309: =-IF($E309=BO$3,$G309,0)+IF($H309=BO$3,$J309,0) | BP309: =-IF($E309=BP$3,$G309,0)+IF($H309=BP$3,$J309,0) | BQ309: =-IF($E309=BQ$3,$G309,0)+IF($H309=BQ$3,$J309,0) | BR309: =-IF($E309=BR$3,$G309,0)+IF($H309=BR$3,$J309,0) | BS309: =-IF($E309=BS$3,$G309,0)+IF($H309=BS$3,$J309,0) | BT309: =-IF($E309=BT$3,$G309,0)+IF($H309=BT$3,$J309,0) | BU309: =+G309-J309 | BV309: =-IF($E309=BV$3,$G309,0)+IF($H309=BV$3,$J309,0)
F310: =IF(E310="","",IF(ISNA(VLOOKUP(E310,科目コード表!$C$4:$D$67,2,FALSE)),"該当科目なし",VLOOKUP(E310,科目コード表!$C$4:$D$67,2,FALSE))) | I310: =IF(H310="","",IF(ISNA(VLOOKUP(H310,科目コード表!$C$4:$D$67,2,FALSE)),"該当科目なし",VLOOKUP(H310,科目コード表!$C$4:$D$67,2,FALSE))) | L310: =SUM(L5:L309) | M310: =SUM(M5:M309) | N310: =SUM(N5:N309) | O310: =SUM(O5:O309) | P310: =SUM(P5:P309) | Q310: =SUM(Q5:Q309) | R310: =SUM(R5:R309) | S310: =SUM(S5:S309) | ... BV310: =SUM(BV5:BV309)

Sheet 決算書
F1: =+'仕訳帳 '!A1
A2: 貸借対照表
A3: 101 | B3: =VLOOKUP(A3,科目コード表!$C$4:$D$67,2,FALSE) | C3: =+'仕訳帳 '!AP310
A4: 102 | B4: =VLOOKUP(A4,科目コード表!$C$4:$D$67,2,FALSE) | C4: =+'仕訳帳 '!AQ310
A5: 103 | B5: =VLOOKUP(A5,科目コード表!$C$4:$D$67,2,FALSE) | C5: =+'仕訳帳 '!AR310
A6: 104 | B6: =VLOOKUP(A6,科目コード表!$C$4:$D$67,2,FALSE) | C6: =+'仕訳帳 '!AS310
A7: 105 | B7: =VLOOKUP(A7,科目コード表!$C$4:$D$67,2,FALSE) | C7: =+'仕訳帳 '!AT310
A8: 106 | B8: =VLOOKUP(A8,科目コード表!$C$4:$D$67,2,FALSE) | C8: =+'仕訳帳 '!AU310 | D8: 201 | E8: =VLOOKUP(D8,科目コード表!$C$4:$D$67,2,FALSE) | F8: =+'仕訳帳 '!BL310
A9: 107 | B9: =VLOOKUP(A9,科目コード表!$C$4:$D$67,2,FALSE) | C9: =+'仕訳帳 '!AV310 | D9: 202 | E9: =VLOOKUP(D9,科目コード表!$C$4:$D$67,2,FALSE) | F9: =+'仕訳帳 '!BM310
A10: 108 | B10: =VLOOKUP(A10,科目コード表!$C$4:$D$67,2,FALSE) | C10: =+'仕訳帳 '!AW310
A11: 109 | B11: =VLOOKUP(A11,科目コード表!$C$4:$D$67,2,FALSE) | C11: =+'仕訳帳 '!AX310 | D11: 203 | E11: =VLOOKUP(D11,科目コード表!$C$4:$D$67,2,FALSE) | F11: =+'仕訳帳 '!BN310
A12: 110 | B12: =VLOOKUP(A12,科目コード表!$C$4:$D$67,2,FALSE) | C12: =+'仕訳帳 '!AY310 | D12: 205 | E12: =VLOOKUP(D12,科目コード表!$C$4:$D$67,2,FALSE) | F12: =+'仕訳帳 '!BP310
A13: 111 | B13: =VLOOKUP(A13,科目コード表!$C$4:$D$67,2,FALSE) | C13: =+'仕訳帳 '!AZ310 | D13: 207 | E13: =VLOOKUP(D13,科目コード表!$C$4:$D$67,2,FALSE) | F13: =+'仕訳帳 '!BR310
A14: 112 | B14: =VLOOKUP(A14,科目コード表!$C$4:$D$67,2,FALSE) | C14: =+'仕訳帳 '!BA310 | D14: 204 | E14: =VLOOKUP(D14,科目コード表!$C$4:$D$67,2,FALSE) | F14: =+'仕訳帳 '!BO310
A15: 113 | B15: =VLOOKUP(A15,科目コード表!$C$4:$D$67,2,FALSE) | C15: =+'仕訳帳 '!BB310 | D15: 206 | E15: =VLOOKUP(D15,科目コード表!$C$4:$D$67,2,FALSE) | F15: =+'仕訳帳 '!BQ310
A16: 114 | B16: =VLOOKUP(A16,科目コード表!$C$4:$D$67,2,FALSE) | C16: =+'仕訳帳 '!BC310 | D16: 208 | E16: =VLOOKUP(D16,科目コード表!$C$4:$D$67,2,FALSE) | F16: =+'仕訳帳 '!BS310
A17: 121 | B17: =VLOOKUP(A17,科目コード表!$C$4:$D$67,2,FALSE) | C17: =+'仕訳帳 '!BD310
A18: 122 | B18: =VLOOKUP(A18,科目コード表!$C$4:$D$67,2,FALSE) | C18: =+'仕訳帳 '!BE310
A19: 123 | B19: =VLOOKUP(A19,科目コード表!$C$4:$D$67,2,FALSE) | C19: =+'仕訳帳 '!BF310
A20: 124 | B20: =VLOOKUP(A20,科目コード表!$C$4:$D$67,2,FALSE) | C20: =+'仕訳帳 '!BG310
A21: 125 | B21: =VLOOKUP(A21,科目コード表!$C$4:$D$67,2,FALSE) | C21: =+'仕訳帳 '!BH310
D22: 209 | E22: =VLOOKUP(D22,科目コード表!$C$4:$D$67,2,FALSE) | F22: =+'仕訳帳 '!BT310
A23: 126 | B23: =VLOOKUP(A23,科目コード表!$C$4:$D$67,2,FALSE) | C23: =+'仕訳帳 '!BI310 | D23: 301 | E23: =VLOOKUP(D23,科目コード表!$C$4:$D$67,2,FALSE) | F23: =+'仕訳帳 '!BU310
A24: 127 | B24: =VLOOKUP(A24,科目コード表!$C$4:$D$67,2,FALSE) | C24: =+'仕訳帳 '!BJ310 | D24: 302 | E24: =VLOOKUP(D24,科目コード表!$C$4:$D$67,2,FALSE) | F24: =+'仕訳帳 '!BV310
A25: 128 | B25: =VLOOKUP(A25,科目コード表!$C$4:$D$67,2,FALSE) | C25: =+'仕訳帳 '!BK310 | E25: 特別控除前利益 | F25: =+C57
B26: 合計 | C26: =SUM(C3:C25) | E26: 合計 | F26: =SUM(F4:F25) | G26: =IF(C26=F26,"OK","貸借不一致です！")
B28: 損益計算書
A29: 501 | B29: =VLOOKUP(A29,科目コード表!$C$4:$D$67,2,FALSE) | C29: =+'仕訳帳 '!L310
A30: 502 | B30: =VLOOKUP(A30,科目コード表!$C$4:$D$67,2,FALSE) | C30: =+'仕訳帳 '!M310 | D30: 401 | E30: =VLOOKUP(D30,科目コード表!$C$4:$D$67,2,FALSE) | F30: =+'仕訳帳 '!AM310
A31: 503 | B31: =VLOOKUP(A31,科目コード表!$C$4:$D$67,2,FALSE) | C31: =+'仕訳帳 '!N310
A32: 504 | B32: =VLOOKUP(A32,科目コード表!$C$4:$D$67,2,FALSE) | C32: =+'仕訳帳 '!O310 | D32: 403 | E32: =VLOOKUP(D32,科目コード表!$C$4:$D$67,2,FALSE) | F32: =+'仕訳帳 '!AO310
A33: 505 | B33: =VLOOKUP(A33,科目コード表!$C$4:$D$67,2,FALSE) | C33: =+'仕訳帳 '!P310 | D33: 402 | E33: =VLOOKUP(D33,科目コード表!$C$4:$D$67,2,FALSE) | F33: =+'仕訳帳 '!AN310
A34: 506 | B34: =VLOOKUP(A34,科目コード表!$C$4:$D$67,2,FALSE) | C34: =+'仕訳帳 '!Q310
A35: 507 | B35: =VLOOKUP(A35,科目コード表!$C$4:$D$67,2,FALSE) | C35: =+'仕訳帳 '!R310
A36: 508 | B36: =VLOOKUP(A36,科目コード表!$C$4:$D$67,2,FALSE) | C36: =+'仕訳帳 '!S310
A37: 509 | B37: =VLOOKUP(A37,科目コード表!$C$4:$D$67,2,FALSE) | C37: =+'仕訳帳 '!T310
A38: 510 | B38: =VLOOKUP(A38,科目コード表!$C$4:$D$67,2,FALSE) | C38: =+'仕訳帳 '!U310
A39: 511 | B39: =VLOOKUP(A39,科目コード表!$C$4:$D$67,2,FALSE) | C39: =+'仕訳帳 '!V310
A40: 512 | B40: =VLOOKUP(A40,科目コード表!$C$4:$D$67,2,FALSE) | C40: =+'仕訳帳 '!W310
A41: 513 | B41: =VLOOKUP(A41,科目コード表!$C$4:$D$67,2,FALSE) | C41: =+'仕訳帳 '!X310
A42: 514 | B42: =VLOOKUP(A42,科目コード表!$C$4:$D$67,2,FALSE) | C42: =+'仕訳帳 '!Y310
A43: 515 | B43: =VLOOKUP(A43,科目コード表!$C$4:$D$67,2,FALSE) | C43: =+'仕訳帳 '!Z310
A44: 516 | B44: =VLOOKUP(A44,科目コード表!$C$4:$D$67,2,FALSE) | C44: =+'仕訳帳 '!AA310
A45: 517 | B45: =VLOOKUP(A45,科目コード表!$C$4:$D$67,2,FALSE) | C45: =+'仕訳帳 '!AB310
A46: 518 | B46: =VLOOKUP(A46,科目コード表!$C$4:$D$67,2,FALSE) | C46: =+'仕訳帳 '!AC310
A47: 519 | B47: =VLOOKUP(A47,科目コード表!$C$4:$D$67,2,FALSE) | C47: =+'仕訳帳 '!AD310
A48: 520 | B48: =VLOOKUP(A48,科目コード表!$C$4:$D$67,2,FALSE) | C48: =+'仕訳帳 '!AE310
A49: 521 | B49: =VLOOKUP(A49,科目コード表!$C$4:$D$67,2,FALSE) | C49: =+'仕訳帳 '!AF310
A50: 522 | B50: =VLOOKUP(A50,科目コード表!$C$4:$D$67,2,FALSE) | C50: =+'仕訳帳 '!AG310
A51: 523 | B51: =VLOOKUP(A51,科目コード表!$C$4:$D$67,2,FALSE) | C51: =+'仕訳帳 '!AH310
A52: 524 | B52: =VLOOKUP(A52,科目コード表!$C$4:$D$67,2,FALSE) | C52: =+'仕訳帳 '!AI310
A53: 525 | B53: =VLOOKUP(A53,科目コード表!$C$4:$D$67,2,FALSE) | C53: =+'仕訳帳 '!AJ310
A54: 526 | B54: =VLOOKUP(A54,科目コード表!$C$4:$D$67,2,FALSE) | C54: =+'仕訳帳 '!AK310
A55: 530 | B55: =VLOOKUP(A55,科目コード表!$C$4:$D$67,2,FALSE) | C55: =+'仕訳帳 '!AL310
B56: 計 | C56: =SUM(C29:C55) | F56: =SUM(F30:F55)
B57: 特別控除前利益 | C57: =+F56-C56
B58: 合計 | C58: =SUM(C56:C57) | F58: =SUM(F56)
A61: 収入内訳一覧表
A62: 日付 | B62: 相手 | C62: 内訳 | F62: 報酬 | G62: 雑収入 | H62: 源泉税 | I62: 差引
A63: 1/31 | B63: 小樽商科大学後援会 | C63: Web Site代 | F63: 11000 | I63: =+F63+G63-H63
A64: 1/31 | B64: ユーユー | C64: ブログ作成費 | F64: 100000 | I64: =+F64+G64-H64
A65: 2/28 | B65: 小樽商科大学後援会 | C65: Web Site代 | F65: 11000 | I65: =+F65+G65-H65
A66: 2/28 | B66: ユーユー | C66: ブログ作成費 | F66: 100000 | I66: =+F66+G66-H66
A67: 2/28 | B67: BASIS | C67: 開発 | F67: 770000 | I67: =+F67+G67-H67
A68: 1/17 | C68: 固定資産売却益 | G68: 329999 | I68: =+F68+G68-H68
I69: =+F69+G69-H69
I70: =+F70+G70-H70
I71: =+F71+G71-H71
I72: =+F72+G72-H72
I73: =+F73+G73-H73
I74: =+F74+G74-H74
I75: =+F75+G75-H75
I76: =+F76+G76-H76
F77: =SUM(F63:F76) | G77: =SUM(G63:G76) | H77: =SUM(H63:H76) | I77: =SUM(I63:I76)

Sheet 科目コード表
D1: 緑色の科目は国税庁HPの標準科目です。黒色の科目は自由に変更してかまいません。
E2: 国税庁の青色申告決算書（一般用）に標準で記載されている科目
C3: コード | D3: 勘定科目 | H3: 決算書と元帳兼精算表に表示した科目・・・不要な科目は非表示に、不足していれば再表示してください。
B4: 資産 | C4: 101 | D4: 現金 | E4: ○ | G4: △
C5: 102 | D5: 当座預金 | E5: ○
C6: 103 | D6: 普通預金 | E6: ○ | G6: △ | H6: (現金・普通預金は、他のソフト等から移行するときのみ使います。通常は不要です。）
C7: 104 | D7: 通知預金 | E7: ○
C8: 105 | D8: 定期預金 | E8: ○
C9: 106 | D9: 受取手形 | E9: ○
C10: 107 | D10: 売掛金 | E10: ○ | G10: ○
C11: 108 | D11: 有価証券 | E11: ○
C12: 109 | D12: 棚卸資産 | E12: ○ | G12: ○
C13: 110 | D13: 前払金 | E13: ○
C14: 111 | D14: 貸付金 | E14: ○
C15: 112 | D15: 未収入金 | G15: ○
C16: 113 | D16: 仮払源泉税 | G16: ○
C17: 114 | D17: リサイクル預託金 | G17: ○
C18: 121 | D18: 建物 | E18: ○ | G18: ○
C19: 122 | D19: 建物付属設備 | E19: ○ | G19: ○
C20: 123 | D20: 機械装置 | E20: ○
C21: 124 | D21: 車両運搬具 | E21: ○ | G21: ○
C22: 125 | D22: 工具器具備品 | E22: ○ | G22: ○
C23: 126 | D23: 土地 | E23: ○ | G23: ○
C24: 127 | D24: 構築物 | G24: ○
C25: 128 | D25: その他投資 | G25: ○
B26: 負債 | C26: 201 | D26: 支払手形 | E26: ○
C27: 202 | D27: 買掛金 | E27: ○ | G27: ○
C28: 203 | D28: 借入金 | E28: ○ | G28: ○
C29: 204 | D29: 未払金 | E29: ○ | G29: ○
C30: 205 | D30: 前受金 | E30: ○ | G30: ○
C31: 206 | D31: 預り金 | E31: ○
C32: 207 | D32: 貸倒引当金 | E32: ○
C33: 208 | D33: その他負債 | G33: ○
C34: 209 | D34: 共有者持分
B35: 資本 | C35: 301 | D35: 事業主勘定 | E35: ○ | G35: ○
C36: 302 | D36: 元入金 | E36: ○ | G36: ○
C37: 303
B38: 収益 | C38: 401 | D38: 売上(報酬） | E38: ○ | G38: ○
C39: 402 | D39: 雑収入 | E39: ○ | G39: ○
C40: 403 | D40: 雑収入(車両売却)
B41: 費用 | C41: 501 | D41: 期首棚卸高 | E41: ○
C42: 502 | D42: 仕入 | E42: ○ | G42: ○
C43: 503 | D43: 製造原価 | E43: ○
C44: 504 | D44: 期末棚卸高 | E44: ○
C45: 505 | D45: 租税公課 | E45: ○ | G45: ○
C46: 506 | D46: 荷造運賃 | E46: ○ | G46: ○
C47: 507 | D47: 水道光熱費 | E47: ○ | G47: ○
C48: 508 | D48: 旅費交通費 | E48: ○ | G48: ○
C49: 509 | D49: 通信費 | E49: ○ | G49: ○
C50: 510 | D50: 広告宣伝費 | E50: ○ | G50: ○
C51: 511 | D51: 接待交際費 | E51: ○ | G51: ○
C52: 512 | D52: 損害保険料 | E52: ○ | G52: ○
C53: 513 | D53: 修繕費 | E53: ○ | G53: ○
C54: 514 | D54: 消耗品費 | E54: ○ | G54: ○
C55: 515 | D55: 減価償却費 | E55: ○ | G55: ○
C56: 516 | D56: 福利厚生費 | E56: ○
C57: 517 | D57: 給料賃金 | E57: ○
C58: 518 | D58: 外注工賃 | E58: ○
C59: 519 | D59: 利子割引料 | E59: ○ | G59: ○
C60: 520 | D60: 地代家賃 | E60: ○ | G60: ○
C61: 521 | D61: 貸倒金 | E61: ○
C62: 522 | D62: 管理費 | G62: ○
C63: 523 | D63: 車両費 | G63: ○
C64: 524 | D64: 新聞図書費 | G64: ○
C65: 525 | D65: リース・賃借料 | G65: ○
C66: 526 | D66: 専従者給与 | E66: ○ | G66: ○
C67: 530 | D67: 雑費 | E67: ○ | G67: ○

Sheet 減価償却費
A1: 簡易減価償却・固定資産台帳 | D1: 平成19（2007）年4月1日以降に取得した減価償却資産、定額法のみ | M1: （償却率を使用する）
A3: No. | B3: 減価償却資産の名称 | C3: 取得年 | D3: 月 | E3: 取得価額 | F3: 前年末 未償却残高 | G3: 未償却残高 | H3: 償却方法 | I3: 耐用 年数 | J3: 償却率 | K3: 償却月数/12 | L3: 普通償却費 (仮） | M3: 普通償却費 | N3: 経費 割合（％） | O3: 経費算入額 | P3: 未償却残高
A4: 1 | B4: デミオ(車両) | C4: H27 | D4: 6 | E4: 2000000 | F4: 1 | G4: =IF(F4="",E4,F4) | H4: 定額法 | I4: 6 | J4: =IF(I4="","",VLOOKUP(I4,$A$32:$B$80,2)) | K4: 12 | L4: =IF(I4="",0,+ROUNDUP(E4*J4*K4/12,0)) | M4: =IF(G4=0,0,IF((G4-L4)>=1,L4,(G4-1))) | N4: 0.5 | O4: =+ROUNDUP(M4*N4,0) | P4: =+G4-M4
A5: 2 | B5: 川崎市麻生区白鳥 自宅 | C5: H28 | D5: 4 | E5: 25614216 | F5: 13983214 | G5: =IF(F5="",E5,F5) | H5: 定額法 | I5: 22 | J5: =IF(I5="","",VLOOKUP(I5,$A$32:$B$80,2)) | K5: 12 | L5: =IF(I5="",0,+ROUNDUP(E5*J5*K5/12,0)) | M5: =IF(G5=0,0,IF((G5-L5)>=1,L5,(G5-1))) | N5: 0.3 | O5: =+ROUNDUP(M5*N5,0) | P5: =+G5-M5
A6: 3 | B6: 庭、駐車場など外構工事 | C6: H28 | D6: 8 | E6: 2462400 | F6: 1303020 | G6: =IF(F6="",E6,F6) | H6: 定額法 | I6: 20 | J6: =IF(I6="","",VLOOKUP(I6,$A$32:$B$80,2)) | K6: 12 | L6: =IF(I6="",0,+ROUNDUP(E6*J6*K6/12,0)) | M6: =IF(G6=0,0,IF((G6-L6)>=1,L6,(G6-1))) | N6: 0.3 | O6: =+ROUNDUP(M6*N6,0) | P6: =+G6-M6
A7: 4 | B7: シエンタ(車両) | C7: R8 | D7: 1 | E7: 3057480 | G7: =IF(F7="",E7,F7) | H7: 定額法 | I7: 6 | J7: =IF(I7="","",VLOOKUP(I7,$A$32:$B$80,2)) | K7: 12 | L7: =IF(I7="",0,+ROUNDUP(E7*J7*K7/12,0)) | M7: =IF(G7=0,0,IF((G7-L7)>=1,L7,(G7-1))) | N7: 0.5 | O7: =+ROUNDUP(M7*N7,0) | P7: =+G7-M7
A8: 5 | G8: =IF(F8="",E8,F8) | H8: 定額法 | J8: =IF(I8="","",VLOOKUP(I8,$A$32:$B$80,2)) | L8: =IF(I8="",0,+ROUNDUP(E8*J8*K8/12,0)) | M8: =IF(G8=0,0,IF((G8-L8)>=1,L8,(G8-1))) | O8: =+ROUNDUP(M8*N8,0) | P8: =+G8-M8
A9: 6 | G9: =IF(F9="",E9,F9) | H9: 定額法 | J9: =IF(I9="","",VLOOKUP(I9,$A$32:$B$80,2)) | L9: =IF(I9="",0,+ROUNDUP(E9*J9*K9/12,0)) | M9: =IF(G9=0,0,IF((G9-L9)>=1,L9,(G9-1))) | O9: =+ROUNDUP(M9*N9,0) | P9: =+G9-M9
A10: 7 | G10: =IF(F10="",E10,F10) | H10: 定額法 | J10: =IF(I10="","",VLOOKUP(I10,$A$32:$B$80,2)) | L10: =IF(I10="",0,+ROUNDUP(E10*J10*K10/12,0)) | M10: =IF(G10=0,0,IF((G10-L10)>=1,L10,(G10-1))) | O10: =+ROUNDUP(M10*N10,0) | P10: =+G10-M10
A11: 8 | G11: =IF(F11="",E11,F11) | H11: 定額法 | J11: =IF(I11="","",VLOOKUP(I11,$A$32:$B$80,2)) | L11: =IF(I11="",0,+ROUNDUP(E11*J11*K11/12,0)) | M11: =IF(G11=0,0,IF((G11-L11)>=1,L11,(G11-1))) | O11: =+ROUNDUP(M11*N11,0) | P11: =+G11-M11
A12: 9 | G12: =IF(F12="",E12,F12) | H12: 定額法 | J12: =IF(I12="","",VLOOKUP(I12,$A$32:$B$80,2)) | L12: =IF(I12="",0,+ROUNDUP(E12*J12*K12/12,0)) | M12: =IF(G12=0,0,IF((G12-L12)>=1,L12,(G12-1))) | O12: =+ROUNDUP(M12*N12,0) | P12: =+G12-M12
A13: 10 | G13: =IF(F13="",E13,F13) | H13: 定額法 | J13: =IF(I13="","",VLOOKUP(I13,$A$32:$B$80,2)) | L13: =IF(I13="",0,+ROUNDUP(E13*J13*K13/12,0)) | M13: =IF(G13=0,0,IF((G13-L13)>=1,L13,(G13-1))) | O13: =+ROUNDUP(M13*N13,0) | P13: =+G13-M13
A14: 11 | G14: =IF(F14="",E14,F14) | H14: 定額法 | J14: =IF(I14="","",VLOOKUP(I14,$A$32:$B$80,2)) | L14: =IF(I14="",0,+ROUNDUP(E14*J14*K14/12,0)) | M14: =IF(G14=0,0,IF((G14-L14)>=1,L14,(G14-1))) | O14: =+ROUNDUP(M14*N14,0) | P14: =+G14-M14
A15: 12 | G15: =IF(F15="",E15,F15) | H15: 定額法 | J15: =IF(I15="","",VLOOKUP(I15,$A$32:$B$80,2)) | L15: =IF(I15="",0,+ROUNDUP(E15*J15*K15/12,0)) | M15: =IF(G15=0,0,IF((G15-L15)>=1,L15,(G15-1))) | O15: =+ROUNDUP(M15*N15,0) | P15: =+G15-M15
M18: 翌年はこちらへ（金額を移す）
A31: 耐用年数 | B31: 償却率
A32: 2 | B32: 0.500
A33: 3 | B33: 0.334
A34: 4 | B34: 0.250
A35: 5 | B35: 0.200
A36: 6 | B36: 0.167
A37: 7 | B37: 0.143
A38: 8 | B38: 0.125
A39: 9 | B39: 0.112
A40: 10 | B40: 0.100
A41: 11 | B41: 0.091
A42: 12 | B42: 0.084
A43: 13 | B43: 0.077
... A80: 50 | B80: 0.020

Sheet 交通費精算書
A1: 交通費精算書 | E1: （伝票No. ）
A2: 年 月 日 | B2: 交通機関 | C2: 経 路 | D2: 金 額 | E2: 用 件
A3: 2026/1/26 | B3: 小田急・地下鉄 | C3: 栗平 -> 湯島 | D3: 545 | E3: BASISで打ち合わせ
A4: 2026/1/26 | B4: 小田急・地下鉄 | C4: 湯島 -> 栗平 | D4: 545 | E4: 同上
A5: 2026/1/31 | B5: 小田急・地下鉄 | C5: 栗平 -> 神保町 | D5: 502 | E5: 神保町で打ち合わせ
A6: 2026/1/31 | B6: JR | C6: 東京 -> 新宿 | D6: 208 | E6: ちょっと八重洲で飲んで帰り
A7: 2026/1/31 | B7: 小田急 | C7: 新宿 -> 栗平 | D7: 324 | E7: 帰り
A8: 2026/2/25 | B8: 小田急・地下鉄 | C8: 栗平 -> 湯島 | D8: 545 | E8: BASISで打ち合わせ
A9: 2026/2/25 | B9: 小田急・地下鉄 | C9: 湯島 -> 栗平 | D9: 545 | E9: 同上
A17: 合計 | D17: =SUM(D3:D16)
A20: この表は自由に修正して使ってください。（どことも連動していません。）

Sheet メモ
B2: 電気料金、2月分のみpaypayで払ったが、1月分はどこで払っているのか
B3: 仕訳帳をpivotすると、月別残高試算表ができるはず
B4: 総勘定元帳は、仕訳帳のソートを変える、、だけじゃダメか。Python書くかな

Sheet Sheet1
A3: 合計 / 残高 | B3: 列ラベル
A4: 行ラベル | B4: 1 | C4: 2 | D4: 3 | E4: 総計
A5: 101 現金 | B5: 0 | E5: 0
A6: 103 普通預金 | B6: 0 | E6: 0
A7: 107 売掛金 | B7: 144000 | C7: 781000 | E7: 925000
A8: 114 リサイクル預託金 | B8: 11650 | E8: 11650
A9: 121 建物 | B9: 14597430 | E9: 14597430
A10: 124 車両運搬具 | B10: 3057480 | E10: 3057480
A11: 127 構築物 | B11: 1303020 | E11: 1303020
A12: 204 未払金 | B12: 0 | E12: 0
A13: 302 元入金 | B13: -28740668 | E13: -28740668
A14: 401 売上(報酬） | B14: -111000 | C14: -881000 | E14: -992000
A15: 403 雑収入(車両売却) | B15: -329999 | E15: -329999
A16: 507 水道光熱費 | B16: 10715 | C16: 2618 | D16: 10343 | E16: 23676
A17: 511 接待交際費 | C17: 16354 | E17: 16354
A18: 514 消耗品費 | B18: 1190 | C18: 33402 | D18: 14369 | E18: 48961
A19: 520 地代家賃 | B19: 20000 | C19: 20000 | D19: 20000 | E19: 60000
A20: 523 車両費 | B20: 20752 | C20: 929 | D20: 11645 | E20: 33326
A21: 524 新聞図書費 | B21: 980 | C21: 20228 | D21: 10012 | E21: 31220
A22: 525 リース・賃借料 | B22: 12369 | C22: 7834 | E22: 20203
A23: 総計 | B23: -10002081 | C23: 1365 | D23: 66369 | E23: -9934347

Sheet 月別残高試算表
A1: 月 | B1: 科目 | C1: 借方合計 | D1: 貸方合計 | E1: 残高
A2: 1 | B2: 101 現金 | C2: 1046520 | D2: 1046520 | E2: 0
A3: 1 | B3: 103 普通預金 | C3: 10475394 | D3: 10475394 | E3: 0
A4: 1 | B4: 107 売掛金 | C4: 1481500 | D4: 1337500 | E4: 144000
A5: 2 | B5: 107 売掛金 | C5: 881000 | D5: 100000 | E5: 781000
A6: 1 | B6: 114 リサイクル預託金 | C6: 20780 | D6: 9130 | E6: 11650
A7: 1 | B7: 121 建物 | C7: 14597430 | D7: 0 | E7: 14597430
A8: 1 | B8: 124 車両運搬具 | C8: 3057481 | D8: 1 | E8: 3057480
A9: 1 | B9: 127 構築物 | C9: 1303020 | D9: 0 | E9: 1303020
A10: 1 | B10: 204 未払金 | C10: 61327 | D10: 61327 | E10: 0
A11: 1 | B11: 302 元入金 | C11: 0 | D11: 28740668 | E11: -28740668
A12: 1 | B12: 401 売上(報酬） | C12: 0 | D12: 111000 | E12: -111000
A13: 2 | B13: 401 売上(報酬） | C13: 0 | D13: 881000 | E13: -881000
... A32: 2 | B32: 525 リース・賃借料 | C32: 7834 | D32: 0 | E32: 7834

Sheet 総勘定元帳
A1: 科目 | B1: 日付 | C1: 摘要 | D1: 相手科目 | E1: 借方 | F1: 貸方 | G1: 残高
A2: 101 現金 | B2: 1月1日 | C2: 前年繰越 現金 | E2: 1046520 | G2: 1046520
A3: 101 現金 | B3: 1月1日 | C3: 現金を事業主へ戻し | F3: 1046520 | G3: 0
A4: 103 普通預金 | B4: 1月1日 | C4: 前年繰越 普通預金 | E4: 10475394 | G4: 10475394
A5: 103 普通預金 | B5: 1月1日 | C5: 普通預金を事業主へ戻し | F5: 10475394 | G5: 0
A6: 107 売掛金 | B6: 1月1日 | C6: 前年繰越 売掛金 | E6: 1370500 | G6: 1370500
A7: 107 売掛金 | B7: 1月15日 | C7: セレサ川崎 ユーユー入金 | F7: 100000 | G7: 1270500
A8: 107 売掛金 | B8: 1月30日 | C8: セレサ川崎 BASIS入金 | F8: 1237500 | G8: 33000
A9: 107 売掛金 | B9: 1月31日 | C9: 売上 小樽商科大学後援会 | D9: 売上(報酬） | E9: 11000 | G9: 44000
A10: 107 売掛金 | B10: 1月31日 | C10: 売上 ユーユー | D10: 売上(報酬） | E10: 100000 | G10: 144000
A11: 107 売掛金 | B11: 2月13日 | C11: セレサ川崎 ユーユー入金 | F11: 100000 | G11: 44000
A12: 107 売掛金 | B12: 2月28日 | C12: 売上 小樽商科大学後援会 | D12: 売上(報酬） | E12: 11000 | G12: 55000
A13: 107 売掛金 | B13: 2月28日 | C13: 売上 ユーユー | D13: 売上(報酬） | E13: 100000 | G13: 155000
A14: 107 売掛金 | B14: 2月28日 | C14: 売上BASIS | D14: 売上(報酬） | E14: 770000 | G14: 925000
A15: 114 リサイクル預託金 | B15: 1月1日 | C15: 前年繰越 リサイクル預託金 | E15: 9130 | G15: 9130
A16: 114 リサイクル預託金 | B16: 1月17日 | C16: リサイクル預託金 | F16: 9130 | G16: 0
A17: 114 リサイクル預託金 | B17: 1月17日 | C17: シエンタのリサイクル預託金 | E17: 11650 | G17: 11650
A18: 121 建物 | B18: 1月1日 | C18: 前年繰越 建物 | E18: 14597430 | G18: 14597430
A19: 124 車両運搬具 | B19: 1月1日 | C19: 前年繰越 車両運搬具 | E19: 1 | G19: 1
A20: 124 車両運搬具 | B20: 1月17日 | C20: デミオを売却 | F20: 1 | G20: 0
A21: 124 車両運搬具 | B21: 1月17日 | C21: シエンタ(車両)購入 | E21: 3057480 | G21: 3057480
A22: 127 構築物 | B22: 1月1日 | C22: 前年繰越 構築物 | E22: 1303020 | G22: 1303020
A23: 204 未払金 | B23: 1月1日 | C23: 前年繰越 未払金 | F23: 61327 | G23: -61327
A24: 204 未払金 | B24: 1月1日 | C24: 振り戻し 未払金 | E24: 61327 | G24: 0
A25: 302 元入金 | B25: 1月1日 | C25: 前年繰越 元入金 | F25: 25846530 | G25: -25846530
A26: 302 元入金 | B26: 1月1日 | C26: 前年繰越 控除前利益 | F26: 2894138 | G26: -28740668
A27: 401 売上(報酬） | B27: 1月31日 | C27: 売上 小樽商科大学後援会 | D27: 売掛金 | F27: 11000 | G27: -11000
A28: 401 売上(報酬） | B28: 1月31日 | C28: 売上 ユーユー | D28: 売掛金 | F28: 100000 | G28: -111000
A29: 401 売上(報酬） | B29: 2月28日 | C29: 売上 小樽商科大学後援会 | D29: 売掛金 | F29: 11000 | G29: -122000
A30: 401 売上(報酬） | B30: 2月28日 | C30: 売上 ユーユー | D30: 売掛金 | F30: 100000 | G30: -222000
A31: 401 売上(報酬） | B31: 2月28日 | C31: 売上BASIS | D31: 売掛金 | F31: 770000 | G31: -992000
A32: 403 雑収入(車両売却) | B32: 1月17日 | C32: 固定資産売却益 | F32: 329999 | G32: -329999
A33: 507 水道光熱費 | B33: 1月28日 | C33: エポス 東京ガス | E33: 10715 | G33: 10715
A34: 507 水道光熱費 | B34: 2月3日 | C34: エポス 水道料金 | E34: 2618 | G34: 13333
A35: 507 水道光熱費 | B35: 3月5日 | C35: 2月分 電気料金 | E35: 10343 | G35: 23676
A36: 511 接待交際費 | B36: 2月14日 | C36: ニャーベトナム交際費 | E36: 8500 | G36: 8500
A37: 511 接待交際費 | B37: 2月22日 | C37: BigBoy交際費 | E37: 7854 | G37: 16354
A38: 514 消耗品費 | B38: 1月21日 | C38: Bluetooth 5.4 対応 USB | E38: 1190 | G38: 1190
A39: 514 消耗品費 | B39: 2月18日 | C39: M.2 NVMe SSD 外付けケース | E39: 1602 | G39: 2792
A40: 514 消耗品費 | B40: 2月24日 | C40: ScanSnap購入 | E40: 31800 | G40: 34592
A41: 514 消耗品費 | B41: 3月2日 | C41: トラスコ中山(TRUSCO) オリコン 薄型軽量折りたたみコンテナ 透明 50L 超軽量 | E41: 960 | G41: 35552
A42: 514 消耗品費 | B42: 3月6日 | C42: やよいの青色申告 26 通常版＜令和7年分確定申告対応＞ | E42: 13409 | G42: 48961
A43: 520 地代家賃 | B43: 1月5日 | C43: 中尾洋一へ地代振込 | E43: 20000 | G43: 20000
A44: 520 地代家賃 | B44: 2月2日 | C44: 中尾洋一へ地代振込 | E44: 20000 | G44: 40000
... A87: 525 リース・賃借料 | B87: 2月29日 | C87: エポス さくらインターネット | E87: 3220 | G87: 20203
